Workbook

Sheet All Exposure Types
A1: Mean Heat Exposure Scores by ACS SOC Grouping | I1: Score Key
A2: ACS Occupation | B2: SOC 2-Digit | C2: Indoors, Uncontrolled | D2: Outdoors, Exposed | E2: Outdoors, Under Cover | F2: Very Hot or Very Cold | I2: Value | J2: Meaning
A3: =_xlfn.XLOOKUP('ACS-NAICS-SOC x-walk'!D2,'ACS-NAICS-SOC x-walk'!D:D,'ACS-NAICS-SOC x-walk'!D:D) -> Management, business, science, and arts occupations | B3: =_xlfn.XLOOKUP(A3,'ACS-NAICS-SOC x-walk'!D:D,'ACS-NAICS-SOC x-walk'!B:B) -> 11 | C3: =_xlfn.XLOOKUP(A3, 'Indoors, uncontrolled'!F:F, 'Indoors, uncontrolled'!H:H) -> 22.668161 | D3: =_xlfn.XLOOKUP(A3,'Outdoors, exposed'!F:F,'Outdoors, exposed'!H:H) -> 21.941573 | E3: =_xlfn.XLOOKUP(A3,'Outdoors, under cover'!F:F,'Outdoors, under cover'!H:H) -> 15.185897 | F3: =_xlfn.XLOOKUP(A3,'Very hot or very cold'!F:F,'Very hot or very cold'!H:H) -> 17.474157 | I3: =_xlfn.XLOOKUP('Context Scale'!A1,'Context Scale'!A:A, 'Context Scale'!A:A) -> 100 | J3: =_xlfn.XLOOKUP('Context Scale'!B1,'Context Scale'!B:B, 'Context Scale'!B:B) -> Every Day
A4: =_xlfn.XLOOKUP('ACS-NAICS-SOC x-walk'!D248,'ACS-NAICS-SOC x-walk'!D248,'ACS-NAICS-SOC x-walk'!D248) -> Service occupations | B4: =_xlfn.XLOOKUP(A4,'ACS-NAICS-SOC x-walk'!D:D,'ACS-NAICS-SOC x-walk'!B:B) -> 31 | C4: =_xlfn.XLOOKUP(A4, 'Indoors, uncontrolled'!F:F, 'Indoors, uncontrolled'!H:H) -> 27.072165 | D4: =_xlfn.XLOOKUP(A4,'Outdoors, exposed'!F:F,'Outdoors, exposed'!H:H) -> 38.360825 | E4: =_xlfn.XLOOKUP(A4,'Outdoors, under cover'!F:F,'Outdoors, under cover'!H:H) -> 23.753086 | F4: =_xlfn.XLOOKUP(A4,'Very hot or very cold'!F:F,'Very hot or very cold'!H:H) -> 34.195876 | I4: =_xlfn.XLOOKUP('Context Scale'!A2,'Context Scale'!A:A, 'Context Scale'!A:A) -> 75 | J4: =_xlfn.XLOOKUP('Context Scale'!B2,'Context Scale'!B:B, 'Context Scale'!B:B) -> Once a week or more, but not every day
A5: =_xlfn.XLOOKUP('ACS-NAICS-SOC x-walk'!D261,'ACS-NAICS-SOC x-walk'!D261,'ACS-NAICS-SOC x-walk'!D261) -> Natural resources, construction, and maintenance occupations | B5: =_xlfn.XLOOKUP(A5,'ACS-NAICS-SOC x-walk'!D:D,'ACS-NAICS-SOC x-walk'!B:B) -> 45 | C5: =_xlfn.XLOOKUP(A5, 'Indoors, uncontrolled'!F:F, 'Indoors, uncontrolled'!H:H) -> 59.666667 | D5: =_xlfn.XLOOKUP(A5,'Outdoors, exposed'!F:F,'Outdoors, exposed'!H:H) -> 71.04065 | E5: =_xlfn.XLOOKUP(A5,'Outdoors, under cover'!F:F,'Outdoors, under cover'!H:H) -> 41.276423 | F5: =_xlfn.XLOOKUP(A5,'Very hot or very cold'!F:F,'Very hot or very cold'!H:H) -> 65.390244 | I5: =_xlfn.XLOOKUP('Context Scale'!A3,'Context Scale'!A:A, 'Context Scale'!A:A) -> 50 | J5: =_xlfn.XLOOKUP('Context Scale'!B3,'Context Scale'!B:B, 'Context Scale'!B:B) -> Once a month or more, but not every week
A6: =_xlfn.XLOOKUP('ACS-NAICS-SOC x-walk'!D318,'ACS-NAICS-SOC x-walk'!D318,'ACS-NAICS-SOC x-walk'!D318) -> Production, transportation, and material moving occupations | B6: =_xlfn.XLOOKUP(A6,'ACS-NAICS-SOC x-walk'!D:D,'ACS-NAICS-SOC x-walk'!B:B) -> 51 | C6: =_xlfn.XLOOKUP(A6, 'Indoors, uncontrolled'!F:F, 'Indoors, uncontrolled'!H:H) -> 51.458065 | D6: =_xlfn.XLOOKUP(A6,'Outdoors, exposed'!F:F,'Outdoors, exposed'!H:H) -> 37.429487 | E6: =_xlfn.XLOOKUP(A6,'Outdoors, under cover'!F:F,'Outdoors, under cover'!H:H) -> 22.262821 | F6: =_xlfn.XLOOKUP(A6,'Very hot or very cold'!F:F,'Very hot or very cold'!H:H) -> 53.564103 | I6: =_xlfn.XLOOKUP('Context Scale'!A4,'Context Scale'!A:A, 'Context Scale'!A:A) -> 25 | J6: =_xlfn.XLOOKUP('Context Scale'!B4,'Context Scale'!B:B, 'Context Scale'!B:B) -> Once a year or more, but not every month
A7: =_xlfn.XLOOKUP('ACS-NAICS-SOC x-walk'!D322,'ACS-NAICS-SOC x-walk'!D322,'ACS-NAICS-SOC x-walk'!D322) -> Management, business, science, and arts occupations | B7: =_xlfn.XLOOKUP(A7,'ACS-NAICS-SOC x-walk'!D:D,'ACS-NAICS-SOC x-walk'!B:B) -> 11 | C7: =_xlfn.XLOOKUP(A7, 'Indoors, uncontrolled'!F:F, 'Indoors, uncontrolled'!H:H) -> 22.668161 | D7: =_xlfn.XLOOKUP(A7,'Outdoors, exposed'!F:F,'Outdoors, exposed'!H:H) -> 21.941573 | E7: =_xlfn.XLOOKUP(A7,'Outdoors, under cover'!F:F,'Outdoors, under cover'!H:H) -> 15.185897 | F7: =_xlfn.XLOOKUP(A7,'Very hot or very cold'!F:F,'Very hot or very cold'!H:H) -> 17.474157 | I7: =_xlfn.XLOOKUP('Context Scale'!A5,'Context Scale'!A:A, 'Context Scale'!A:A) -> 0 | J7: =_xlfn.XLOOKUP('Context Scale'!B5,'Context Scale'!B:B, 'Context Scale'!B:B) -> Never
A8: =_xlfn.XLOOKUP('ACS-NAICS-SOC x-walk'!D826,'ACS-NAICS-SOC x-walk'!D826,'ACS-NAICS-SOC x-walk'!D826) -> Sales and office occupations | B8: =_xlfn.XLOOKUP(A8,'ACS-NAICS-SOC x-walk'!D:D,'ACS-NAICS-SOC x-walk'!B:B) -> 43 | C8: =_xlfn.XLOOKUP(A8, 'Indoors, uncontrolled'!F:F, 'Indoors, uncontrolled'!H:H) -> 16.305556 | D8: =_xlfn.XLOOKUP(A8,'Outdoors, exposed'!F:F,'Outdoors, exposed'!H:H) -> 18.430556 | E8: =_xlfn.XLOOKUP(A8,'Outdoors, under cover'!F:F,'Outdoors, under cover'!H:H) -> 5.0980392 | F8: =_xlfn.XLOOKUP(A8,'Very hot or very cold'!F:F,'Very hot or very cold'!H:H) -> 17.152778
A12: Mean Heat Exposure Scores by ACS Industry Grouping
A13: ACS Industry | B13: NAICS 2-Digit | C13: Indoors, Uncontrolled | D13: Outdoors, Exposed | E13: Outdoors, Under Cover | F13: Very Hot or Very Cold
A14: =_xlfn.XLOOKUP('ACS-NAICS-SOC x-walk'!L2,'ACS-NAICS-SOC x-walk'!L2,'ACS-NAICS-SOC x-walk'!L2) -> Agriculture, Forestry, Fishing and Hunting, and Mining | B14: =_xlfn.XLOOKUP(A14,'ACS-NAICS-SOC x-walk'!L:L,'ACS-NAICS-SOC x-walk'!J:J) -> 11 | C14: =_xlfn.XLOOKUP(A14,'Indoors, uncontrolled'!J:J,'Indoors, uncontrolled'!M:M) -> 48.483871 | D14: =_xlfn.XLOOKUP(A14,'Outdoors, exposed'!J:J,'Outdoors, exposed'!M:M) -> 55.946237 | E14: =_xlfn.XLOOKUP(A14,'Outdoors, under cover'!J:J,'Outdoors, under cover'!M:M) -> 34.5 | F14: =_xlfn.XLOOKUP($A14,'Indoors, uncontrolled'!$J:$J,'Indoors, uncontrolled'!$M:$M) -> 48.483871
A15: =_xlfn.XLOOKUP('ACS-NAICS-SOC x-walk'!L3,'ACS-NAICS-SOC x-walk'!L3,'ACS-NAICS-SOC x-walk'!L3) -> Agriculture, Forestry, Fishing and Hunting, and Mining | B15: =_xlfn.XLOOKUP(A15,'ACS-NAICS-SOC x-walk'!L:L,'ACS-NAICS-SOC x-walk'!J:J) -> 11 | C15: =_xlfn.XLOOKUP(A15,'Indoors, uncontrolled'!J:J,'Indoors, uncontrolled'!M:M) -> 48.483871 | D15: =_xlfn.XLOOKUP(A15,'Outdoors, exposed'!J:J,'Outdoors, exposed'!M:M) -> 55.946237 | E15: =_xlfn.XLOOKUP(A15,'Outdoors, under cover'!J:J,'Outdoors, under cover'!M:M) -> 34.5 | F15: =_xlfn.XLOOKUP($A15,'Indoors, uncontrolled'!$J:$J,'Indoors, uncontrolled'!$M:$M) -> 48.483871
A16: =_xlfn.XLOOKUP('ACS-NAICS-SOC x-walk'!L4,'ACS-NAICS-SOC x-walk'!L4,'ACS-NAICS-SOC x-walk'!L4) -> Transportation and Warehousing, and Utilities | B16: =_xlfn.XLOOKUP(A16,'ACS-NAICS-SOC x-walk'!L:L,'ACS-NAICS-SOC x-walk'!J:J) -> 22 | C16: =_xlfn.XLOOKUP(A16,'Indoors, uncontrolled'!J:J,'Indoors, uncontrolled'!M:M) -> #N/A | D16: =_xlfn.XLOOKUP(A16,'Outdoors, exposed'!J:J,'Outdoors, exposed'!M:M) -> #N/A | E16: =_xlfn.XLOOKUP(A16,'Outdoors, under cover'!J:J,'Outdoors, under cover'!M:M) -> #N/A | F16: =_xlfn.XLOOKUP($A16,'Indoors, uncontrolled'!$J:$J,'Indoors, uncontrolled'!$M:$M) -> #N/A
A17: =_xlfn.XLOOKUP('ACS-NAICS-SOC x-walk'!L5,'ACS-NAICS-SOC x-walk'!L5,'ACS-NAICS-SOC x-walk'!L5) -> Construction | B17: =_xlfn.XLOOKUP(A17,'ACS-NAICS-SOC x-walk'!L:L,'ACS-NAICS-SOC x-walk'!J:J) -> 23 | C17: =_xlfn.XLOOKUP(A17,'Indoors, uncontrolled'!J:J,'Indoors, uncontrolled'!M:M) -> 57.934211 | D17: =_xlfn.XLOOKUP(A17,'Outdoors, exposed'!J:J,'Outdoors, exposed'!M:M) -> 61.434211 | E17: =_xlfn.XLOOKUP(A17,'Outdoors, under cover'!J:J,'Outdoors, under cover'!M:M) -> 38.146667 | F17: =_xlfn.XLOOKUP($A17,'Indoors, uncontrolled'!$J:$J,'Indoors, uncontrolled'!$M:$M) -> 57.934211
A18: =_xlfn.XLOOKUP('ACS-NAICS-SOC x-walk'!L6,'ACS-NAICS-SOC x-walk'!L6,'ACS-NAICS-SOC x-walk'!L6) -> Wholesale Trade | B18: =_xlfn.XLOOKUP(A18,'ACS-NAICS-SOC x-walk'!L:L,'ACS-NAICS-SOC x-walk'!J:J) -> 42 | C18: =_xlfn.XLOOKUP(A18,'Indoors, uncontrolled'!J:J,'Indoors, uncontrolled'!M:M) -> 53.857143 | D18: =_xlfn.XLOOKUP(A18,'Outdoors, exposed'!J:J,'Outdoors, exposed'!M:M) -> 61.704225 | E18: =_xlfn.XLOOKUP(A18,'Outdoors, under cover'!J:J,'Outdoors, under cover'!M:M) -> 35.235294 | F18: =_xlfn.XLOOKUP($A18,'Indoors, uncontrolled'!$J:$J,'Indoors, uncontrolled'!$M:$M) -> 53.857143
A19: =_xlfn.XLOOKUP('ACS-NAICS-SOC x-walk'!L7,'ACS-NAICS-SOC x-walk'!L7,'ACS-NAICS-SOC x-walk'!L7) -> Information | B19: =_xlfn.XLOOKUP(A19,'ACS-NAICS-SOC x-walk'!L:L,'ACS-NAICS-SOC x-walk'!J:J) -> 51 | C19: =_xlfn.XLOOKUP(A19,'Indoors, uncontrolled'!J:J,'Indoors, uncontrolled'!M:M) -> 11.518519 | D19: =_xlfn.XLOOKUP(A19,'Outdoors, exposed'!J:J,'Outdoors, exposed'!M:M) -> 7.962963 | E19: =_xlfn.XLOOKUP(A19,'Outdoors, under cover'!J:J,'Outdoors, under cover'!M:M) -> 6.8076923 | F19: =_xlfn.XLOOKUP($A19,'Indoors, uncontrolled'!$J:$J,'Indoors, uncontrolled'!$M:$M) -> 11.518519
A20: =_xlfn.XLOOKUP('ACS-NAICS-SOC x-walk'!L8,'ACS-NAICS-SOC x-walk'!L8,'ACS-NAICS-SOC x-walk'!L8) -> Finance and Insurance, and Real Estate, and Rental and Leasing | B20: =_xlfn.XLOOKUP(A20,'ACS-NAICS-SOC x-walk'!L:L,'ACS-NAICS-SOC x-walk'!J:J) -> 52 | C20: =_xlfn.XLOOKUP(A20,'Indoors, uncontrolled'!J:J,'Indoors, uncontrolled'!M:M) -> 11.96875 | D20: =_xlfn.XLOOKUP(A20,'Outdoors, exposed'!J:J,'Outdoors, exposed'!M:M) -> 14.75 | E20: =_xlfn.XLOOKUP(A20,'Outdoors, under cover'!J:J,'Outdoors, under cover'!M:M) -> 7.4333333 | F20: =_xlfn.XLOOKUP($A20,'Indoors, uncontrolled'!$J:$J,'Indoors, uncontrolled'!$M:$M) -> 11.96875
A21: =_xlfn.XLOOKUP('ACS-NAICS-SOC x-walk'!L9,'ACS-NAICS-SOC x-walk'!L9,'ACS-NAICS-SOC x-walk'!L9) -> Finance and Insurance, and Real Estate, and Rental and Leasing | B21: =_xlfn.XLOOKUP(A21,'ACS-NAICS-SOC x-walk'!L:L,'ACS-NAICS-SOC x-walk'!J:J) -> 52 | C21: =_xlfn.XLOOKUP(A21,'Indoors, uncontrolled'!J:J,'Indoors, uncontrolled'!M:M) -> 11.96875 | D21: =_xlfn.XLOOKUP(A21,'Outdoors, exposed'!J:J,'Outdoors, exposed'!M:M) -> 14.75 | E21: =_xlfn.XLOOKUP(A21,'Outdoors, under cover'!J:J,'Outdoors, under cover'!M:M) -> 7.4333333 | F21: =_xlfn.XLOOKUP($A21,'Indoors, uncontrolled'!$J:$J,'Indoors, uncontrolled'!$M:$M) -> 11.96875
A22: =_xlfn.XLOOKUP('ACS-NAICS-SOC x-walk'!L10,'ACS-NAICS-SOC x-walk'!L10,'ACS-NAICS-SOC x-walk'!L10) -> Professional, Scientific, and Management, and Administrative, and Waste Management Services | B22: =_xlfn.XLOOKUP(A22,'ACS-NAICS-SOC x-walk'!L:L,'ACS-NAICS-SOC x-walk'!J:J) -> 54 | C22: =_xlfn.XLOOKUP(A22,'Indoors, uncontrolled'!J:J,'Indoors, uncontrolled'!M:M) -> 28.163636 | D22: =_xlfn.XLOOKUP(A22,'Outdoors, exposed'!J:J,'Outdoors, exposed'!M:M) -> 37.072727 | E22: =_xlfn.XLOOKUP(A22,'Outdoors, under cover'!J:J,'Outdoors, under cover'!M:M) -> 19.346154 | F22: =_xlfn.XLOOKUP($A22,'Indoors, uncontrolled'!$J:$J,'Indoors, uncontrolled'!$M:$M) -> 28.163636
A23: =_xlfn.XLOOKUP('ACS-NAICS-SOC x-walk'!L11,'ACS-NAICS-SOC x-walk'!L11,'ACS-NAICS-SOC x-walk'!L11) -> Professional, Scientific, and Management, and Administrative, and Waste Management Services | B23: =_xlfn.XLOOKUP(A23,'ACS-NAICS-SOC x-walk'!L:L,'ACS-NAICS-SOC x-walk'!J:J) -> 54 | C23: =_xlfn.XLOOKUP(A23,'Indoors, uncontrolled'!J:J,'Indoors, uncontrolled'!M:M) -> 28.163636 | D23: =_xlfn.XLOOKUP(A23,'Outdoors, exposed'!J:J,'Outdoors, exposed'!M:M) -> 37.072727 | E23: =_xlfn.XLOOKUP(A23,'Outdoors, under cover'!J:J,'Outdoors, under cover'!M:M) -> 19.346154 | F23: =_xlfn.XLOOKUP($A23,'Indoors, uncontrolled'!$J:$J,'Indoors, uncontrolled'!$M:$M) -> 28.163636
A24: =_xlfn.XLOOKUP('ACS-NAICS-SOC x-walk'!L12,'ACS-NAICS-SOC x-walk'!L12,'ACS-NAICS-SOC x-walk'!L12) -> Professional, Scientific, and Management, and Administrative, and Waste Management Services | B24: =_xlfn.XLOOKUP(A24,'ACS-NAICS-SOC x-walk'!L:L,'ACS-NAICS-SOC x-walk'!J:J) -> 54 | C24: =_xlfn.XLOOKUP(A24,'Indoors, uncontrolled'!J:J,'Indoors, uncontrolled'!M:M) -> 28.163636 | D24: =_xlfn.XLOOKUP(A24,'Outdoors, exposed'!J:J,'Outdoors, exposed'!M:M) -> 37.072727 | E24: =_xlfn.XLOOKUP(A24,'Outdoors, under cover'!J:J,'Outdoors, under cover'!M:M) -> 19.346154 | F24: =_xlfn.XLOOKUP($A24,'Indoors, uncontrolled'!$J:$J,'Indoors, uncontrolled'!$M:$M) -> 28.163636
A25: =_xlfn.XLOOKUP('ACS-NAICS-SOC x-walk'!L13,'ACS-NAICS-SOC x-walk'!L13,'ACS-NAICS-SOC x-walk'!L13) -> Professional, Scientific, and Management, and Administrative, and Waste Management Services | B25: =_xlfn.XLOOKUP(A25,'ACS-NAICS-SOC x-walk'!L:L,'ACS-NAICS-SOC x-walk'!J:J) -> 54 | C25: =_xlfn.XLOOKUP(A25,'Indoors, uncontrolled'!J:J,'Indoors, uncontrolled'!M:M) -> 28.163636 | D25: =_xlfn.XLOOKUP(A25,'Outdoors, exposed'!J:J,'Outdoors, exposed'!M:M) -> 37.072727 | E25: =_xlfn.XLOOKUP(A25,'Outdoors, under cover'!J:J,'Outdoors, under cover'!M:M) -> 19.346154 | F25: =_xlfn.XLOOKUP($A25,'Indoors, uncontrolled'!$J:$J,'Indoors, uncontrolled'!$M:$M) -> 28.163636
... A28: =_xlfn.XLOOKUP('ACS-NAICS-SOC x-walk'!L16,'ACS-NAICS-SOC x-walk'!L16,'ACS-NAICS-SOC x-walk'!L16) -> Arts, Entertainment, and Recreation, and Accommodation and Food Services, and Retail Trade | B28: =_xlfn.XLOOKUP(A28,'ACS-NAICS-SOC x-walk'!L:L,'ACS-NAICS-SOC x-walk'!J:J) -> 71 | C28: =_xlfn.XLOOKUP(A28,'Indoors, uncontrolled'!J:J,'Indoors, uncontrolled'!M:M) -> 22.883721 | D28: =_xlfn.XLOOKUP(A28,'Outdoors, exposed'!J:J,'Outdoors, exposed'!M:M) -> 28.418605 | E28: =_xlfn.XLOOKUP(A28,'Outdoors, under cover'!J:J,'Outdoors, under cover'!M:M) -> 15.820513 | F28: =_xlfn.XLOOKUP($A28,'Indoors, uncontrolled'!$J:$J,'Indoors, uncontrolled'!$M:$M) -> 22.883721
A29: Manufacturing | B29: 31 | C29: =_xlfn.XLOOKUP(A29,'Indoors, uncontrolled'!J:J,'Indoors, uncontrolled'!M:M) -> 49.539823 | D29: =_xlfn.XLOOKUP(A29,'Outdoors, exposed'!J:J,'Outdoors, exposed'!M:M) -> 22.699115 | E29: =_xlfn.XLOOKUP(A29,'Outdoors, under cover'!J:J,'Outdoors, under cover'!M:M) -> 14.71028 | F29: =_xlfn.XLOOKUP($A29,'Indoors, uncontrolled'!$J:$J,'Indoors, uncontrolled'!$M:$M) -> 49.539823
A30: Manufacturing | B30: 32 | C30: =_xlfn.XLOOKUP(A30,'Indoors, uncontrolled'!J:J,'Indoors, uncontrolled'!M:M) -> 49.539823 | D30: =_xlfn.XLOOKUP(A30,'Outdoors, exposed'!J:J,'Outdoors, exposed'!M:M) -> 22.699115 | E30: =_xlfn.XLOOKUP(A30,'Outdoors, under cover'!J:J,'Outdoors, under cover'!M:M) -> 14.71028 | F30: =_xlfn.XLOOKUP($A30,'Indoors, uncontrolled'!$J:$J,'Indoors, uncontrolled'!$M:$M) -> 49.539823
A31: Manufacturing | B31: 33 | C31: =_xlfn.XLOOKUP(A31,'Indoors, uncontrolled'!J:J,'Indoors, uncontrolled'!M:M) -> 49.539823 | D31: =_xlfn.XLOOKUP(A31,'Outdoors, exposed'!J:J,'Outdoors, exposed'!M:M) -> 22.699115 | E31: =_xlfn.XLOOKUP(A31,'Outdoors, under cover'!J:J,'Outdoors, under cover'!M:M) -> 14.71028 | F31: =_xlfn.XLOOKUP($A31,'Indoors, uncontrolled'!$J:$J,'Indoors, uncontrolled'!$M:$M) -> 49.539823

Sheet Indoors, uncontrolled
A1: Browse by Work Context
A2: Indoors, Not Environmentally Controlled
A4: Context | B4: Job Zone | C4: SOC Occupation Code | D4: SOC 2-Digit Code | E4: SOC 6-Digit Description | F4: ACS Occupation Description | G4: Aggregate ACS Occupation Context Score | H4: ACS Occupation Category Mean Context Score | I4: NAICS Code | J4: ACS Industry Description | K4: NAICS Description | L4: Aggregate Industry Context Score | M4: ACS Industry Category Mean Context Score
A5: 47 | B5: 3 | C5: 47-1011 | D5: =VALUE(LEFT(C5,2)) -> 47 | E5: First-Line Supervisors of Construction Trades and Extraction Workers | F5: {=_xlfn.IFS( AND(D5>=11, D5<=29), "Management, business, science, and arts occupations", AND(D5>=31, D5<=39), "Service occupations", AND(D5>=41, D5<=43), "Sales and office occupations", AND(D5>=51, D5<=53), "Production, transportation, and material moving occupations", AND(D5>=45, D5<=49), "Natural resources, construction, and maintenance occupations", TRUE, "Not applicable to study area" )} -> Natural resources, construction, and maintenance occupations | G5: =SUMIF(F:F, F5, A:A) -> 7339 | H5: =AVERAGEIF(F:F, F5, A:A) -> 59.666667 | I5: =_xlfn.XLOOKUP($C5,'NAICS-SOC-CIP x-walk'!C:C, 'NAICS-SOC-CIP x-walk'!H:H) -> 21, 22 | J5: =_xlfn.XLOOKUP(K5,'ACS-NAICS-SOC x-walk'!K:K,'ACS-NAICS-SOC x-walk'!L:L) -> Agriculture, Forestry, Fishing and Hunting, and Mining | K5: =_xlfn.XLOOKUP($C5,'NAICS-SOC-CIP x-walk'!$C:$C, 'NAICS-SOC-CIP x-walk'!I:I) -> Mining, Quarrying, and Oil and Gas Extraction, Utilities | L5: =SUMIF(K:K, K5, A:A) -> 4509 | M5: =AVERAGEIF(K:K, K5, A:A) -> 48.483871
A6: 61 | B6: 3 | C6: 47-1011 | D6: =VALUE(LEFT(C6,2)) -> 47 | E6: Solar Energy Installation Managers | F6: {=_xlfn.IFS( AND(D6>=11, D6<=29), "Management, business, science, and arts occupations", AND(D6>=31, D6<=39), "Service occupations", AND(D6>=41, D6<=43), "Sales and office occupations", AND(D6>=51, D6<=53), "Production, transportation, and material moving occupations", AND(D6>=45, D6<=49), "Natural resources, construction, and maintenance occupations", TRUE, "Not applicable to study area" )} -> Natural resources, construction, and maintenance occupations | G6: =SUMIF(F:F, F6, A:A) -> 7339 | H6: =AVERAGEIF(F:F, F6, A:A) -> 59.666667 | I6: =_xlfn.XLOOKUP($C6,'NAICS-SOC-CIP x-walk'!C:C, 'NAICS-SOC-CIP x-walk'!H:H) -> 21, 22 | J6: =_xlfn.XLOOKUP(K6,'ACS-NAICS-SOC x-walk'!K:K,'ACS-NAICS-SOC x-walk'!L:L) -> Agriculture, Forestry, Fishing and Hunting, and Mining | K6: =_xlfn.XLOOKUP($C6,'NAICS-SOC-CIP x-walk'!$C:$C, 'NAICS-SOC-CIP x-walk'!I:I) -> Mining, Quarrying, and Oil and Gas Extraction, Utilities | L6: =SUMIF(K:K, K6, A:A) -> 4509 | M6: =AVERAGEIF(K:K, K6, A:A) -> 48.483871
A7: 73 | B7: 1-2 | C7: 47-2011 | D7: =VALUE(LEFT(C7,2)) -> 47 | E7: Boilermakers | F7: {=_xlfn.IFS( AND(D7>=11, D7<=29), "Management, business, science, and arts occupations", AND(D7>=31, D7<=39), "Service occupations", AND(D7>=41, D7<=43), "Sales and office occupations", AND(D7>=51, D7<=53), "Production, transportation, and material moving occupations", AND(D7>=45, D7<=49), "Natural resources, construction, and maintenance occupations", TRUE, "Not applicable to study area" )} -> Natural resources, construction, and maintenance occupations | G7: =SUMIF(F:F, F7, A:A) -> 7339 | H7: =AVERAGEIF(F:F, F7, A:A) -> 59.666667 | I7: =_xlfn.XLOOKUP($C7,'NAICS-SOC-CIP x-walk'!C:C, 'NAICS-SOC-CIP x-walk'!H:H) -> 23 | J7: =_xlfn.XLOOKUP(K7,'ACS-NAICS-SOC x-walk'!K:K,'ACS-NAICS-SOC x-walk'!L:L) -> Construction | K7: =_xlfn.XLOOKUP($C7,'NAICS-SOC-CIP x-walk'!$C:$C, 'NAICS-SOC-CIP x-walk'!I:I) -> Construction | L7: =SUMIF(K:K, K7, A:A) -> 4403 | M7: =AVERAGEIF(K:K, K7, A:A) -> 57.934211
A8: 74 | B8: 1-2 | C8: 47-2021 | D8: =VALUE(LEFT(C8,2)) -> 47 | E8: Brickmasons and Blockmasons | F8: {=_xlfn.IFS( AND(D8>=11, D8<=29), "Management, business, science, and arts occupations", AND(D8>=31, D8<=39), "Service occupations", AND(D8>=41, D8<=43), "Sales and office occupations", AND(D8>=51, D8<=53), "Production, transportation, and material moving occupations", AND(D8>=45, D8<=49), "Natural resources, construction, and maintenance occupations", TRUE, "Not applicable to study area" )} -> Natural resources, construction, and maintenance occupations | G8: =SUMIF(F:F, F8, A:A) -> 7339 | H8: =AVERAGEIF(F:F, F8, A:A) -> 59.666667 | I8: =_xlfn.XLOOKUP($C8,'NAICS-SOC-CIP x-walk'!C:C, 'NAICS-SOC-CIP x-walk'!H:H) -> 23 | J8: =_xlfn.XLOOKUP(K8,'ACS-NAICS-SOC x-walk'!K:K,'ACS-NAICS-SOC x-walk'!L:L) -> Construction | K8: =_xlfn.XLOOKUP($C8,'NAICS-SOC-CIP x-walk'!$C:$C, 'NAICS-SOC-CIP x-walk'!I:I) -> Construction | L8: =SUMIF(K:K, K8, A:A) -> 4403 | M8: =AVERAGEIF(K:K, K8, A:A) -> 57.934211
A9: 29 | B9: 1-2 | C9: 47-2022 | D9: =VALUE(LEFT(C9,2)) -> 47 | E9: Stonemasons | F9: {=_xlfn.IFS( AND(D9>=11, D9<=29), "Management, business, science, and arts occupations", AND(D9>=31, D9<=39), "Service occupations", AND(D9>=41, D9<=43), "Sales and office occupations", AND(D9>=51, D9<=53), "Production, transportation, and material moving occupations", AND(D9>=45, D9<=49), "Natural resources, construction, and maintenance occupations", TRUE, "Not applicable to study area" )} -> Natural resources, construction, and maintenance occupations | G9: =SUMIF(F:F, F9, A:A) -> 7339 | H9: =AVERAGEIF(F:F, F9, A:A) -> 59.666667 | I9: =_xlfn.XLOOKUP($C9,'NAICS-SOC-CIP x-walk'!C:C, 'NAICS-SOC-CIP x-walk'!H:H) -> 23 | J9: =_xlfn.XLOOKUP(K9,'ACS-NAICS-SOC x-walk'!K:K,'ACS-NAICS-SOC x-walk'!L:L) -> Construction | K9: =_xlfn.XLOOKUP($C9,'NAICS-SOC-CIP x-walk'!$C:$C, 'NAICS-SOC-CIP x-walk'!I:I) -> Construction | L9: =SUMIF(K:K, K9, A:A) -> 4403 | M9: =AVERAGEIF(K:K, K9, A:A) -> 57.934211
A10: 43 | B10: 1-2 | C10: 47-2031 | D10: =VALUE(LEFT(C10,2)) -> 47 | E10: Carpenters | F10: {=_xlfn.IFS( AND(D10>=11, D10<=29), "Management, business, science, and arts occupations", AND(D10>=31, D10<=39), "Service occupations", AND(D10>=41, D10<=43), "Sales and office occupations", AND(D10>=51, D10<=53), "Production, transportation, and material moving occupations", AND(D10>=45, D10<=49), "Natural resources, construction, and maintenance occupations", TRUE, "Not applicable to study area" )} -> Natural resources, construction, and maintenance occupations | G10: =SUMIF(F:F, F10, A:A) -> 7339 | H10: =AVERAGEIF(F:F, F10, A:A) -> 59.666667 | I10: =_xlfn.XLOOKUP($C10,'NAICS-SOC-CIP x-walk'!C:C, 'NAICS-SOC-CIP x-walk'!H:H) -> 23 | J10: =_xlfn.XLOOKUP(K10,'ACS-NAICS-SOC x-walk'!K:K,'ACS-NAICS-SOC x-walk'!L:L) -> Construction | K10: =_xlfn.XLOOKUP($C10,'NAICS-SOC-CIP x-walk'!$C:$C, 'NAICS-SOC-CIP x-walk'!I:I) -> Construction | L10: =SUMIF(K:K, K10, A:A) -> 4403 | M10: =AVERAGEIF(K:K, K10, A:A) -> 57.934211
A11: 42 | B11: 1-2 | C11: 47-2041 | D11: =VALUE(LEFT(C11,2)) -> 47 | E11: Carpet Installers | F11: {=_xlfn.IFS( AND(D11>=11, D11<=29), "Management, business, science, and arts occupations", AND(D11>=31, D11<=39), "Service occupations", AND(D11>=41, D11<=43), "Sales and office occupations", AND(D11>=51, D11<=53), "Production, transportation, and material moving occupations", AND(D11>=45, D11<=49), "Natural resources, construction, and maintenance occupations", TRUE, "Not applicable to study area" )} -> Natural resources, construction, and maintenance occupations | G11: =SUMIF(F:F, F11, A:A) -> 7339 | H11: =AVERAGEIF(F:F, F11, A:A) -> 59.666667 | I11: =_xlfn.XLOOKUP($C11,'NAICS-SOC-CIP x-walk'!C:C, 'NAICS-SOC-CIP x-walk'!H:H) -> 23 | J11: =_xlfn.XLOOKUP(K11,'ACS-NAICS-SOC x-walk'!K:K,'ACS-NAICS-SOC x-walk'!L:L) -> Construction | K11: =_xlfn.XLOOKUP($C11,'NAICS-SOC-CIP x-walk'!$C:$C, 'NAICS-SOC-CIP x-walk'!I:I) -> Construction | L11: =SUMIF(K:K, K11, A:A) -> 4403 | M11: =AVERAGEIF(K:K, K11, A:A) -> 57.934211
A12: 57 | B12: 1-2 | C12: 47-2042 | D12: =VALUE(LEFT(C12,2)) -> 47 | E12: Floor Layers, Except Carpet, Wood, and Hard Tiles | F12: {=_xlfn.IFS( AND(D12>=11, D12<=29), "Management, business, science, and arts occupations", AND(D12>=31, D12<=39), "Service occupations", AND(D12>=41, D12<=43), "Sales and office occupations", AND(D12>=51, D12<=53), "Production, transportation, and material moving occupations", AND(D12>=45, D12<=49), "Natural resources, construction, and maintenance occupations", TRUE, "Not applicable to study area" )} -> Natural resources, construction, and maintenance occupations | G12: =SUMIF(F:F, F12, A:A) -> 7339 | H12: =AVERAGEIF(F:F, F12, A:A) -> 59.666667 | I12: =_xlfn.XLOOKUP($C12,'NAICS-SOC-CIP x-walk'!C:C, 'NAICS-SOC-CIP x-walk'!H:H) -> 23 | J12: =_xlfn.XLOOKUP(K12,'ACS-NAICS-SOC x-walk'!K:K,'ACS-NAICS-SOC x-walk'!L:L) -> Construction | K12: =_xlfn.XLOOKUP($C12,'NAICS-SOC-CIP x-walk'!$C:$C, 'NAICS-SOC-CIP x-walk'!I:I) -> Construction | L12: =SUMIF(K:K, K12, A:A) -> 4403 | M12: =AVERAGEIF(K:K, K12, A:A) -> 57.934211
A13: 44 | B13: 1-2 | C13: 47-2043 | D13: =VALUE(LEFT(C13,2)) -> 47 | E13: Floor Sanders and Finishers | F13: {=_xlfn.IFS( AND(D13>=11, D13<=29), "Management, business, science, and arts occupations", AND(D13>=31, D13<=39), "Service occupations", AND(D13>=41, D13<=43), "Sales and office occupations", AND(D13>=51, D13<=53), "Production, transportation, and material moving occupations", AND(D13>=45, D13<=49), "Natural resources, construction, and maintenance occupations", TRUE, "Not applicable to study area" )} -> Natural resources, construction, and maintenance occupations | G13: =SUMIF(F:F, F13, A:A) -> 7339 | H13: =AVERAGEIF(F:F, F13, A:A) -> 59.666667 | I13: =_xlfn.XLOOKUP($C13,'NAICS-SOC-CIP x-walk'!C:C, 'NAICS-SOC-CIP x-walk'!H:H) -> 23 | J13: =_xlfn.XLOOKUP(K13,'ACS-NAICS-SOC x-walk'!K:K,'ACS-NAICS-SOC x-walk'!L:L) -> Construction | K13: =_xlfn.XLOOKUP($C13,'NAICS-SOC-CIP x-walk'!$C:$C, 'NAICS-SOC-CIP x-walk'!I:I) -> Construction | L13: =SUMIF(K:K, K13, A:A) -> 4403 | M13: =AVERAGEIF(K:K, K13, A:A) -> 57.934211
A14: 47 | B14: 1-2 | C14: 47-2044 | D14: =VALUE(LEFT(C14,2)) -> 47 | E14: Tile and Stone Setters | F14: {=_xlfn.IFS( AND(D14>=11, D14<=29), "Management, business, science, and arts occupations", AND(D14>=31, D14<=39), "Service occupations", AND(D14>=41, D14<=43), "Sales and office occupations", AND(D14>=51, D14<=53), "Production, transportation, and material moving occupations", AND(D14>=45, D14<=49), "Natural resources, construction, and maintenance occupations", TRUE, "Not applicable to study area" )} -> Natural resources, construction, and maintenance occupations | G14: =SUMIF(F:F, F14, A:A) -> 7339 | H14: =AVERAGEIF(F:F, F14, A:A) -> 59.666667 | I14: =_xlfn.XLOOKUP($C14,'NAICS-SOC-CIP x-walk'!C:C, 'NAICS-SOC-CIP x-walk'!H:H) -> 23 | J14: =_xlfn.XLOOKUP(K14,'ACS-NAICS-SOC x-walk'!K:K,'ACS-NAICS-SOC x-walk'!L:L) -> Construction | K14: =_xlfn.XLOOKUP($C14,'NAICS-SOC-CIP x-walk'!$C:$C, 'NAICS-SOC-CIP x-walk'!I:I) -> Construction | L14: =SUMIF(K:K, K14, A:A) -> 4403 | M14: =AVERAGEIF(K:K, K14, A:A) -> 57.934211
A15: 38 | B15: 1-2 | C15: 47-2051 | D15: =VALUE(LEFT(C15,2)) -> 47 | E15: Cement Masons and Concrete Finishers | F15: {=_xlfn.IFS( AND(D15>=11, D15<=29), "Management, business, science, and arts occupations", AND(D15>=31, D15<=39), "Service occupations", AND(D15>=41, D15<=43), "Sales and office occupations", AND(D15>=51, D15<=53), "Production, transportation, and material moving occupations", AND(D15>=45, D15<=49), "Natural resources, construction, and maintenance occupations", TRUE, "Not applicable to study area" )} -> Natural resources, construction, and maintenance occupations | G15: =SUMIF(F:F, F15, A:A) -> 7339 | H15: =AVERAGEIF(F:F, F15, A:A) -> 59.666667 | I15: =_xlfn.XLOOKUP($C15,'NAICS-SOC-CIP x-walk'!C:C, 'NAICS-SOC-CIP x-walk'!H:H) -> 23 | J15: =_xlfn.XLOOKUP(K15,'ACS-NAICS-SOC x-walk'!K:K,'ACS-NAICS-SOC x-walk'!L:L) -> Construction | K15: =_xlfn.XLOOKUP($C15,'NAICS-SOC-CIP x-walk'!$C:$C, 'NAICS-SOC-CIP x-walk'!I:I) -> Construction | L15: =SUMIF(K:K, K15, A:A) -> 4403 | M15: =AVERAGEIF(K:K, K15, A:A) -> 57.934211
A16: 54 | B16: 1-2 | C16: 47-2053 | D16: =VALUE(LEFT(C16,2)) -> 47 | E16: Terrazzo Workers and Finishers | F16: {=_xlfn.IFS( AND(D16>=11, D16<=29), "Management, business, science, and arts occupations", AND(D16>=31, D16<=39), "Service occupations", AND(D16>=41, D16<=43), "Sales and office occupations", AND(D16>=51, D16<=53), "Production, transportation, and material moving occupations", AND(D16>=45, D16<=49), "Natural resources, construction, and maintenance occupations", TRUE, "Not applicable to study area" )} -> Natural resources, construction, and maintenance occupations | G16: =SUMIF(F:F, F16, A:A) -> 7339 | H16: =AVERAGEIF(F:F, F16, A:A) -> 59.666667 | I16: =_xlfn.XLOOKUP($C16,'NAICS-SOC-CIP x-walk'!C:C, 'NAICS-SOC-CIP x-walk'!H:H) -> 23 | J16: =_xlfn.XLOOKUP(K16,'ACS-NAICS-SOC x-walk'!K:K,'ACS-NAICS-SOC x-walk'!L:L) -> Construction | K16: =_xlfn.XLOOKUP($C16,'NAICS-SOC-CIP x-walk'!$C:$C, 'NAICS-SOC-CIP x-walk'!I:I) -> Construction | L16: =SUMIF(K:K, K16, A:A) -> 4403 | M16: =AVERAGEIF(K:K, K16, A:A) -> 57.934211
A17: 57 | B17: 1-2 | C17: 47-2061 | D17: =VALUE(LEFT(C17,2)) -> 47 | E17: Construction Laborers | F17: {=_xlfn.IFS( AND(D17>=11, D17<=29), "Management, business, science, and arts occupations", AND(D17>=31, D17<=39), "Service occupations", AND(D17>=41, D17<=43), "Sales and office occupations", AND(D17>=51, D17<=53), "Production, transportation, and material moving occupations", AND(D17>=45, D17<=49), "Natural resources, construction, and maintenance occupations", TRUE, "Not applicable to study area" )} -> Natural resources, construction, and maintenance occupations | G17: =SUMIF(F:F, F17, A:A) -> 7339 | H17: =AVERAGEIF(F:F, F17, A:A) -> 59.666667 | I17: =_xlfn.XLOOKUP($C17,'NAICS-SOC-CIP x-walk'!C:C, 'NAICS-SOC-CIP x-walk'!H:H) -> 23 | J17: =_xlfn.XLOOKUP(K17,'ACS-NAICS-SOC x-walk'!K:K,'ACS-NAICS-SOC x-walk'!L:L) -> Construction | K17: =_xlfn.XLOOKUP($C17,'NAICS-SOC-CIP x-walk'!$C:$C, 'NAICS-SOC-CIP x-walk'!I:I) -> Construction | L17: =SUMIF(K:K, K17, A:A) -> 4403 | M17: =AVERAGEIF(K:K, K17, A:A) -> 57.934211
A18: 31 | B18: 1-2 | C18: 47-2071 | D18: =VALUE(LEFT(C18,2)) -> 47 | E18: Paving, Surfacing, and Tamping Equipment Operators | F18: {=_xlfn.IFS( AND(D18>=11, D18<=29), "Management, business, science, and arts occupations", AND(D18>=31, D18<=39), "Service occupations", AND(D18>=41, D18<=43), "Sales and office occupations", AND(D18>=51, D18<=53), "Production, transportation, and material moving occupations", AND(D18>=45, D18<=49), "Natural resources, construction, and maintenance occupations", TRUE, "Not applicable to study area" )} -> Natural resources, construction, and maintenance occupations | G18: =SUMIF(F:F, F18, A:A) -> 7339 | H18: =AVERAGEIF(F:F, F18, A:A) -> 59.666667 | I18: =_xlfn.XLOOKUP($C18,'NAICS-SOC-CIP x-walk'!C:C, 'NAICS-SOC-CIP x-walk'!H:H) -> 23 | J18: =_xlfn.XLOOKUP(K18,'ACS-NAICS-SOC x-walk'!K:K,'ACS-NAICS-SOC x-walk'!L:L) -> Construction | K18: =_xlfn.XLOOKUP($C18,'NAICS-SOC-CIP x-walk'!$C:$C, 'NAICS-SOC-CIP x-walk'!I:I) -> Construction | L18: =SUMIF(K:K, K18, A:A) -> 4403 | M18: =AVERAGEIF(K:K, K18, A:A) -> 57.934211
... A22: 66 | B22: 1-2 | C22: 47-2082 | D22: =VALUE(LEFT(C22,2)) -> 47 | E22: Tapers | F22: {=_xlfn.IFS( AND(D22>=11, D22<=29), "Management, business, science, and arts occupations", AND(D22>=31, D22<=39), "Service occupations", AND(D22>=41, D22<=43), "Sales and office occupations", AND(D22>=51, D22<=53), "Production, transportation, and material moving occupations", AND(D22>=45, D22<=49), "Natural resources, construction, and maintenance occupations", TRUE, "Not applicable to study area" )} -> Natural resources, construction, and maintenance occupations | G22: =SUMIF(F:F, F22, A:A) -> 7339 | H22: =AVERAGEIF(F:F, F22, A:A) -> 59.666667 | I22: =_xlfn.XLOOKUP($C22,'NAICS-SOC-CIP x-walk'!C:C, 'NAICS-SOC-CIP x-walk'!H:H) -> 23 | J22: =_xlfn.XLOOKUP(K22,'ACS-NAICS-SOC x-walk'!K:K,'ACS-NAICS-SOC x-walk'!L:L) -> Construction | K22: =_xlfn.XLOOKUP($C22,'NAICS-SOC-CIP x-walk'!$C:$C, 'NAICS-SOC-CIP x-walk'!I:I) -> Construction | L22: =SUMIF(K:K, K22, A:A) -> 4403 | M22: =AVERAGEIF(K:K, K22, A:A) -> 57.934211
A23: 81 | B23: 3 | C23: 47-2111 | D23: =VALUE(LEFT(C23,2)) -> 47 | E23: Electricians | F23: {=_xlfn.IFS( AND(D23>=11, D23<=29), "Management, business, science, and arts occupations", AND(D23>=31, D23<=39), "Service occupations", AND(D23>=41, D23<=43), "Sales and office occupations", AND(D23>=51, D23<=53), "Production, transportation, and material moving occupations", AND(D23>=45, D23<=49), "Natural resources, construction, and maintenance occupations", TRUE, "Not applicable to study area" )} -> Natural resources, construction, and maintenance occupations | G23: =SUMIF(F:F, F23, A:A) -> 7339 | H23: =AVERAGEIF(F:F, F23, A:A) -> 59.666667 | I23: =_xlfn.XLOOKUP($C23,'NAICS-SOC-CIP x-walk'!C:C, 'NAICS-SOC-CIP x-walk'!H:H) -> 23 | J23: =_xlfn.XLOOKUP(K23,'ACS-NAICS-SOC x-walk'!K:K,'ACS-NAICS-SOC x-walk'!L:L) -> Construction | K23: =_xlfn.XLOOKUP($C23,'NAICS-SOC-CIP x-walk'!$C:$C, 'NAICS-SOC-CIP x-walk'!I:I) -> Construction | L23: =SUMIF(K:K, K23, A:A) -> 4403 | M23: =AVERAGEIF(K:K, K23, A:A) -> 57.934211
A24: 72 | B24: 1-2 | C24: 47-2121 | D24: =VALUE(LEFT(C24,2)) -> 47 | E24: Glaziers | F24: {=_xlfn.IFS( AND(D24>=11, D24<=29), "Management, business, science, and arts occupations", AND(D24>=31, D24<=39), "Service occupations", AND(D24>=41, D24<=43), "Sales and office occupations", AND(D24>=51, D24<=53), "Production, transportation, and material moving occupations", AND(D24>=45, D24<=49), "Natural resources, construction, and maintenance occupations", TRUE, "Not applicable to study area" )} -> Natural resources, construction, and maintenance occupations | G24: =SUMIF(F:F, F24, A:A) -> 7339 | H24: =AVERAGEIF(F:F, F24, A:A) -> 59.666667 | I24: =_xlfn.XLOOKUP($C24,'NAICS-SOC-CIP x-walk'!C:C, 'NAICS-SOC-CIP x-walk'!H:H) -> 23 | J24: =_xlfn.XLOOKUP(K24,'ACS-NAICS-SOC x-walk'!K:K,'ACS-NAICS-SOC x-walk'!L:L) -> Construction | K24: =_xlfn.XLOOKUP($C24,'NAICS-SOC-CIP x-walk'!$C:$C, 'NAICS-SOC-CIP x-walk'!I:I) -> Construction | L24: =SUMIF(K:K, K24, A:A) -> 4403 | M24: =AVERAGEIF(K:K, K24, A:A) -> 57.934211
A25: 72 | B25: 1-2 | C25: 47-2131 | D25: =VALUE(LEFT(C25,2)) -> 47 | E25: Insulation Workers, Floor, Ceiling, and Wall | F25: {=_xlfn.IFS( AND(D25>=11, D25<=29), "Management, business, science, and arts occupations", AND(D25>=31, D25<=39), "Service occupations", AND(D25>=41, D25<=43), "Sales and office occupations", AND(D25>=51, D25<=53), "Production, transportation, and material moving occupations", AND(D25>=45, D25<=49), "Natural resources, construction, and maintenance occupations", TRUE, "Not applicable to study area" )} -> Natural resources, construction, and maintenance occupations | G25: =SUMIF(F:F, F25, A:A) -> 7339 | H25: =AVERAGEIF(F:F, F25, A:A) -> 59.666667 | I25: =_xlfn.XLOOKUP($C25,'NAICS-SOC-CIP x-walk'!C:C, 'NAICS-SOC-CIP x-walk'!H:H) -> 23 | J25: =_xlfn.XLOOKUP(K25,'ACS-NAICS-SOC x-walk'!K:K,'ACS-NAICS-SOC x-walk'!L:L) -> Construction | K25: =_xlfn.XLOOKUP($C25,'NAICS-SOC-CIP x-walk'!$C:$C, 'NAICS-SOC-CIP x-walk'!I:I) -> Construction | L25: =SUMIF(K:K, K25, A:A) -> 4403 | M25: =AVERAGEIF(K:K, K25, A:A) -> 57.934211
A26: 74 | B26: 1-2 | C26: 47-2132 | D26: =VALUE(LEFT(C26,2)) -> 47 | E26: Insulation Workers, Mechanical | F26: {=_xlfn.IFS( AND(D26>=11, D26<=29), "Management, business, science, and arts occupations", AND(D26>=31, D26<=39), "Service occupations", AND(D26>=41, D26<=43), "Sales and office occupations", AND(D26>=51, D26<=53), "Production, transportation, and material moving occupations", AND(D26>=45, D26<=49), "Natural resources, construction, and maintenance occupations", TRUE, "Not applicable to study area" )} -> Natural resources, construction, and maintenance occupations | G26: =SUMIF(F:F, F26, A:A) -> 7339 | H26: =AVERAGEIF(F:F, F26, A:A) -> 59.666667 | I26: =_xlfn.XLOOKUP($C26,'NAICS-SOC-CIP x-walk'!C:C, 'NAICS-SOC-CIP x-walk'!H:H) -> 23 | J26: =_xlfn.XLOOKUP(K26,'ACS-NAICS-SOC x-walk'!K:K,'ACS-NAICS-SOC x-walk'!L:L) -> Construction | K26: =_xlfn.XLOOKUP($C26,'NAICS-SOC-CIP x-walk'!$C:$C, 'NAICS-SOC-CIP x-walk'!I:I) -> Construction | L26: =SUMIF(K:K, K26, A:A) -> 4403 | M26: =AVERAGEIF(K:K, K26, A:A) -> 57.934211
A27: 27 | B27: 1-2 | C27: 47-2141 | D27: =VALUE(LEFT(C27,2)) -> 47 | E27: Painters, Construction and Maintenance | F27: {=_xlfn.IFS( AND(D27>=11, D27<=29), "Management, business, science, and arts occupations", AND(D27>=31, D27<=39), "Service occupations", AND(D27>=41, D27<=43), "Sales and office occupations", AND(D27>=51, D27<=53), "Production, transportation, and material moving occupations", AND(D27>=45, D27<=49), "Natural resources, construction, and maintenance occupations", TRUE, "Not applicable to study area" )} -> Natural resources, construction, and maintenance occupations | G27: =SUMIF(F:F, F27, A:A) -> 7339 | H27: =AVERAGEIF(F:F, F27, A:A) -> 59.666667 | I27: =_xlfn.XLOOKUP($C27,'NAICS-SOC-CIP x-walk'!C:C, 'NAICS-SOC-CIP x-walk'!H:H) -> 23 | J27: =_xlfn.XLOOKUP(K27,'ACS-NAICS-SOC x-walk'!K:K,'ACS-NAICS-SOC x-walk'!L:L) -> Construction | K27: =_xlfn.XLOOKUP($C27,'NAICS-SOC-CIP x-walk'!$C:$C, 'NAICS-SOC-CIP x-walk'!I:I) -> Construction | L27: =SUMIF(K:K, K27, A:A) -> 4403 | M27: =AVERAGEIF(K:K, K27, A:A) -> 57.934211
A28: 45 | B28: 1-2 | C28: 47-2142 | D28: =VALUE(LEFT(C28,2)) -> 47 | E28: Paperhangers | F28: {=_xlfn.IFS( AND(D28>=11, D28<=29), "Management, business, science, and arts occupations", AND(D28>=31, D28<=39), "Service occupations", AND(D28>=41, D28<=43), "Sales and office occupations", AND(D28>=51, D28<=53), "Production, transportation, and material moving occupations", AND(D28>=45, D28<=49), "Natural resources, construction, and maintenance occupations", TRUE, "Not applicable to study area" )} -> Natural resources, construction, and maintenance occupations | G28: =SUMIF(F:F, F28, A:A) -> 7339 | H28: =AVERAGEIF(F:F, F28, A:A) -> 59.666667 | I28: =_xlfn.XLOOKUP($C28,'NAICS-SOC-CIP x-walk'!C:C, 'NAICS-SOC-CIP x-walk'!H:H) -> 23 | J28: =_xlfn.XLOOKUP(K28,'ACS-NAICS-SOC x-walk'!K:K,'ACS-NAICS-SOC x-walk'!L:L) -> Construction | K28: =_xlfn.XLOOKUP($C28,'NAICS-SOC-CIP x-walk'!$C:$C, 'NAICS-SOC-CIP x-walk'!I:I) -> Construction | L28: =SUMIF(K:K, K28, A:A) -> 4403 | M28: =AVERAGEIF(K:K, K28, A:A) -> 57.934211
A29: 21 | B29: 1-2 | C29: 47-2151 | D29: =VALUE(LEFT(C29,2)) -> 47 | E29: Pipelayers | F29: {=_xlfn.IFS( AND(D29>=11, D29<=29), "Management, business, science, and arts occupations", AND(D29>=31, D29<=39), "Service occupations", AND(D29>=41, D29<=43), "Sales and office occupations", AND(D29>=51, D29<=53), "Production, transportation, and material moving occupations", AND(D29>=45, D29<=49), "Natural resources, construction, and maintenance occupations", TRUE, "Not applicable to study area" )} -> Natural resources, construction, and maintenance occupations | G29: =SUMIF(F:F, F29, A:A) -> 7339 | H29: =AVERAGEIF(F:F, F29, A:A) -> 59.666667 | I29: =_xlfn.XLOOKUP($C29,'NAICS-SOC-CIP x-walk'!C:C, 'NAICS-SOC-CIP x-walk'!H:H) -> 23 | J29: =_xlfn.XLOOKUP(K29,'ACS-NAICS-SOC x-walk'!K:K,'ACS-NAICS-SOC x-walk'!L:L) -> Construction | K29: =_xlfn.XLOOKUP($C29,'NAICS-SOC-CIP x-walk'!$C:$C, 'NAICS-SOC-CIP x-walk'!I:I) -> Construction | L29: =SUMIF(K:K, K29, A:A) -> 4403 | M29: =AVERAGEIF(K:K, K29, A:A) -> 57.934211
A30: 80 | B30: 3 | C30: 47-2152 | D30: =VALUE(LEFT(C30,2)) -> 47 | E30: Plumbers, Pipefitters, and Steamfitters | F30: {=_xlfn.IFS( AND(D30>=11, D30<=29), "Management, business, science, and arts occupations", AND(D30>=31, D30<=39), "Service occupations", AND(D30>=41, D30<=43), "Sales and office occupations", AND(D30>=51, D30<=53), "Production, transportation, and material moving occupations", AND(D30>=45, D30<=49), "Natural resources, construction, and maintenance occupations", TRUE, "Not applicable to study area" )} -> Natural resources, construction, and maintenance occupations | G30: =SUMIF(F:F, F30, A:A) -> 7339 | H30: =AVERAGEIF(F:F, F30, A:A) -> 59.666667 | I30: =_xlfn.XLOOKUP($C30,'NAICS-SOC-CIP x-walk'!C:C, 'NAICS-SOC-CIP x-walk'!H:H) -> 23 | J30: =_xlfn.XLOOKUP(K30,'ACS-NAICS-SOC x-walk'!K:K,'ACS-NAICS-SOC x-walk'!L:L) -> Construction | K30: =_xlfn.XLOOKUP($C30,'NAICS-SOC-CIP x-walk'!$C:$C, 'NAICS-SOC-CIP x-walk'!I:I) -> Construction | L30: =SUMIF(K:K, K30, A:A) -> 4403 | M30: =AVERAGEIF(K:K, K30, A:A) -> 57.934211
A31: 74 | B31: 3 | C31: 47-2152 | D31: =VALUE(LEFT(C31,2)) -> 47 | E31: Solar Thermal Installers and Technicians | F31: {=_xlfn.IFS( AND(D31>=11, D31<=29), "Management, business, science, and arts occupations", AND(D31>=31, D31<=39), "Service occupations", AND(D31>=41, D31<=43), "Sales and office occupations", AND(D31>=51, D31<=53), "Production, transportation, and material moving occupations", AND(D31>=45, D31<=49), "Natural resources, construction, and maintenance occupations", TRUE, "Not applicable to study area" )} -> Natural resources, construction, and maintenance occupations | G31: =SUMIF(F:F, F31, A:A) -> 7339 | H31: =AVERAGEIF(F:F, F31, A:A) -> 59.666667 | I31: =_xlfn.XLOOKUP($C31,'NAICS-SOC-CIP x-walk'!C:C, 'NAICS-SOC-CIP x-walk'!H:H) -> 23 | J31: =_xlfn.XLOOKUP(K31,'ACS-NAICS-SOC x-walk'!K:K,'ACS-NAICS-SOC x-walk'!L:L) -> Construction | K31: =_xlfn.XLOOKUP($C31,'NAICS-SOC-CIP x-walk'!$C:$C, 'NAICS-SOC-CIP x-walk'!I:I) -> Construction | L31: =SUMIF(K:K, K31, A:A) -> 4403 | M31: =AVERAGEIF(K:K, K31, A:A) -> 57.934211
A32: 33 | B32: 1-2 | C32: 47-2161 | D32: =VALUE(LEFT(C32,2)) -> 47 | E32: Plasterers and Stucco Masons | F32: {=_xlfn.IFS( AND(D32>=11, D32<=29), "Management, business, science, and arts occupations", AND(D32>=31, D32<=39), "Service occupations", AND(D32>=41, D32<=43), "Sales and office occupations", AND(D32>=51, D32<=53), "Production, transportation, and material moving occupations", AND(D32>=45, D32<=49), "Natural resources, construction, and maintenance occupations", TRUE, "Not applicable to study area" )} -> Natural resources, construction, and maintenance occupations | G32: =SUMIF(F:F, F32, A:A) -> 7339 | H32: =AVERAGEIF(F:F, F32, A:A) -> 59.666667 | I32: =_xlfn.XLOOKUP($C32,'NAICS-SOC-CIP x-walk'!C:C, 'NAICS-SOC-CIP x-walk'!H:H) -> 23 | J32: =_xlfn.XLOOKUP(K32,'ACS-NAICS-SOC x-walk'!K:K,'ACS-NAICS-SOC x-walk'!L:L) -> Construction | K32: =_xlfn.XLOOKUP($C32,'NAICS-SOC-CIP x-walk'!$C:$C, 'NAICS-SOC-CIP x-walk'!I:I) -> Construction | L32: =SUMIF(K:K, K32, A:A) -> 4403 | M32: =AVERAGEIF(K:K, K32, A:A) -> 57.934211
A33: 48 | B33: 1-2 | C33: 47-2171 | D33: =VALUE(LEFT(C33,2)) -> 47 | E33: Reinforcing Iron and Rebar Workers | F33: {=_xlfn.IFS( AND(D33>=11, D33<=29), "Management, business, science, and arts occupations", AND(D33>=31, D33<=39), "Service occupations", AND(D33>=41, D33<=43), "Sales and office occupations", AND(D33>=51, D33<=53), "Production, transportation, and material moving occupations", AND(D33>=45, D33<=49), "Natural resources, construction, and maintenance occupations", TRUE, "Not applicable to study area" )} -> Natural resources, construction, and maintenance occupations | G33: =SUMIF(F:F, F33, A:A) -> 7339 | H33: =AVERAGEIF(F:F, F33, A:A) -> 59.666667 | I33: =_xlfn.XLOOKUP($C33,'NAICS-SOC-CIP x-walk'!C:C, 'NAICS-SOC-CIP x-walk'!H:H) -> 23 | J33: =_xlfn.XLOOKUP(K33,'ACS-NAICS-SOC x-walk'!K:K,'ACS-NAICS-SOC x-walk'!L:L) -> Construction | K33: =_xlfn.XLOOKUP($C33,'NAICS-SOC-CIP x-walk'!$C:$C, 'NAICS-SOC-CIP x-walk'!I:I) -> Construction | L33: =SUMIF(K:K, K33, A:A) -> 4403 | M33: =AVERAGEIF(K:K, K33, A:A) -> 57.934211
A34: 71 | B34: 1-2 | C34: 47-2181 | D34: =VALUE(LEFT(C34,2)) -> 47 | E34: Roofers | F34: {=_xlfn.IFS( AND(D34>=11, D34<=29), "Management, business, science, and arts occupations", AND(D34>=31, D34<=39), "Service occupations", AND(D34>=41, D34<=43), "Sales and office occupations", AND(D34>=51, D34<=53), "Production, transportation, and material moving occupations", AND(D34>=45, D34<=49), "Natural resources, construction, and maintenance occupations", TRUE, "Not applicable to study area" )} -> Natural resources, construction, and maintenance occupations | G34: =SUMIF(F:F, F34, A:A) -> 7339 | H34: =AVERAGEIF(F:F, F34, A:A) -> 59.666667 | I34: =_xlfn.XLOOKUP($C34,'NAICS-SOC-CIP x-walk'!C:C, 'NAICS-SOC-CIP x-walk'!H:H) -> 23 | J34: =_xlfn.XLOOKUP(K34,'ACS-NAICS-SOC x-walk'!K:K,'ACS-NAICS-SOC x-walk'!L:L) -> Construction | K34: =_xlfn.XLOOKUP($C34,'NAICS-SOC-CIP x-walk'!$C:$C, 'NAICS-SOC-CIP x-walk'!I:I) -> Construction | L34: =SUMIF(K:K, K34, A:A) -> 4403 | M34: =AVERAGEIF(K:K, K34, A:A) -> 57.934211
A35: 64 | B35: 1-2 | C35: 47-2211 | D35: =VALUE(LEFT(C35,2)) -> 47 | E35: Sheet Metal Workers | F35: {=_xlfn.IFS( AND(D35>=11, D35<=29), "Management, business, science, and arts occupations", AND(D35>=31, D35<=39), "Service occupations", AND(D35>=41, D35<=43), "Sales and office occupations", AND(D35>=51, D35<=53), "Production, transportation, and material moving occupations", AND(D35>=45, D35<=49), "Natural resources, construction, and maintenance occupations", TRUE, "Not applicable to study area" )} -> Natural resources, construction, and maintenance occupations | G35: =SUMIF(F:F, F35, A:A) -> 7339 | H35: =AVERAGEIF(F:F, F35, A:A) -> 59.666667 | I35: =_xlfn.XLOOKUP($C35,'NAICS-SOC-CIP x-walk'!C:C, 'NAICS-SOC-CIP x-walk'!H:H) -> 23 | J35: =_xlfn.XLOOKUP(K35,'ACS-NAICS-SOC x-walk'!K:K,'ACS-NAICS-SOC x-walk'!L:L) -> Construction | K35: =_xlfn.XLOOKUP($C35,'NAICS-SOC-CIP x-walk'!$C:$C, 'NAICS-SOC-CIP x-walk'!I:I) -> Construction | L35: =SUMIF(K:K, K35, A:A) -> 4403 | M35: =AVERAGEIF(K:K, K35, A:A) -> 57.934211
A36: 61 | B36: 1-2 | C36: 47-2221 | D36: =VALUE(LEFT(C36,2)) -> 47 | E36: Structural Iron and Steel Workers | F36: {=_xlfn.IFS( AND(D36>=11, D36<=29), "Management, business, science, and arts occupations", AND(D36>=31, D36<=39), "Service occupations", AND(D36>=41, D36<=43), "Sales and office occupations", AND(D36>=51, D36<=53), "Production, transportation, and material moving occupations", AND(D36>=45, D36<=49), "Natural resources, construction, and maintenance occupations", TRUE, "Not applicable to study area" )} -> Natural resources, construction, and maintenance occupations | G36: =SUMIF(F:F, F36, A:A) -> 7339 | H36: =AVERAGEIF(F:F, F36, A:A) -> 59.666667 | I36: =_xlfn.XLOOKUP($C36,'NAICS-SOC-CIP x-walk'!C:C, 'NAICS-SOC-CIP x-walk'!H:H) -> 23 | J36: =_xlfn.XLOOKUP(K36,'ACS-NAICS-SOC x-walk'!K:K,'ACS-NAICS-SOC x-walk'!L:L) -> Construction | K36: =_xlfn.XLOOKUP($C36,'NAICS-SOC-CIP x-walk'!$C:$C, 'NAICS-SOC-CIP x-walk'!I:I) -> Construction | L36: =SUMIF(K:K, K36, A:A) -> 4403 | M36: =AVERAGEIF(K:K, K36, A:A) -> 57.934211
A37: 74 | B37: 1-2 | C37: 47-2231 | D37: =VALUE(LEFT(C37,2)) -> 47 | E37: Solar Photovoltaic Installers | F37: {=_xlfn.IFS( AND(D37>=11, D37<=29), "Management, business, science, and arts occupations", AND(D37>=31, D37<=39), "Service occupations", AND(D37>=41, D37<=43), "Sales and office occupations", AND(D37>=51, D37<=53), "Production, transportation, and material moving occupations", AND(D37>=45, D37<=49), "Natural resources, construction, and maintenance occupations", TRUE, "Not applicable to study area" )} -> Natural resources, construction, and maintenance occupations | G37: =SUMIF(F:F, F37, A:A) -> 7339 | H37: =AVERAGEIF(F:F, F37, A:A) -> 59.666667 | I37: =_xlfn.XLOOKUP($C37,'NAICS-SOC-CIP x-walk'!C:C, 'NAICS-SOC-CIP x-walk'!H:H) -> 21, 22 | J37: =_xlfn.XLOOKUP(K37,'ACS-NAICS-SOC x-walk'!K:K,'ACS-NAICS-SOC x-walk'!L:L) -> Agriculture, Forestry, Fishing and Hunting, and Mining | K37: =_xlfn.XLOOKUP($C37,'NAICS-SOC-CIP x-walk'!$C:$C, 'NAICS-SOC-CIP x-walk'!I:I) -> Mining, Quarrying, and Oil and Gas Extraction, Utilities | L37: =SUMIF(K:K, K37, A:A) -> 4509 | M37: =AVERAGEIF(K:K, K37, A:A) -> 48.483871
A38: 57 | B38: 1-2 | C38: 47-3011 | D38: =VALUE(LEFT(C38,2)) -> 47 | E38: Helpers--Brickmasons, Blockmasons, Stonemasons, and Tile and Marble Setters | F38: {=_xlfn.IFS( AND(D38>=11, D38<=29), "Management, business, science, and arts occupations", AND(D38>=31, D38<=39), "Service occupations", AND(D38>=41, D38<=43), "Sales and office occupations", AND(D38>=51, D38<=53), "Production, transportation, and material moving occupations", AND(D38>=45, D38<=49), "Natural resources, construction, and maintenance occupations", TRUE, "Not applicable to study area" )} -> Natural resources, construction, and maintenance occupations | G38: =SUMIF(F:F, F38, A:A) -> 7339 | H38: =AVERAGEIF(F:F, F38, A:A) -> 59.666667 | I38: =_xlfn.XLOOKUP($C38,'NAICS-SOC-CIP x-walk'!C:C, 'NAICS-SOC-CIP x-walk'!H:H) -> 23 | J38: =_xlfn.XLOOKUP(K38,'ACS-NAICS-SOC x-walk'!K:K,'ACS-NAICS-SOC x-walk'!L:L) -> Construction | K38: =_xlfn.XLOOKUP($C38,'NAICS-SOC-CIP x-walk'!$C:$C, 'NAICS-SOC-CIP x-walk'!I:I) -> Construction | L38: =SUMIF(K:K, K38, A:A) -> 4403 | M38: =AVERAGEIF(K:K, K38, A:A) -> 57.934211
A39: 61 | B39: 1-2 | C39: 47-3012 | D39: =VALUE(LEFT(C39,2)) -> 47 | E39: Helpers--Carpenters | F39: {=_xlfn.IFS( AND(D39>=11, D39<=29), "Management, business, science, and arts occupations", AND(D39>=31, D39<=39), "Service occupations", AND(D39>=41, D39<=43), "Sales and office occupations", AND(D39>=51, D39<=53), "Production, transportation, and material moving occupations", AND(D39>=45, D39<=49), "Natural resources, construction, and maintenance occupations", TRUE, "Not applicable to study area" )} -> Natural resources, construction, and maintenance occupations | G39: =SUMIF(F:F, F39, A:A) -> 7339 | H39: =AVERAGEIF(F:F, F39, A:A) -> 59.666667 | I39: =_xlfn.XLOOKUP($C39,'NAICS-SOC-CIP x-walk'!C:C, 'NAICS-SOC-CIP x-walk'!H:H) -> 23 | J39: =_xlfn.XLOOKUP(K39,'ACS-NAICS-SOC x-walk'!K:K,'ACS-NAICS-SOC x-walk'!L:L) -> Construction | K39: =_xlfn.XLOOKUP($C39,'NAICS-SOC-CIP x-walk'!$C:$C, 'NAICS-SOC-CIP x-walk'!I:I) -> Construction | L39: =SUMIF(K:K, K39, A:A) -> 4403 | M39: =AVERAGEIF(K:K, K39, A:A) -> 57.934211
A40: 70 | B40: 1-2 | C40: 47-3013 | D40: =VALUE(LEFT(C40,2)) -> 47 | E40: Helpers--Electricians | F40: {=_xlfn.IFS( AND(D40>=11, D40<=29), "Management, business, science, and arts occupations", AND(D40>=31, D40<=39), "Service occupations", AND(D40>=41, D40<=43), "Sales and office occupations", AND(D40>=51, D40<=53), "Production, transportation, and material moving occupations", AND(D40>=45, D40<=49), "Natural resources, construction, and maintenance occupations", TRUE, "Not applicable to study area" )} -> Natural resources, construction, and maintenance occupations | G40: =SUMIF(F:F, F40, A:A) -> 7339 | H40: =AVERAGEIF(F:F, F40, A:A) -> 59.666667 | I40: =_xlfn.XLOOKUP($C40,'NAICS-SOC-CIP x-walk'!C:C, 'NAICS-SOC-CIP x-walk'!H:H) -> 23 | J40: =_xlfn.XLOOKUP(K40,'ACS-NAICS-SOC x-walk'!K:K,'ACS-NAICS-SOC x-walk'!L:L) -> Construction | K40: =_xlfn.XLOOKUP($C40,'NAICS-SOC-CIP x-walk'!$C:$C, 'NAICS-SOC-CIP x-walk'!I:I) -> Construction | L40: =SUMIF(K:K, K40, A:A) -> 4403 | M40: =AVERAGEIF(K:K, K40, A:A) -> 57.934211
A41: 47 | B41: 1-2 | C41: 47-3014 | D41: =VALUE(LEFT(C41,2)) -> 47 | E41: Helpers--Painters, Paperhangers, Plasterers, and Stucco Masons | F41: {=_xlfn.IFS( AND(D41>=11, D41<=29), "Management, business, science, and arts occupations", AND(D41>=31, D41<=39), "Service occupations", AND(D41>=41, D41<=43), "Sales and office occupations", AND(D41>=51, D41<=53), "Production, transportation, and material moving occupations", AND(D41>=45, D41<=49), "Natural resources, construction, and maintenance occupations", TRUE, "Not applicable to study area" )} -> Natural resources, construction, and maintenance occupations | G41: =SUMIF(F:F, F41, A:A) -> 7339 | H41: =AVERAGEIF(F:F, F41, A:A) -> 59.666667 | I41: =_xlfn.XLOOKUP($C41,'NAICS-SOC-CIP x-walk'!C:C, 'NAICS-SOC-CIP x-walk'!H:H) -> 23 | J41: =_xlfn.XLOOKUP(K41,'ACS-NAICS-SOC x-walk'!K:K,'ACS-NAICS-SOC x-walk'!L:L) -> Construction | K41: =_xlfn.XLOOKUP($C41,'NAICS-SOC-CIP x-walk'!$C:$C, 'NAICS-SOC-CIP x-walk'!I:I) -> Construction | L41: =SUMIF(K:K, K41, A:A) -> 4403 | M41: =AVERAGEIF(K:K, K41, A:A) -> 57.934211
A42: 65 | B42: 1-2 | C42: 47-3015 | D42: =VALUE(LEFT(C42,2)) -> 47 | E42: Helpers--Pipelayers, Plumbers, Pipefitters, and Steamfitters | F42: {=_xlfn.IFS( AND(D42>=11, D42<=29), "Management, business, science, and arts occupations", AND(D42>=31, D42<=39), "Service occupations", AND(D42>=41, D42<=43), "Sales and office occupations", AND(D42>=51, D42<=53), "Production, transportation, and material moving occupations", AND(D42>=45, D42<=49), "Natural resources, construction, and maintenance occupations", TRUE, "Not applicable to study area" )} -> Natural resources, construction, and maintenance occupations | G42: =SUMIF(F:F, F42, A:A) -> 7339 | H42: =AVERAGEIF(F:F, F42, A:A) -> 59.666667 | I42: =_xlfn.XLOOKUP($C42,'NAICS-SOC-CIP x-walk'!C:C, 'NAICS-SOC-CIP x-walk'!H:H) -> 23 | J42: =_xlfn.XLOOKUP(K42,'ACS-NAICS-SOC x-walk'!K:K,'ACS-NAICS-SOC x-walk'!L:L) -> Construction | K42: =_xlfn.XLOOKUP($C42,'NAICS-SOC-CIP x-walk'!$C:$C, 'NAICS-SOC-CIP x-walk'!I:I) -> Construction | L42: =SUMIF(K:K, K42, A:A) -> 4403 | M42: =AVERAGEIF(K:K, K42, A:A) -> 57.934211
A43: 48 | B43: 1-2 | C43: 47-3016 | D43: =VALUE(LEFT(C43,2)) -> 47 | E43: Helpers--Roofers | F43: {=_xlfn.IFS( AND(D43>=11, D43<=29), "Management, business, science, and arts occupations", AND(D43>=31, D43<=39), "Service occupations", AND(D43>=41, D43<=43), "Sales and office occupations", AND(D43>=51, D43<=53), "Production, transportation, and material moving occupations", AND(D43>=45, D43<=49), "Natural resources, construction, and maintenance occupations", TRUE, "Not applicable to study area" )} -> Natural resources, construction, and maintenance occupations | G43: =SUMIF(F:F, F43, A:A) -> 7339 | H43: =AVERAGEIF(F:F, F43, A:A) -> 59.666667 | I43: =_xlfn.XLOOKUP($C43,'NAICS-SOC-CIP x-walk'!C:C, 'NAICS-SOC-CIP x-walk'!H:H) -> 23 | J43: =_xlfn.XLOOKUP(K43,'ACS-NAICS-SOC x-walk'!K:K,'ACS-NAICS-SOC x-walk'!L:L) -> Construction | K43: =_xlfn.XLOOKUP($C43,'NAICS-SOC-CIP x-walk'!$C:$C, 'NAICS-SOC-CIP x-walk'!I:I) -> Construction | L43: =SUMIF(K:K, K43, A:A) -> 4403 | M43: =AVERAGEIF(K:K, K43, A:A) -> 57.934211
A44: 81 | B44: 3 | C44: 47-4011 | D44: =VALUE(LEFT(C44,2)) -> 47 | E44: Construction and Building Inspectors | F44: {=_xlfn.IFS( AND(D44>=11, D44<=29), "Management, business, science, and arts occupations", AND(D44>=31, D44<=39), "Service occupations", AND(D44>=41, D44<=43), "Sales and office occupations", AND(D44>=51, D44<=53), "Production, transportation, and material moving occupations", AND(D44>=45, D44<=49), "Natural resources, construction, and maintenance occupations", TRUE, "Not applicable to study area" )} -> Natural resources, construction, and maintenance occupations | G44: =SUMIF(F:F, F44, A:A) -> 7339 | H44: =AVERAGEIF(F:F, F44, A:A) -> 59.666667 | I44: =_xlfn.XLOOKUP($C44,'NAICS-SOC-CIP x-walk'!C:C, 'NAICS-SOC-CIP x-walk'!H:H) -> 23 | J44: =_xlfn.XLOOKUP(K44,'ACS-NAICS-SOC x-walk'!K:K,'ACS-NAICS-SOC x-walk'!L:L) -> Construction | K44: =_xlfn.XLOOKUP($C44,'NAICS-SOC-CIP x-walk'!$C:$C, 'NAICS-SOC-CIP x-walk'!I:I) -> Construction | L44: =SUMIF(K:K, K44, A:A) -> 4403 | M44: =AVERAGEIF(K:K, K44, A:A) -> 57.934211
A45: 64 | B45: 3 | C45: 47-4011 | D45: =VALUE(LEFT(C45,2)) -> 47 | E45: Energy Auditors | F45: {=_xlfn.IFS( AND(D45>=11, D45<=29), "Management, business, science, and arts occupations", AND(D45>=31, D45<=39), "Service occupations", AND(D45>=41, D45<=43), "Sales and office occupations", AND(D45>=51, D45<=53), "Production, transportation, and material moving occupations", AND(D45>=45, D45<=49), "Natural resources, construction, and maintenance occupations", TRUE, "Not applicable to study area" )} -> Natural resources, construction, and maintenance occupations | G45: =SUMIF(F:F, F45, A:A) -> 7339 | H45: =AVERAGEIF(F:F, F45, A:A) -> 59.666667 | I45: =_xlfn.XLOOKUP($C45,'NAICS-SOC-CIP x-walk'!C:C, 'NAICS-SOC-CIP x-walk'!H:H) -> 23 | J45: =_xlfn.XLOOKUP(K45,'ACS-NAICS-SOC x-walk'!K:K,'ACS-NAICS-SOC x-walk'!L:L) -> Construction | K45: =_xlfn.XLOOKUP($C45,'NAICS-SOC-CIP x-walk'!$C:$C, 'NAICS-SOC-CIP x-walk'!I:I) -> Construction | L45: =SUMIF(K:K, K45, A:A) -> 4403 | M45: =AVERAGEIF(K:K, K45, A:A) -> 57.934211
A46: 70 | B46: 3 | C46: 47-4021 | D46: =VALUE(LEFT(C46,2)) -> 47 | E46: Elevator and Escalator Installers and Repairers | F46: {=_xlfn.IFS( AND(D46>=11, D46<=29), "Management, business, science, and arts occupations", AND(D46>=31, D46<=39), "Service occupations", AND(D46>=41, D46<=43), "Sales and office occupations", AND(D46>=51, D46<=53), "Production, transportation, and material moving occupations", AND(D46>=45, D46<=49), "Natural resources, construction, and maintenance occupations", TRUE, "Not applicable to study area" )} -> Natural resources, construction, and maintenance occupations | G46: =SUMIF(F:F, F46, A:A) -> 7339 | H46: =AVERAGEIF(F:F, F46, A:A) -> 59.666667 | I46: =_xlfn.XLOOKUP($C46,'NAICS-SOC-CIP x-walk'!C:C, 'NAICS-SOC-CIP x-walk'!H:H) -> 23 | J46: =_xlfn.XLOOKUP(K46,'ACS-NAICS-SOC x-walk'!K:K,'ACS-NAICS-SOC x-walk'!L:L) -> Construction | K46: =_xlfn.XLOOKUP($C46,'NAICS-SOC-CIP x-walk'!$C:$C, 'NAICS-SOC-CIP x-walk'!I:I) -> Construction | L46: =SUMIF(K:K, K46, A:A) -> 4403 | M46: =AVERAGEIF(K:K, K46, A:A) -> 57.934211
A47: 39 | B47: 1-2 | C47: 47-4031 | D47: =VALUE(LEFT(C47,2)) -> 47 | E47: Fence Erectors | F47: {=_xlfn.IFS( AND(D47>=11, D47<=29), "Management, business, science, and arts occupations", AND(D47>=31, D47<=39), "Service occupations", AND(D47>=41, D47<=43), "Sales and office occupations", AND(D47>=51, D47<=53), "Production, transportation, and material moving occupations", AND(D47>=45, D47<=49), "Natural resources, construction, and maintenance occupations", TRUE, "Not applicable to study area" )} -> Natural resources, construction, and maintenance occupations | G47: =SUMIF(F:F, F47, A:A) -> 7339 | H47: =AVERAGEIF(F:F, F47, A:A) -> 59.666667 | I47: =_xlfn.XLOOKUP($C47,'NAICS-SOC-CIP x-walk'!C:C, 'NAICS-SOC-CIP x-walk'!H:H) -> 23 | J47: =_xlfn.XLOOKUP(K47,'ACS-NAICS-SOC x-walk'!K:K,'ACS-NAICS-SOC x-walk'!L:L) -> Construction | K47: =_xlfn.XLOOKUP($C47,'NAICS-SOC-CIP x-walk'!$C:$C, 'NAICS-SOC-CIP x-walk'!I:I) -> Construction | L47: =SUMIF(K:K, K47, A:A) -> 4403 | M47: =AVERAGEIF(K:K, K47, A:A) -> 57.934211
A48: 65 | B48: 1-2 | C48: 47-4051 | D48: =VALUE(LEFT(C48,2)) -> 47 | E48: Highway Maintenance Workers | F48: {=_xlfn.IFS( AND(D48>=11, D48<=29), "Management, business, science, and arts occupations", AND(D48>=31, D48<=39), "Service occupations", AND(D48>=41, D48<=43), "Sales and office occupations", AND(D48>=51, D48<=53), "Production, transportation, and material moving occupations", AND(D48>=45, D48<=49), "Natural resources, construction, and maintenance occupations", TRUE, "Not applicable to study area" )} -> Natural resources, construction, and maintenance occupations | G48: =SUMIF(F:F, F48, A:A) -> 7339 | H48: =AVERAGEIF(F:F, F48, A:A) -> 59.666667 | I48: =_xlfn.XLOOKUP($C48,'NAICS-SOC-CIP x-walk'!C:C, 'NAICS-SOC-CIP x-walk'!H:H) -> 23 | J48: =_xlfn.XLOOKUP(K48,'ACS-NAICS-SOC x-walk'!K:K,'ACS-NAICS-SOC x-walk'!L:L) -> Construction | K48: =_xlfn.XLOOKUP($C48,'NAICS-SOC-CIP x-walk'!$C:$C, 'NAICS-SOC-CIP x-walk'!I:I) -> Construction | L48: =SUMIF(K:K, K48, A:A) -> 4403 | M48: =AVERAGEIF(K:K, K48, A:A) -> 57.934211
A49: 24 | B49: 1-2 | C49: 47-5022 | D49: =VALUE(LEFT(C49,2)) -> 47 | E49: Excavating and Loading Machine and Dragline Operators, Surface Mining | F49: {=_xlfn.IFS( AND(D49>=11, D49<=29), "Management, business, science, and arts occupations", AND(D49>=31, D49<=39), "Service occupations", AND(D49>=41, D49<=43), "Sales and office occupations", AND(D49>=51, D49<=53), "Production, transportation, and material moving occupations", AND(D49>=45, D49<=49), "Natural resources, construction, and maintenance occupations", TRUE, "Not applicable to study area" )} -> Natural resources, construction, and maintenance occupations | G49: =SUMIF(F:F, F49, A:A) -> 7339 | H49: =AVERAGEIF(F:F, F49, A:A) -> 59.666667 | I49: =_xlfn.XLOOKUP($C49,'NAICS-SOC-CIP x-walk'!C:C, 'NAICS-SOC-CIP x-walk'!H:H) -> 21, 22 | J49: =_xlfn.XLOOKUP(K49,'ACS-NAICS-SOC x-walk'!K:K,'ACS-NAICS-SOC x-walk'!L:L) -> Agriculture, Forestry, Fishing and Hunting, and Mining | K49: =_xlfn.XLOOKUP($C49,'NAICS-SOC-CIP x-walk'!$C:$C, 'NAICS-SOC-CIP x-walk'!I:I) -> Mining, Quarrying, and Oil and Gas Extraction, Utilities | L49: =SUMIF(K:K, K49, A:A) -> 4509 | M49: =AVERAGEIF(K:K, K49, A:A) -> 48.483871
A50: 30 | B50: 1-2 | C50: 47-5023 | D50: =VALUE(LEFT(C50,2)) -> 47 | E50: Earth Drillers, Except Oil and Gas | F50: {=_xlfn.IFS( AND(D50>=11, D50<=29), "Management, business, science, and arts occupations", AND(D50>=31, D50<=39), "Service occupations", AND(D50>=41, D50<=43), "Sales and office occupations", AND(D50>=51, D50<=53), "Production, transportation, and material moving occupations", AND(D50>=45, D50<=49), "Natural resources, construction, and maintenance occupations", TRUE, "Not applicable to study area" )} -> Natural resources, construction, and maintenance occupations | G50: =SUMIF(F:F, F50, A:A) -> 7339 | H50: =AVERAGEIF(F:F, F50, A:A) -> 59.666667 | I50: =_xlfn.XLOOKUP($C50,'NAICS-SOC-CIP x-walk'!C:C, 'NAICS-SOC-CIP x-walk'!H:H) -> 21, 22 | J50: =_xlfn.XLOOKUP(K50,'ACS-NAICS-SOC x-walk'!K:K,'ACS-NAICS-SOC x-walk'!L:L) -> Agriculture, Forestry, Fishing and Hunting, and Mining | K50: =_xlfn.XLOOKUP($C50,'NAICS-SOC-CIP x-walk'!$C:$C, 'NAICS-SOC-CIP x-walk'!I:I) -> Mining, Quarrying, and Oil and Gas Extraction, Utilities | L50: =SUMIF(K:K, K50, A:A) -> 4509 | M50: =AVERAGEIF(K:K, K50, A:A) -> 48.483871
A51: 56 | B51: 1-2 | C51: 47-5032 | D51: =VALUE(LEFT(C51,2)) -> 47 | E51: Explosives Workers, Ordnance Handling Experts, and Blasters | F51: {=_xlfn.IFS( AND(D51>=11, D51<=29), "Management, business, science, and arts occupations", AND(D51>=31, D51<=39), "Service occupations", AND(D51>=41, D51<=43), "Sales and office occupations", AND(D51>=51, D51<=53), "Production, transportation, and material moving occupations", AND(D51>=45, D51<=49), "Natural resources, construction, and maintenance occupations", TRUE, "Not applicable to study area" )} -> Natural resources, construction, and maintenance occupations | G51: =SUMIF(F:F, F51, A:A) -> 7339 | H51: =AVERAGEIF(F:F, F51, A:A) -> 59.666667 | I51: =_xlfn.XLOOKUP($C51,'NAICS-SOC-CIP x-walk'!C:C, 'NAICS-SOC-CIP x-walk'!H:H) -> 21, 22 | J51: =_xlfn.XLOOKUP(K51,'ACS-NAICS-SOC x-walk'!K:K,'ACS-NAICS-SOC x-walk'!L:L) -> Agriculture, Forestry, Fishing and Hunting, and Mining | K51: =_xlfn.XLOOKUP($C51,'NAICS-SOC-CIP x-walk'!$C:$C, 'NAICS-SOC-CIP x-walk'!I:I) -> Mining, Quarrying, and Oil and Gas Extraction, Utilities | L51: =SUMIF(K:K, K51, A:A) -> 4509 | M51: =AVERAGEIF(K:K, K51, A:A) -> 48.483871
A52: 59 | B52: 1-2 | C52: 47-5041 | D52: =VALUE(LEFT(C52,2)) -> 47 | E52: Continuous Mining Machine Operators | F52: {=_xlfn.IFS( AND(D52>=11, D52<=29), "Management, business, science, and arts occupations", AND(D52>=31, D52<=39), "Service occupations", AND(D52>=41, D52<=43), "Sales and office occupations", AND(D52>=51, D52<=53), "Production, transportation, and material moving occupations", AND(D52>=45, D52<=49), "Natural resources, construction, and maintenance occupations", TRUE, "Not applicable to study area" )} -> Natural resources, construction, and maintenance occupations | G52: =SUMIF(F:F, F52, A:A) -> 7339 | H52: =AVERAGEIF(F:F, F52, A:A) -> 59.666667 | I52: =_xlfn.XLOOKUP($C52,'NAICS-SOC-CIP x-walk'!C:C, 'NAICS-SOC-CIP x-walk'!H:H) -> 21, 22 | J52: =_xlfn.XLOOKUP(K52,'ACS-NAICS-SOC x-walk'!K:K,'ACS-NAICS-SOC x-walk'!L:L) -> Agriculture, Forestry, Fishing and Hunting, and Mining | K52: =_xlfn.XLOOKUP($C52,'NAICS-SOC-CIP x-walk'!$C:$C, 'NAICS-SOC-CIP x-walk'!I:I) -> Mining, Quarrying, and Oil and Gas Extraction, Utilities | L52: =SUMIF(K:K, K52, A:A) -> 4509 | M52: =AVERAGEIF(K:K, K52, A:A) -> 48.483871
A53: 73 | B53: 3 | C53: 49-2098 | D53: =VALUE(LEFT(C53,2)) -> 49 | E53: Security and Fire Alarm Systems Installers | F53: {=_xlfn.IFS( AND(D53>=11, D53<=29), "Management, business, science, and arts occupations", AND(D53>=31, D53<=39), "Service occupations", AND(D53>=41, D53<=43), "Sales and office occupations", AND(D53>=51, D53<=53), "Production, transportation, and material moving occupations", AND(D53>=45, D53<=49), "Natural resources, construction, and maintenance occupations", TRUE, "Not applicable to study area" )} -> Natural resources, construction, and maintenance occupations | G53: =SUMIF(F:F, F53, A:A) -> 7339 | H53: =AVERAGEIF(F:F, F53, A:A) -> 59.666667 | I53: =_xlfn.XLOOKUP($C53,'NAICS-SOC-CIP x-walk'!C:C, 'NAICS-SOC-CIP x-walk'!H:H) -> 23 | J53: =_xlfn.XLOOKUP(K53,'ACS-NAICS-SOC x-walk'!K:K,'ACS-NAICS-SOC x-walk'!L:L) -> Construction | K53: =_xlfn.XLOOKUP($C53,'NAICS-SOC-CIP x-walk'!$C:$C, 'NAICS-SOC-CIP x-walk'!I:I) -> Construction | L53: =SUMIF(K:K, K53, A:A) -> 4403 | M53: =AVERAGEIF(K:K, K53, A:A) -> 57.934211
A54: 72 | B54: 1-2 | C54: 49-9011 | D54: =VALUE(LEFT(C54,2)) -> 49 | E54: Mechanical Door Repairers | F54: {=_xlfn.IFS( AND(D54>=11, D54<=29), "Management, business, science, and arts occupations", AND(D54>=31, D54<=39), "Service occupations", AND(D54>=41, D54<=43), "Sales and office occupations", AND(D54>=51, D54<=53), "Production, transportation, and material moving occupations", AND(D54>=45, D54<=49), "Natural resources, construction, and maintenance occupations", TRUE, "Not applicable to study area" )} -> Natural resources, construction, and maintenance occupations | G54: =SUMIF(F:F, F54, A:A) -> 7339 | H54: =AVERAGEIF(F:F, F54, A:A) -> 59.666667 | I54: =_xlfn.XLOOKUP($C54,'NAICS-SOC-CIP x-walk'!C:C, 'NAICS-SOC-CIP x-walk'!H:H) -> 23 | J54: =_xlfn.XLOOKUP(K54,'ACS-NAICS-SOC x-walk'!K:K,'ACS-NAICS-SOC x-walk'!L:L) -> Construction | K54: =_xlfn.XLOOKUP($C54,'NAICS-SOC-CIP x-walk'!$C:$C, 'NAICS-SOC-CIP x-walk'!I:I) -> Construction | L54: =SUMIF(K:K, K54, A:A) -> 4403 | M54: =AVERAGEIF(K:K, K54, A:A) -> 57.934211
A55: 76 | B55: 3 | C55: 49-9012 | D55: =VALUE(LEFT(C55,2)) -> 49 | E55: Control and Valve Installers and Repairers, Except Mechanical Door | F55: {=_xlfn.IFS( AND(D55>=11, D55<=29), "Management, business, science, and arts occupations", AND(D55>=31, D55<=39), "Service occupations", AND(D55>=41, D55<=43), "Sales and office occupations", AND(D55>=51, D55<=53), "Production, transportation, and material moving occupations", AND(D55>=45, D55<=49), "Natural resources, construction, and maintenance occupations", TRUE, "Not applicable to study area" )} -> Natural resources, construction, and maintenance occupations | G55: =SUMIF(F:F, F55, A:A) -> 7339 | H55: =AVERAGEIF(F:F, F55, A:A) -> 59.666667 | I55: =_xlfn.XLOOKUP($C55,'NAICS-SOC-CIP x-walk'!C:C, 'NAICS-SOC-CIP x-walk'!H:H) -> 23 | J55: =_xlfn.XLOOKUP(K55,'ACS-NAICS-SOC x-walk'!K:K,'ACS-NAICS-SOC x-walk'!L:L) -> Construction | K55: =_xlfn.XLOOKUP($C55,'NAICS-SOC-CIP x-walk'!$C:$C, 'NAICS-SOC-CIP x-walk'!I:I) -> Construction | L55: =SUMIF(K:K, K55, A:A) -> 4403 | M55: =AVERAGEIF(K:K, K55, A:A) -> 57.934211
A56: 74 | B56: 3 | C56: 49-9021 | D56: =VALUE(LEFT(C56,2)) -> 49 | E56: Heating, Air Conditioning, and Refrigeration Mechanics and Installers | F56: {=_xlfn.IFS( AND(D56>=11, D56<=29), "Management, business, science, and arts occupations", AND(D56>=31, D56<=39), "Service occupations", AND(D56>=41, D56<=43), "Sales and office occupations", AND(D56>=51, D56<=53), "Production, transportation, and material moving occupations", AND(D56>=45, D56<=49), "Natural resources, construction, and maintenance occupations", TRUE, "Not applicable to study area" )} -> Natural resources, construction, and maintenance occupations | G56: =SUMIF(F:F, F56, A:A) -> 7339 | H56: =AVERAGEIF(F:F, F56, A:A) -> 59.666667 | I56: =_xlfn.XLOOKUP($C56,'NAICS-SOC-CIP x-walk'!C:C, 'NAICS-SOC-CIP x-walk'!H:H) -> 23 | J56: =_xlfn.XLOOKUP(K56,'ACS-NAICS-SOC x-walk'!K:K,'ACS-NAICS-SOC x-walk'!L:L) -> Construction | K56: =_xlfn.XLOOKUP($C56,'NAICS-SOC-CIP x-walk'!$C:$C, 'NAICS-SOC-CIP x-walk'!I:I) -> Construction | L56: =SUMIF(K:K, K56, A:A) -> 4403 | M56: =AVERAGEIF(K:K, K56, A:A) -> 57.934211
A57: 68 | B57: 1-2 | C57: 49-9031 | D57: =VALUE(LEFT(C57,2)) -> 49 | E57: Home Appliance Repairers | F57: {=_xlfn.IFS( AND(D57>=11, D57<=29), "Management, business, science, and arts occupations", AND(D57>=31, D57<=39), "Service occupations", AND(D57>=41, D57<=43), "Sales and office occupations", AND(D57>=51, D57<=53), "Production, transportation, and material moving occupations", AND(D57>=45, D57<=49), "Natural resources, construction, and maintenance occupations", TRUE, "Not applicable to study area" )} -> Natural resources, construction, and maintenance occupations | G57: =SUMIF(F:F, F57, A:A) -> 7339 | H57: =AVERAGEIF(F:F, F57, A:A) -> 59.666667 | I57: =_xlfn.XLOOKUP($C57,'NAICS-SOC-CIP x-walk'!C:C, 'NAICS-SOC-CIP x-walk'!H:H) -> 23 | J57: =_xlfn.XLOOKUP(K57,'ACS-NAICS-SOC x-walk'!K:K,'ACS-NAICS-SOC x-walk'!L:L) -> Construction | K57: =_xlfn.XLOOKUP($C57,'NAICS-SOC-CIP x-walk'!$C:$C, 'NAICS-SOC-CIP x-walk'!I:I) -> Construction | L57: =SUMIF(K:K, K57, A:A) -> 4403 | M57: =AVERAGEIF(K:K, K57, A:A) -> 57.934211
A58: 68 | B58: 3 | C58: 49-9043 | D58: =VALUE(LEFT(C58,2)) -> 49 | E58: Maintenance Workers, Machinery | F58: {=_xlfn.IFS( AND(D58>=11, D58<=29), "Management, business, science, and arts occupations", AND(D58>=31, D58<=39), "Service occupations", AND(D58>=41, D58<=43), "Sales and office occupations", AND(D58>=51, D58<=53), "Production, transportation, and material moving occupations", AND(D58>=45, D58<=49), "Natural resources, construction, and maintenance occupations", TRUE, "Not applicable to study area" )} -> Natural resources, construction, and maintenance occupations | G58: =SUMIF(F:F, F58, A:A) -> 7339 | H58: =AVERAGEIF(F:F, F58, A:A) -> 59.666667 | I58: =_xlfn.XLOOKUP($C58,'NAICS-SOC-CIP x-walk'!C:C, 'NAICS-SOC-CIP x-walk'!H:H) -> 23 | J58: =_xlfn.XLOOKUP(K58,'ACS-NAICS-SOC x-walk'!K:K,'ACS-NAICS-SOC x-walk'!L:L) -> Construction | K58: =_xlfn.XLOOKUP($C58,'NAICS-SOC-CIP x-walk'!$C:$C, 'NAICS-SOC-CIP x-walk'!I:I) -> Construction | L58: =SUMIF(K:K, K58, A:A) -> 4403 | M58: =AVERAGEIF(K:K, K58, A:A) -> 57.934211
A59: 88 | B59: 1-2 | C59: 49-9044 | D59: =VALUE(LEFT(C59,2)) -> 49 | E59: Millwrights | F59: {=_xlfn.IFS( AND(D59>=11, D59<=29), "Management, business, science, and arts occupations", AND(D59>=31, D59<=39), "Service occupations", AND(D59>=41, D59<=43), "Sales and office occupations", AND(D59>=51, D59<=53), "Production, transportation, and material moving occupations", AND(D59>=45, D59<=49), "Natural resources, construction, and maintenance occupations", TRUE, "Not applicable to study area" )} -> Natural resources, construction, and maintenance occupations | G59: =SUMIF(F:F, F59, A:A) -> 7339 | H59: =AVERAGEIF(F:F, F59, A:A) -> 59.666667 | I59: =_xlfn.XLOOKUP($C59,'NAICS-SOC-CIP x-walk'!C:C, 'NAICS-SOC-CIP x-walk'!H:H) -> 23 | J59: =_xlfn.XLOOKUP(K59,'ACS-NAICS-SOC x-walk'!K:K,'ACS-NAICS-SOC x-walk'!L:L) -> Construction | K59: =_xlfn.XLOOKUP($C59,'NAICS-SOC-CIP x-walk'!$C:$C, 'NAICS-SOC-CIP x-walk'!I:I) -> Construction | L59: =SUMIF(K:K, K59, A:A) -> 4403 | M59: =AVERAGEIF(K:K, K59, A:A) -> 57.934211
A60: 99 | B60: 1-2 | C60: 49-9045 | D60: =VALUE(LEFT(C60,2)) -> 49 | E60: Refractory Materials Repairers, Except Brickmasons | F60: {=_xlfn.IFS( AND(D60>=11, D60<=29), "Management, business, science, and arts occupations", AND(D60>=31, D60<=39), "Service occupations", AND(D60>=41, D60<=43), "Sales and office occupations", AND(D60>=51, D60<=53), "Production, transportation, and material moving occupations", AND(D60>=45, D60<=49), "Natural resources, construction, and maintenance occupations", TRUE, "Not applicable to study area" )} -> Natural resources, construction, and maintenance occupations | G60: =SUMIF(F:F, F60, A:A) -> 7339 | H60: =AVERAGEIF(F:F, F60, A:A) -> 59.666667 | I60: =_xlfn.XLOOKUP($C60,'NAICS-SOC-CIP x-walk'!C:C, 'NAICS-SOC-CIP x-walk'!H:H) -> 23 | J60: =_xlfn.XLOOKUP(K60,'ACS-NAICS-SOC x-walk'!K:K,'ACS-NAICS-SOC x-walk'!L:L) -> Construction | K60: =_xlfn.XLOOKUP($C60,'NAICS-SOC-CIP x-walk'!$C:$C, 'NAICS-SOC-CIP x-walk'!I:I) -> Construction | L60: =SUMIF(K:K, K60, A:A) -> 4403 | M60: =AVERAGEIF(K:K, K60, A:A) -> 57.934211
A61: 69 | B61: 3 | C61: 49-9071 | D61: =VALUE(LEFT(C61,2)) -> 49 | E61: Maintenance and Repair Workers, General | F61: {=_xlfn.IFS( AND(D61>=11, D61<=29), "Management, business, science, and arts occupations", AND(D61>=31, D61<=39), "Service occupations", AND(D61>=41, D61<=43), "Sales and office occupations", AND(D61>=51, D61<=53), "Production, transportation, and material moving occupations", AND(D61>=45, D61<=49), "Natural resources, construction, and maintenance occupations", TRUE, "Not applicable to study area" )} -> Natural resources, construction, and maintenance occupations | G61: =SUMIF(F:F, F61, A:A) -> 7339 | H61: =AVERAGEIF(F:F, F61, A:A) -> 59.666667 | I61: =_xlfn.XLOOKUP($C61,'NAICS-SOC-CIP x-walk'!C:C, 'NAICS-SOC-CIP x-walk'!H:H) -> 23 | J61: =_xlfn.XLOOKUP(K61,'ACS-NAICS-SOC x-walk'!K:K,'ACS-NAICS-SOC x-walk'!L:L) -> Construction | K61: =_xlfn.XLOOKUP($C61,'NAICS-SOC-CIP x-walk'!$C:$C, 'NAICS-SOC-CIP x-walk'!I:I) -> Construction | L61: =SUMIF(K:K, K61, A:A) -> 4403 | M61: =AVERAGEIF(K:K, K61, A:A) -> 57.934211
A62: 73 | B62: 1-2 | C62: 49-9094 | D62: =VALUE(LEFT(C62,2)) -> 49 | E62: Locksmiths and Safe Repairers | F62: {=_xlfn.IFS( AND(D62>=11, D62<=29), "Management, business, science, and arts occupations", AND(D62>=31, D62<=39), "Service occupations", AND(D62>=41, D62<=43), "Sales and office occupations", AND(D62>=51, D62<=53), "Production, transportation, and material moving occupations", AND(D62>=45, D62<=49), "Natural resources, construction, and maintenance occupations", TRUE, "Not applicable to study area" )} -> Natural resources, construction, and maintenance occupations | G62: =SUMIF(F:F, F62, A:A) -> 7339 | H62: =AVERAGEIF(F:F, F62, A:A) -> 59.666667 | I62: =_xlfn.XLOOKUP($C62,'NAICS-SOC-CIP x-walk'!C:C, 'NAICS-SOC-CIP x-walk'!H:H) -> 23 | J62: =_xlfn.XLOOKUP(K62,'ACS-NAICS-SOC x-walk'!K:K,'ACS-NAICS-SOC x-walk'!L:L) -> Construction | K62: =_xlfn.XLOOKUP($C62,'NAICS-SOC-CIP x-walk'!$C:$C, 'NAICS-SOC-CIP x-walk'!I:I) -> Construction | L62: =SUMIF(K:K, K62, A:A) -> 4403 | M62: =AVERAGEIF(K:K, K62, A:A) -> 57.934211
A63: 81 | B63: 1-2 | C63: 49-9098 | D63: =VALUE(LEFT(C63,2)) -> 49 | E63: Helpers--Installation, Maintenance, and Repair Workers | F63: {=_xlfn.IFS( AND(D63>=11, D63<=29), "Management, business, science, and arts occupations", AND(D63>=31, D63<=39), "Service occupations", AND(D63>=41, D63<=43), "Sales and office occupations", AND(D63>=51, D63<=53), "Production, transportation, and material moving occupations", AND(D63>=45, D63<=49), "Natural resources, construction, and maintenance occupations", TRUE, "Not applicable to study area" )} -> Natural resources, construction, and maintenance occupations | G63: =SUMIF(F:F, F63, A:A) -> 7339 | H63: =AVERAGEIF(F:F, F63, A:A) -> 59.666667 | I63: =_xlfn.XLOOKUP($C63,'NAICS-SOC-CIP x-walk'!C:C, 'NAICS-SOC-CIP x-walk'!H:H) -> 23 | J63: =_xlfn.XLOOKUP(K63,'ACS-NAICS-SOC x-walk'!K:K,'ACS-NAICS-SOC x-walk'!L:L) -> Construction | K63: =_xlfn.XLOOKUP($C63,'NAICS-SOC-CIP x-walk'!$C:$C, 'NAICS-SOC-CIP x-walk'!I:I) -> Construction | L63: =SUMIF(K:K, K63, A:A) -> 4403 | M63: =AVERAGEIF(K:K, K63, A:A) -> 57.934211
A64: 53 | B64: 3 | C64: 51-4111 | D64: =VALUE(LEFT(C64,2)) -> 51 | E64: Tool and Die Makers | F64: {=_xlfn.IFS( AND(D64>=11, D64<=29), "Management, business, science, and arts occupations", AND(D64>=31, D64<=39), "Service occupations", AND(D64>=41, D64<=43), "Sales and office occupations", AND(D64>=51, D64<=53), "Production, transportation, and material moving occupations", AND(D64>=45, D64<=49), "Natural resources, construction, and maintenance occupations", TRUE, "Not applicable to study area" )} -> Production, transportation, and material moving occupations | G64: =SUMIF(F:F, F64, A:A) -> 7976 | H64: =AVERAGEIF(F:F, F64, A:A) -> 51.458065 | I64: =_xlfn.XLOOKUP($C64,'NAICS-SOC-CIP x-walk'!C:C, 'NAICS-SOC-CIP x-walk'!H:H) -> 23 | J64: =_xlfn.XLOOKUP(K64,'ACS-NAICS-SOC x-walk'!K:K,'ACS-NAICS-SOC x-walk'!L:L) -> Construction | K64: =_xlfn.XLOOKUP($C64,'NAICS-SOC-CIP x-walk'!$C:$C, 'NAICS-SOC-CIP x-walk'!I:I) -> Construction | L64: =SUMIF(K:K, K64, A:A) -> 4403 | M64: =AVERAGEIF(K:K, K64, A:A) -> 57.934211
A65: 73 | B65: 1-2 | C65: 51-4122 | D65: =VALUE(LEFT(C65,2)) -> 51 | E65: Welding, Soldering, and Brazing Machine Setters, Operators, and Tenders | F65: {=_xlfn.IFS( AND(D65>=11, D65<=29), "Management, business, science, and arts occupations", AND(D65>=31, D65<=39), "Service occupations", AND(D65>=41, D65<=43), "Sales and office occupations", AND(D65>=51, D65<=53), "Production, transportation, and material moving occupations", AND(D65>=45, D65<=49), "Natural resources, construction, and maintenance occupations", TRUE, "Not applicable to study area" )} -> Production, transportation, and material moving occupations | G65: =SUMIF(F:F, F65, A:A) -> 7976 | H65: =AVERAGEIF(F:F, F65, A:A) -> 51.458065 | I65: =_xlfn.XLOOKUP($C65,'NAICS-SOC-CIP x-walk'!C:C, 'NAICS-SOC-CIP x-walk'!H:H) -> 23 | J65: =_xlfn.XLOOKUP(K65,'ACS-NAICS-SOC x-walk'!K:K,'ACS-NAICS-SOC x-walk'!L:L) -> Construction | K65: =_xlfn.XLOOKUP($C65,'NAICS-SOC-CIP x-walk'!$C:$C, 'NAICS-SOC-CIP x-walk'!I:I) -> Construction | L65: =SUMIF(K:K, K65, A:A) -> 4403 | M65: =AVERAGEIF(K:K, K65, A:A) -> 57.934211
A66: 60 | B66: 1-2 | C66: 51-9123 | D66: =VALUE(LEFT(C66,2)) -> 51 | E66: Painting, Coating, and Decorating Workers | F66: {=_xlfn.IFS( AND(D66>=11, D66<=29), "Management, business, science, and arts occupations", AND(D66>=31, D66<=39), "Service occupations", AND(D66>=41, D66<=43), "Sales and office occupations", AND(D66>=51, D66<=53), "Production, transportation, and material moving occupations", AND(D66>=45, D66<=49), "Natural resources, construction, and maintenance occupations", TRUE, "Not applicable to study area" )} -> Production, transportation, and material moving occupations | G66: =SUMIF(F:F, F66, A:A) -> 7976 | H66: =AVERAGEIF(F:F, F66, A:A) -> 51.458065 | I66: =_xlfn.XLOOKUP($C66,'NAICS-SOC-CIP x-walk'!C:C, 'NAICS-SOC-CIP x-walk'!H:H) -> 23 | J66: =_xlfn.XLOOKUP(K66,'ACS-NAICS-SOC x-walk'!K:K,'ACS-NAICS-SOC x-walk'!L:L) -> Construction | K66: =_xlfn.XLOOKUP($C66,'NAICS-SOC-CIP x-walk'!$C:$C, 'NAICS-SOC-CIP x-walk'!I:I) -> Construction | L66: =SUMIF(K:K, K66, A:A) -> 4403 | M66: =AVERAGEIF(K:K, K66, A:A) -> 57.934211
A67: 71 | B67: 4 | C67: 11-9021 | D67: =VALUE(LEFT(C67,2)) -> 11 | E67: Construction Managers | F67: {=_xlfn.IFS( AND(D67>=11, D67<=29), "Management, business, science, and arts occupations", AND(D67>=31, D67<=39), "Service occupations", AND(D67>=41, D67<=43), "Sales and office occupations", AND(D67>=51, D67<=53), "Production, transportation, and material moving occupations", AND(D67>=45, D67<=49), "Natural resources, construction, and maintenance occupations", TRUE, "Not applicable to study area" )} -> Management, business, science, and arts occupations | G67: =SUMIF(F:F, F67, A:A) -> 10110 | H67: =AVERAGEIF(F:F, F67, A:A) -> 22.668161 | I67: =_xlfn.XLOOKUP($C67,'NAICS-SOC-CIP x-walk'!C:C, 'NAICS-SOC-CIP x-walk'!H:H) -> 23 | J67: =_xlfn.XLOOKUP(K67,'ACS-NAICS-SOC x-walk'!K:K,'ACS-NAICS-SOC x-walk'!L:L) -> Construction | K67: =_xlfn.XLOOKUP($C67,'NAICS-SOC-CIP x-walk'!$C:$C, 'NAICS-SOC-CIP x-walk'!I:I) -> Construction | L67: =SUMIF(K:K, K67, A:A) -> 4403 | M67: =AVERAGEIF(K:K, K67, A:A) -> 57.934211
A68: 17 | B68: 4 | C68: 13-1051 | D68: =VALUE(LEFT(C68,2)) -> 13 | E68: Cost Estimators | F68: {=_xlfn.IFS( AND(D68>=11, D68<=29), "Management, business, science, and arts occupations", AND(D68>=31, D68<=39), "Service occupations", AND(D68>=41, D68<=43), "Sales and office occupations", AND(D68>=51, D68<=53), "Production, transportation, and material moving occupations", AND(D68>=45, D68<=49), "Natural resources, construction, and maintenance occupations", TRUE, "Not applicable to study area" )} -> Management, business, science, and arts occupations | G68: =SUMIF(F:F, F68, A:A) -> 10110 | H68: =AVERAGEIF(F:F, F68, A:A) -> 22.668161 | I68: =_xlfn.XLOOKUP($C68,'NAICS-SOC-CIP x-walk'!C:C, 'NAICS-SOC-CIP x-walk'!H:H) -> 23 | J68: =_xlfn.XLOOKUP(K68,'ACS-NAICS-SOC x-walk'!K:K,'ACS-NAICS-SOC x-walk'!L:L) -> Construction | K68: =_xlfn.XLOOKUP($C68,'NAICS-SOC-CIP x-walk'!$C:$C, 'NAICS-SOC-CIP x-walk'!I:I) -> Construction | L68: =SUMIF(K:K, K68, A:A) -> 4403 | M68: =AVERAGEIF(K:K, K68, A:A) -> 57.934211
A69: 36 | B69: 5 | C69: 17-1011 | D69: =VALUE(LEFT(C69,2)) -> 17 | E69: Architects, Except Landscape and Naval | F69: {=_xlfn.IFS( AND(D69>=11, D69<=29), "Management, business, science, and arts occupations", AND(D69>=31, D69<=39), "Service occupations", AND(D69>=41, D69<=43), "Sales and office occupations", AND(D69>=51, D69<=53), "Production, transportation, and material moving occupations", AND(D69>=45, D69<=49), "Natural resources, construction, and maintenance occupations", TRUE, "Not applicable to study area" )} -> Management, business, science, and arts occupations | G69: =SUMIF(F:F, F69, A:A) -> 10110 | H69: =AVERAGEIF(F:F, F69, A:A) -> 22.668161 | I69: =_xlfn.XLOOKUP($C69,'NAICS-SOC-CIP x-walk'!C:C, 'NAICS-SOC-CIP x-walk'!H:H) -> 23 | J69: =_xlfn.XLOOKUP(K69,'ACS-NAICS-SOC x-walk'!K:K,'ACS-NAICS-SOC x-walk'!L:L) -> Construction | K69: =_xlfn.XLOOKUP($C69,'NAICS-SOC-CIP x-walk'!$C:$C, 'NAICS-SOC-CIP x-walk'!I:I) -> Construction | L69: =SUMIF(K:K, K69, A:A) -> 4403 | M69: =AVERAGEIF(K:K, K69, A:A) -> 57.934211
A70: 37 | B70: 4 | C70: 17-1012 | D70: =VALUE(LEFT(C70,2)) -> 17 | E70: Landscape Architects | F70: {=_xlfn.IFS( AND(D70>=11, D70<=29), "Management, business, science, and arts occupations", AND(D70>=31, D70<=39), "Service occupations", AND(D70>=41, D70<=43), "Sales and office occupations", AND(D70>=51, D70<=53), "Production, transportation, and material moving occupations", AND(D70>=45, D70<=49), "Natural resources, construction, and maintenance occupations", TRUE, "Not applicable to study area" )} -> Management, business, science, and arts occupations | G70: =SUMIF(F:F, F70, A:A) -> 10110 | H70: =AVERAGEIF(F:F, F70, A:A) -> 22.668161 | I70: =_xlfn.XLOOKUP($C70,'NAICS-SOC-CIP x-walk'!C:C, 'NAICS-SOC-CIP x-walk'!H:H) -> 23 | J70: =_xlfn.XLOOKUP(K70,'ACS-NAICS-SOC x-walk'!K:K,'ACS-NAICS-SOC x-walk'!L:L) -> Construction | K70: =_xlfn.XLOOKUP($C70,'NAICS-SOC-CIP x-walk'!$C:$C, 'NAICS-SOC-CIP x-walk'!I:I) -> Construction | L70: =SUMIF(K:K, K70, A:A) -> 4403 | M70: =AVERAGEIF(K:K, K70, A:A) -> 57.934211
A71: 13 | B71: 4 | C71: 17-1021 | D71: =VALUE(LEFT(C71,2)) -> 17 | E71: Cartographers and Photogrammetrists | F71: {=_xlfn.IFS( AND(D71>=11, D71<=29), "Management, business, science, and arts occupations", AND(D71>=31, D71<=39), "Service occupations", AND(D71>=41, D71<=43), "Sales and office occupations", AND(D71>=51, D71<=53), "Production, transportation, and material moving occupations", AND(D71>=45, D71<=49), "Natural resources, construction, and maintenance occupations", TRUE, "Not applicable to study area" )} -> Management, business, science, and arts occupations | G71: =SUMIF(F:F, F71, A:A) -> 10110 | H71: =AVERAGEIF(F:F, F71, A:A) -> 22.668161 | I71: =_xlfn.XLOOKUP($C71,'NAICS-SOC-CIP x-walk'!C:C, 'NAICS-SOC-CIP x-walk'!H:H) -> 21, 22 | J71: =_xlfn.XLOOKUP(K71,'ACS-NAICS-SOC x-walk'!K:K,'ACS-NAICS-SOC x-walk'!L:L) -> Agriculture, Forestry, Fishing and Hunting, and Mining | K71: =_xlfn.XLOOKUP($C71,'NAICS-SOC-CIP x-walk'!$C:$C, 'NAICS-SOC-CIP x-walk'!I:I) -> Mining, Quarrying, and Oil and Gas Extraction, Utilities | L71: =SUMIF(K:K, K71, A:A) -> 4509 | M71: =AVERAGEIF(K:K, K71, A:A) -> 48.483871
A72: 49 | B72: 4 | C72: 17-1022 | D72: =VALUE(LEFT(C72,2)) -> 17 | E72: Surveyors | F72: {=_xlfn.IFS( AND(D72>=11, D72<=29), "Management, business, science, and arts occupations", AND(D72>=31, D72<=39), "Service occupations", AND(D72>=41, D72<=43), "Sales and office occupations", AND(D72>=51, D72<=53), "Production, transportation, and material moving occupations", AND(D72>=45, D72<=49), "Natural resources, construction, and maintenance occupations", TRUE, "Not applicable to study area" )} -> Management, business, science, and arts occupations | G72: =SUMIF(F:F, F72, A:A) -> 10110 | H72: =AVERAGEIF(F:F, F72, A:A) -> 22.668161 | I72: =_xlfn.XLOOKUP($C72,'NAICS-SOC-CIP x-walk'!C:C, 'NAICS-SOC-CIP x-walk'!H:H) -> 21, 22 | J72: =_xlfn.XLOOKUP(K72,'ACS-NAICS-SOC x-walk'!K:K,'ACS-NAICS-SOC x-walk'!L:L) -> Agriculture, Forestry, Fishing and Hunting, and Mining | K72: =_xlfn.XLOOKUP($C72,'NAICS-SOC-CIP x-walk'!$C:$C, 'NAICS-SOC-CIP x-walk'!I:I) -> Mining, Quarrying, and Oil and Gas Extraction, Utilities | L72: =SUMIF(K:K, K72, A:A) -> 4509 | M72: =AVERAGEIF(K:K, K72, A:A) -> 48.483871
A73: 58 | B73: 4 | C73: 17-1022 | D73: =VALUE(LEFT(C73,2)) -> 17 | E73: Geodetic Surveyors | F73: {=_xlfn.IFS( AND(D73>=11, D73<=29), "Management, business, science, and arts occupations", AND(D73>=31, D73<=39), "Service occupations", AND(D73>=41, D73<=43), "Sales and office occupations", AND(D73>=51, D73<=53), "Production, transportation, and material moving occupations", AND(D73>=45, D73<=49), "Natural resources, construction, and maintenance occupations", TRUE, "Not applicable to study area" )} -> Management, business, science, and arts occupations | G73: =SUMIF(F:F, F73, A:A) -> 10110 | H73: =AVERAGEIF(F:F, F73, A:A) -> 22.668161 | I73: =_xlfn.XLOOKUP($C73,'NAICS-SOC-CIP x-walk'!C:C, 'NAICS-SOC-CIP x-walk'!H:H) -> 21, 22 | J73: =_xlfn.XLOOKUP(K73,'ACS-NAICS-SOC x-walk'!K:K,'ACS-NAICS-SOC x-walk'!L:L) -> Agriculture, Forestry, Fishing and Hunting, and Mining | K73: =_xlfn.XLOOKUP($C73,'NAICS-SOC-CIP x-walk'!$C:$C, 'NAICS-SOC-CIP x-walk'!I:I) -> Mining, Quarrying, and Oil and Gas Extraction, Utilities | L73: =SUMIF(K:K, K73, A:A) -> 4509 | M73: =AVERAGEIF(K:K, K73, A:A) -> 48.483871
A74: 44 | B74: 4 | C74: 17-2051 | D74: =VALUE(LEFT(C74,2)) -> 17 | E74: Civil Engineers | F74: {=_xlfn.IFS( AND(D74>=11, D74<=29), "Management, business, science, and arts occupations", AND(D74>=31, D74<=39), "Service occupations", AND(D74>=41, D74<=43), "Sales and office occupations", AND(D74>=51, D74<=53), "Production, transportation, and material moving occupations", AND(D74>=45, D74<=49), "Natural resources, construction, and maintenance occupations", TRUE, "Not applicable to study area" )} -> Management, business, science, and arts occupations | G74: =SUMIF(F:F, F74, A:A) -> 10110 | H74: =AVERAGEIF(F:F, F74, A:A) -> 22.668161 | I74: =_xlfn.XLOOKUP($C74,'NAICS-SOC-CIP x-walk'!C:C, 'NAICS-SOC-CIP x-walk'!H:H) -> 23 | J74: =_xlfn.XLOOKUP(K74,'ACS-NAICS-SOC x-walk'!K:K,'ACS-NAICS-SOC x-walk'!L:L) -> Construction | K74: =_xlfn.XLOOKUP($C74,'NAICS-SOC-CIP x-walk'!$C:$C, 'NAICS-SOC-CIP x-walk'!I:I) -> Construction | L74: =SUMIF(K:K, K74, A:A) -> 4403 | M74: =AVERAGEIF(K:K, K74, A:A) -> 57.934211
A75: 33 | B75: 4 | C75: 17-2051 | D75: =VALUE(LEFT(C75,2)) -> 17 | E75: Transportation Engineers | F75: {=_xlfn.IFS( AND(D75>=11, D75<=29), "Management, business, science, and arts occupations", AND(D75>=31, D75<=39), "Service occupations", AND(D75>=41, D75<=43), "Sales and office occupations", AND(D75>=51, D75<=53), "Production, transportation, and material moving occupations", AND(D75>=45, D75<=49), "Natural resources, construction, and maintenance occupations", TRUE, "Not applicable to study area" )} -> Management, business, science, and arts occupations | G75: =SUMIF(F:F, F75, A:A) -> 10110 | H75: =AVERAGEIF(F:F, F75, A:A) -> 22.668161 | I75: =_xlfn.XLOOKUP($C75,'NAICS-SOC-CIP x-walk'!C:C, 'NAICS-SOC-CIP x-walk'!H:H) -> 23 | J75: =_xlfn.XLOOKUP(K75,'ACS-NAICS-SOC x-walk'!K:K,'ACS-NAICS-SOC x-walk'!L:L) -> Construction | K75: =_xlfn.XLOOKUP($C75,'NAICS-SOC-CIP x-walk'!$C:$C, 'NAICS-SOC-CIP x-walk'!I:I) -> Construction | L75: =SUMIF(K:K, K75, A:A) -> 4403 | M75: =AVERAGEIF(K:K, K75, A:A) -> 57.934211
A76: 34 | B76: 4 | C76: 17-2051 | D76: =VALUE(LEFT(C76,2)) -> 17 | E76: Water/Wastewater Engineers | F76: {=_xlfn.IFS( AND(D76>=11, D76<=29), "Management, business, science, and arts occupations", AND(D76>=31, D76<=39), "Service occupations", AND(D76>=41, D76<=43), "Sales and office occupations", AND(D76>=51, D76<=53), "Production, transportation, and material moving occupations", AND(D76>=45, D76<=49), "Natural resources, construction, and maintenance occupations", TRUE, "Not applicable to study area" )} -> Management, business, science, and arts occupations | G76: =SUMIF(F:F, F76, A:A) -> 10110 | H76: =AVERAGEIF(F:F, F76, A:A) -> 22.668161 | I76: =_xlfn.XLOOKUP($C76,'NAICS-SOC-CIP x-walk'!C:C, 'NAICS-SOC-CIP x-walk'!H:H) -> 23 | J76: =_xlfn.XLOOKUP(K76,'ACS-NAICS-SOC x-walk'!K:K,'ACS-NAICS-SOC x-walk'!L:L) -> Construction | K76: =_xlfn.XLOOKUP($C76,'NAICS-SOC-CIP x-walk'!$C:$C, 'NAICS-SOC-CIP x-walk'!I:I) -> Construction | L76: =SUMIF(K:K, K76, A:A) -> 4403 | M76: =AVERAGEIF(K:K, K76, A:A) -> 57.934211
A77: 20 | B77: 3 | C77: 17-3011 | D77: =VALUE(LEFT(C77,2)) -> 17 | E77: Architectural and Civil Drafters | F77: {=_xlfn.IFS( AND(D77>=11, D77<=29), "Management, business, science, and arts occupations", AND(D77>=31, D77<=39), "Service occupations", AND(D77>=41, D77<=43), "Sales and office occupations", AND(D77>=51, D77<=53), "Production, transportation, and material moving occupations", AND(D77>=45, D77<=49), "Natural resources, construction, and maintenance occupations", TRUE, "Not applicable to study area" )} -> Management, business, science, and arts occupations | G77: =SUMIF(F:F, F77, A:A) -> 10110 | H77: =AVERAGEIF(F:F, F77, A:A) -> 22.668161 | I77: =_xlfn.XLOOKUP($C77,'NAICS-SOC-CIP x-walk'!C:C, 'NAICS-SOC-CIP x-walk'!H:H) -> 23 | J77: =_xlfn.XLOOKUP(K77,'ACS-NAICS-SOC x-walk'!K:K,'ACS-NAICS-SOC x-walk'!L:L) -> Construction | K77: =_xlfn.XLOOKUP($C77,'NAICS-SOC-CIP x-walk'!$C:$C, 'NAICS-SOC-CIP x-walk'!I:I) -> Construction | L77: =SUMIF(K:K, K77, A:A) -> 4403 | M77: =AVERAGEIF(K:K, K77, A:A) -> 57.934211
A78: 38 | B78: 3 | C78: 17-3022 | D78: =VALUE(LEFT(C78,2)) -> 17 | E78: Civil Engineering Technologists and Technicians | F78: {=_xlfn.IFS( AND(D78>=11, D78<=29), "Management, business, science, and arts occupations", AND(D78>=31, D78<=39), "Service occupations", AND(D78>=41, D78<=43), "Sales and office occupations", AND(D78>=51, D78<=53), "Production, transportation, and material moving occupations", AND(D78>=45, D78<=49), "Natural resources, construction, and maintenance occupations", TRUE, "Not applicable to study area" )} -> Management, business, science, and arts occupations | G78: =SUMIF(F:F, F78, A:A) -> 10110 | H78: =AVERAGEIF(F:F, F78, A:A) -> 22.668161 | I78: =_xlfn.XLOOKUP($C78,'NAICS-SOC-CIP x-walk'!C:C, 'NAICS-SOC-CIP x-walk'!H:H) -> 21, 22 | J78: =_xlfn.XLOOKUP(K78,'ACS-NAICS-SOC x-walk'!K:K,'ACS-NAICS-SOC x-walk'!L:L) -> Agriculture, Forestry, Fishing and Hunting, and Mining | K78: =_xlfn.XLOOKUP($C78,'NAICS-SOC-CIP x-walk'!$C:$C, 'NAICS-SOC-CIP x-walk'!I:I) -> Mining, Quarrying, and Oil and Gas Extraction, Utilities | L78: =SUMIF(K:K, K78, A:A) -> 4509 | M78: =AVERAGEIF(K:K, K78, A:A) -> 48.483871
A79: 23 | B79: 5 | C79: 19-3051 | D79: =VALUE(LEFT(C79,2)) -> 19 | E79: Urban and Regional Planners | F79: {=_xlfn.IFS( AND(D79>=11, D79<=29), "Management, business, science, and arts occupations", AND(D79>=31, D79<=39), "Service occupations", AND(D79>=41, D79<=43), "Sales and office occupations", AND(D79>=51, D79<=53), "Production, transportation, and material moving occupations", AND(D79>=45, D79<=49), "Natural resources, construction, and maintenance occupations", TRUE, "Not applicable to study area" )} -> Management, business, science, and arts occupations | G79: =SUMIF(F:F, F79, A:A) -> 10110 | H79: =AVERAGEIF(F:F, F79, A:A) -> 22.668161 | I79: =_xlfn.XLOOKUP($C79,'NAICS-SOC-CIP x-walk'!C:C, 'NAICS-SOC-CIP x-walk'!H:H) -> 23 | J79: =_xlfn.XLOOKUP(K79,'ACS-NAICS-SOC x-walk'!K:K,'ACS-NAICS-SOC x-walk'!L:L) -> Construction | K79: =_xlfn.XLOOKUP($C79,'NAICS-SOC-CIP x-walk'!$C:$C, 'NAICS-SOC-CIP x-walk'!I:I) -> Construction | L79: =SUMIF(K:K, K79, A:A) -> 4403 | M79: =AVERAGEIF(K:K, K79, A:A) -> 57.934211
A80: 40 | B80: 1-2 | C80: 47-4061 | D80: =VALUE(LEFT(C80,2)) -> 47 | E80: Rail-Track Laying and Maintenance Equipment Operators | F80: {=_xlfn.IFS( AND(D80>=11, D80<=29), "Management, business, science, and arts occupations", AND(D80>=31, D80<=39), "Service occupations", AND(D80>=41, D80<=43), "Sales and office occupations", AND(D80>=51, D80<=53), "Production, transportation, and material moving occupations", AND(D80>=45, D80<=49), "Natural resources, construction, and maintenance occupations", TRUE, "Not applicable to study area" )} -> Natural resources, construction, and maintenance occupations | G80: =SUMIF(F:F, F80, A:A) -> 7339 | H80: =AVERAGEIF(F:F, F80, A:A) -> 59.666667 | I80: =_xlfn.XLOOKUP($C80,'NAICS-SOC-CIP x-walk'!C:C, 'NAICS-SOC-CIP x-walk'!H:H) -> 42, 48-49 | J80: =_xlfn.XLOOKUP(K80,'ACS-NAICS-SOC x-walk'!K:K,'ACS-NAICS-SOC x-walk'!L:L) -> Wholesale Trade | K80: =_xlfn.XLOOKUP($C80,'NAICS-SOC-CIP x-walk'!$C:$C, 'NAICS-SOC-CIP x-walk'!I:I) -> Wholesale Trade, Transportation and Warehousing | L80: =SUMIF(K:K, K80, A:A) -> 3770 | M80: =AVERAGEIF(K:K, K80, A:A) -> 53.857143
A81: 53 | B81: 3 | C81: 49-2091 | D81: =VALUE(LEFT(C81,2)) -> 49 | E81: Avionics Technicians | F81: {=_xlfn.IFS( AND(D81>=11, D81<=29), "Management, business, science, and arts occupations", AND(D81>=31, D81<=39), "Service occupations", AND(D81>=41, D81<=43), "Sales and office occupations", AND(D81>=51, D81<=53), "Production, transportation, and material moving occupations", AND(D81>=45, D81<=49), "Natural resources, construction, and maintenance occupations", TRUE, "Not applicable to study area" )} -> Natural resources, construction, and maintenance occupations | G81: =SUMIF(F:F, F81, A:A) -> 7339 | H81: =AVERAGEIF(F:F, F81, A:A) -> 59.666667 | I81: =_xlfn.XLOOKUP($C81,'NAICS-SOC-CIP x-walk'!C:C, 'NAICS-SOC-CIP x-walk'!H:H) -> 42, 48-49 | J81: =_xlfn.XLOOKUP(K81,'ACS-NAICS-SOC x-walk'!K:K,'ACS-NAICS-SOC x-walk'!L:L) -> Wholesale Trade | K81: =_xlfn.XLOOKUP($C81,'NAICS-SOC-CIP x-walk'!$C:$C, 'NAICS-SOC-CIP x-walk'!I:I) -> Wholesale Trade, Transportation and Warehousing | L81: =SUMIF(K:K, K81, A:A) -> 3770 | M81: =AVERAGEIF(K:K, K81, A:A) -> 53.857143
A82: 73 | B82: 3 | C82: 49-2093 | D82: =VALUE(LEFT(C82,2)) -> 49 | E82: Electrical and Electronics Installers and Repairers, Transportation Equipment | F82: {=_xlfn.IFS( AND(D82>=11, D82<=29), "Management, business, science, and arts occupations", AND(D82>=31, D82<=39), "Service occupations", AND(D82>=41, D82<=43), "Sales and office occupations", AND(D82>=51, D82<=53), "Production, transportation, and material moving occupations", AND(D82>=45, D82<=49), "Natural resources, construction, and maintenance occupations", TRUE, "Not applicable to study area" )} -> Natural resources, construction, and maintenance occupations | G82: =SUMIF(F:F, F82, A:A) -> 7339 | H82: =AVERAGEIF(F:F, F82, A:A) -> 59.666667 | I82: =_xlfn.XLOOKUP($C82,'NAICS-SOC-CIP x-walk'!C:C, 'NAICS-SOC-CIP x-walk'!H:H) -> 42, 48-49 | J82: =_xlfn.XLOOKUP(K82,'ACS-NAICS-SOC x-walk'!K:K,'ACS-NAICS-SOC x-walk'!L:L) -> Wholesale Trade | K82: =_xlfn.XLOOKUP($C82,'NAICS-SOC-CIP x-walk'!$C:$C, 'NAICS-SOC-CIP x-walk'!I:I) -> Wholesale Trade, Transportation and Warehousing | L82: =SUMIF(K:K, K82, A:A) -> 3770 | M82: =AVERAGEIF(K:K, K82, A:A) -> 53.857143
A83: 74 | B83: 3 | C83: 49-2096 | D83: =VALUE(LEFT(C83,2)) -> 49 | E83: Electronic Equipment Installers and Repairers, Motor Vehicles | F83: {=_xlfn.IFS( AND(D83>=11, D83<=29), "Management, business, science, and arts occupations", AND(D83>=31, D83<=39), "Service occupations", AND(D83>=41, D83<=43), "Sales and office occupations", AND(D83>=51, D83<=53), "Production, transportation, and material moving occupations", AND(D83>=45, D83<=49), "Natural resources, construction, and maintenance occupations", TRUE, "Not applicable to study area" )} -> Natural resources, construction, and maintenance occupations | G83: =SUMIF(F:F, F83, A:A) -> 7339 | H83: =AVERAGEIF(F:F, F83, A:A) -> 59.666667 | I83: =_xlfn.XLOOKUP($C83,'NAICS-SOC-CIP x-walk'!C:C, 'NAICS-SOC-CIP x-walk'!H:H) -> 42, 48-49 | J83: =_xlfn.XLOOKUP(K83,'ACS-NAICS-SOC x-walk'!K:K,'ACS-NAICS-SOC x-walk'!L:L) -> Wholesale Trade | K83: =_xlfn.XLOOKUP($C83,'NAICS-SOC-CIP x-walk'!$C:$C, 'NAICS-SOC-CIP x-walk'!I:I) -> Wholesale Trade, Transportation and Warehousing | L83: =SUMIF(K:K, K83, A:A) -> 3770 | M83: =AVERAGEIF(K:K, K83, A:A) -> 53.857143
A84: 93 | B84: 3 | C84: 49-3011 | D84: =VALUE(LEFT(C84,2)) -> 49 | E84: Aircraft Mechanics and Service Technicians | F84: {=_xlfn.IFS( AND(D84>=11, D84<=29), "Management, business, science, and arts occupations", AND(D84>=31, D84<=39), "Service occupations", AND(D84>=41, D84<=43), "Sales and office occupations", AND(D84>=51, D84<=53), "Production, transportation, and material moving occupations", AND(D84>=45, D84<=49), "Natural resources, construction, and maintenance occupations", TRUE, "Not applicable to study area" )} -> Natural resources, construction, and maintenance occupations | G84: =SUMIF(F:F, F84, A:A) -> 7339 | H84: =AVERAGEIF(F:F, F84, A:A) -> 59.666667 | I84: =_xlfn.XLOOKUP($C84,'NAICS-SOC-CIP x-walk'!C:C, 'NAICS-SOC-CIP x-walk'!H:H) -> 42, 48-49 | J84: =_xlfn.XLOOKUP(K84,'ACS-NAICS-SOC x-walk'!K:K,'ACS-NAICS-SOC x-walk'!L:L) -> Wholesale Trade | K84: =_xlfn.XLOOKUP($C84,'NAICS-SOC-CIP x-walk'!$C:$C, 'NAICS-SOC-CIP x-walk'!I:I) -> Wholesale Trade, Transportation and Warehousing | L84: =SUMIF(K:K, K84, A:A) -> 3770 | M84: =AVERAGEIF(K:K, K84, A:A) -> 53.857143
A85: 77 | B85: 1-2 | C85: 49-3021 | D85: =VALUE(LEFT(C85,2)) -> 49 | E85: Automotive Body and Related Repairers | F85: {=_xlfn.IFS( AND(D85>=11, D85<=29), "Management, business, science, and arts occupations", AND(D85>=31, D85<=39), "Service occupations", AND(D85>=41, D85<=43), "Sales and office occupations", AND(D85>=51, D85<=53), "Production, transportation, and material moving occupations", AND(D85>=45, D85<=49), "Natural resources, construction, and maintenance occupations", TRUE, "Not applicable to study area" )} -> Natural resources, construction, and maintenance occupations | G85: =SUMIF(F:F, F85, A:A) -> 7339 | H85: =AVERAGEIF(F:F, F85, A:A) -> 59.666667 | I85: =_xlfn.XLOOKUP($C85,'NAICS-SOC-CIP x-walk'!C:C, 'NAICS-SOC-CIP x-walk'!H:H) -> 42, 48-49 | J85: =_xlfn.XLOOKUP(K85,'ACS-NAICS-SOC x-walk'!K:K,'ACS-NAICS-SOC x-walk'!L:L) -> Wholesale Trade | K85: =_xlfn.XLOOKUP($C85,'NAICS-SOC-CIP x-walk'!$C:$C, 'NAICS-SOC-CIP x-walk'!I:I) -> Wholesale Trade, Transportation and Warehousing | L85: =SUMIF(K:K, K85, A:A) -> 3770 | M85: =AVERAGEIF(K:K, K85, A:A) -> 53.857143
A86: 78 | B86: 1-2 | C86: 49-3022 | D86: =VALUE(LEFT(C86,2)) -> 49 | E86: Automotive Glass Installers and Repairers | F86: {=_xlfn.IFS( AND(D86>=11, D86<=29), "Management, business, science, and arts occupations", AND(D86>=31, D86<=39), "Service occupations", AND(D86>=41, D86<=43), "Sales and office occupations", AND(D86>=51, D86<=53), "Production, transportation, and material moving occupations", AND(D86>=45, D86<=49), "Natural resources, construction, and maintenance occupations", TRUE, "Not applicable to study area" )} -> Natural resources, construction, and maintenance occupations | G86: =SUMIF(F:F, F86, A:A) -> 7339 | H86: =AVERAGEIF(F:F, F86, A:A) -> 59.666667 | I86: =_xlfn.XLOOKUP($C86,'NAICS-SOC-CIP x-walk'!C:C, 'NAICS-SOC-CIP x-walk'!H:H) -> 42, 48-49 | J86: =_xlfn.XLOOKUP(K86,'ACS-NAICS-SOC x-walk'!K:K,'ACS-NAICS-SOC x-walk'!L:L) -> Wholesale Trade | K86: =_xlfn.XLOOKUP($C86,'NAICS-SOC-CIP x-walk'!$C:$C, 'NAICS-SOC-CIP x-walk'!I:I) -> Wholesale Trade, Transportation and Warehousing | L86: =SUMIF(K:K, K86, A:A) -> 3770 | M86: =AVERAGEIF(K:K, K86, A:A) -> 53.857143
A87: 69 | B87: 3 | C87: 49-3023 | D87: =VALUE(LEFT(C87,2)) -> 49 | E87: Automotive Service Technicians and Mechanics | F87: {=_xlfn.IFS( AND(D87>=11, D87<=29), "Management, business, science, and arts occupations", AND(D87>=31, D87<=39), "Service occupations", AND(D87>=41, D87<=43), "Sales and office occupations", AND(D87>=51, D87<=53), "Production, transportation, and material moving occupations", AND(D87>=45, D87<=49), "Natural resources, construction, and maintenance occupations", TRUE, "Not applicable to study area" )} -> Natural resources, construction, and maintenance occupations | G87: =SUMIF(F:F, F87, A:A) -> 7339 | H87: =AVERAGEIF(F:F, F87, A:A) -> 59.666667 | I87: =_xlfn.XLOOKUP($C87,'NAICS-SOC-CIP x-walk'!C:C, 'NAICS-SOC-CIP x-walk'!H:H) -> 42, 48-49 | J87: =_xlfn.XLOOKUP(K87,'ACS-NAICS-SOC x-walk'!K:K,'ACS-NAICS-SOC x-walk'!L:L) -> Wholesale Trade | K87: =_xlfn.XLOOKUP($C87,'NAICS-SOC-CIP x-walk'!$C:$C, 'NAICS-SOC-CIP x-walk'!I:I) -> Wholesale Trade, Transportation and Warehousing | L87: =SUMIF(K:K, K87, A:A) -> 3770 | M87: =AVERAGEIF(K:K, K87, A:A) -> 53.857143
A88: 88 | B88: 3 | C88: 49-3031 | D88: =VALUE(LEFT(C88,2)) -> 49 | E88: Bus and Truck Mechanics and Diesel Engine Specialists | F88: {=_xlfn.IFS( AND(D88>=11, D88<=29), "Management, business, science, and arts occupations", AND(D88>=31, D88<=39), "Service occupations", AND(D88>=41, D88<=43), "Sales and office occupations", AND(D88>=51, D88<=53), "Production, transportation, and material moving occupations", AND(D88>=45, D88<=49), "Natural resources, construction, and maintenance occupations", TRUE, "Not applicable to study area" )} -> Natural resources, construction, and maintenance occupations | G88: =SUMIF(F:F, F88, A:A) -> 7339 | H88: =AVERAGEIF(F:F, F88, A:A) -> 59.666667 | I88: =_xlfn.XLOOKUP($C88,'NAICS-SOC-CIP x-walk'!C:C, 'NAICS-SOC-CIP x-walk'!H:H) -> 42, 48-49 | J88: =_xlfn.XLOOKUP(K88,'ACS-NAICS-SOC x-walk'!K:K,'ACS-NAICS-SOC x-walk'!L:L) -> Wholesale Trade | K88: =_xlfn.XLOOKUP($C88,'NAICS-SOC-CIP x-walk'!$C:$C, 'NAICS-SOC-CIP x-walk'!I:I) -> Wholesale Trade, Transportation and Warehousing | L88: =SUMIF(K:K, K88, A:A) -> 3770 | M88: =AVERAGEIF(K:K, K88, A:A) -> 53.857143
A89: 85 | B89: 1-2 | C89: 49-3043 | D89: =VALUE(LEFT(C89,2)) -> 49 | E89: Rail Car Repairers | F89: {=_xlfn.IFS( AND(D89>=11, D89<=29), "Management, business, science, and arts occupations", AND(D89>=31, D89<=39), "Service occupations", AND(D89>=41, D89<=43), "Sales and office occupations", AND(D89>=51, D89<=53), "Production, transportation, and material moving occupations", AND(D89>=45, D89<=49), "Natural resources, construction, and maintenance occupations", TRUE, "Not applicable to study area" )} -> Natural resources, construction, and maintenance occupations | G89: =SUMIF(F:F, F89, A:A) -> 7339 | H89: =AVERAGEIF(F:F, F89, A:A) -> 59.666667 | I89: =_xlfn.XLOOKUP($C89,'NAICS-SOC-CIP x-walk'!C:C, 'NAICS-SOC-CIP x-walk'!H:H) -> 42, 48-49 | J89: =_xlfn.XLOOKUP(K89,'ACS-NAICS-SOC x-walk'!K:K,'ACS-NAICS-SOC x-walk'!L:L) -> Wholesale Trade | K89: =_xlfn.XLOOKUP($C89,'NAICS-SOC-CIP x-walk'!$C:$C, 'NAICS-SOC-CIP x-walk'!I:I) -> Wholesale Trade, Transportation and Warehousing | L89: =SUMIF(K:K, K89, A:A) -> 3770 | M89: =AVERAGEIF(K:K, K89, A:A) -> 53.857143
A90: 86 | B90: 3 | C90: 49-3051 | D90: =VALUE(LEFT(C90,2)) -> 49 | E90: Motorboat Mechanics and Service Technicians | F90: {=_xlfn.IFS( AND(D90>=11, D90<=29), "Management, business, science, and arts occupations", AND(D90>=31, D90<=39), "Service occupations", AND(D90>=41, D90<=43), "Sales and office occupations", AND(D90>=51, D90<=53), "Production, transportation, and material moving occupations", AND(D90>=45, D90<=49), "Natural resources, construction, and maintenance occupations", TRUE, "Not applicable to study area" )} -> Natural resources, construction, and maintenance occupations | G90: =SUMIF(F:F, F90, A:A) -> 7339 | H90: =AVERAGEIF(F:F, F90, A:A) -> 59.666667 | I90: =_xlfn.XLOOKUP($C90,'NAICS-SOC-CIP x-walk'!C:C, 'NAICS-SOC-CIP x-walk'!H:H) -> 42, 48-49 | J90: =_xlfn.XLOOKUP(K90,'ACS-NAICS-SOC x-walk'!K:K,'ACS-NAICS-SOC x-walk'!L:L) -> Wholesale Trade | K90: =_xlfn.XLOOKUP($C90,'NAICS-SOC-CIP x-walk'!$C:$C, 'NAICS-SOC-CIP x-walk'!I:I) -> Wholesale Trade, Transportation and Warehousing | L90: =SUMIF(K:K, K90, A:A) -> 3770 | M90: =AVERAGEIF(K:K, K90, A:A) -> 53.857143
A91: 40 | B91: 3 | C91: 49-3052 | D91: =VALUE(LEFT(C91,2)) -> 49 | E91: Motorcycle Mechanics | F91: {=_xlfn.IFS( AND(D91>=11, D91<=29), "Management, business, science, and arts occupations", AND(D91>=31, D91<=39), "Service occupations", AND(D91>=41, D91<=43), "Sales and office occupations", AND(D91>=51, D91<=53), "Production, transportation, and material moving occupations", AND(D91>=45, D91<=49), "Natural resources, construction, and maintenance occupations", TRUE, "Not applicable to study area" )} -> Natural resources, construction, and maintenance occupations | G91: =SUMIF(F:F, F91, A:A) -> 7339 | H91: =AVERAGEIF(F:F, F91, A:A) -> 59.666667 | I91: =_xlfn.XLOOKUP($C91,'NAICS-SOC-CIP x-walk'!C:C, 'NAICS-SOC-CIP x-walk'!H:H) -> 42, 48-49 | J91: =_xlfn.XLOOKUP(K91,'ACS-NAICS-SOC x-walk'!K:K,'ACS-NAICS-SOC x-walk'!L:L) -> Wholesale Trade | K91: =_xlfn.XLOOKUP($C91,'NAICS-SOC-CIP x-walk'!$C:$C, 'NAICS-SOC-CIP x-walk'!I:I) -> Wholesale Trade, Transportation and Warehousing | L91: =SUMIF(K:K, K91, A:A) -> 3770 | M91: =AVERAGEIF(K:K, K91, A:A) -> 53.857143
A92: 25 | B92: 1-2 | C92: 49-3091 | D92: =VALUE(LEFT(C92,2)) -> 49 | E92: Bicycle Repairers | F92: {=_xlfn.IFS( AND(D92>=11, D92<=29), "Management, business, science, and arts occupations", AND(D92>=31, D92<=39), "Service occupations", AND(D92>=41, D92<=43), "Sales and office occupations", AND(D92>=51, D92<=53), "Production, transportation, and material moving occupations", AND(D92>=45, D92<=49), "Natural resources, construction, and maintenance occupations", TRUE, "Not applicable to study area" )} -> Natural resources, construction, and maintenance occupations | G92: =SUMIF(F:F, F92, A:A) -> 7339 | H92: =AVERAGEIF(F:F, F92, A:A) -> 59.666667 | I92: =_xlfn.XLOOKUP($C92,'NAICS-SOC-CIP x-walk'!C:C, 'NAICS-SOC-CIP x-walk'!H:H) -> 42, 48-49 | J92: =_xlfn.XLOOKUP(K92,'ACS-NAICS-SOC x-walk'!K:K,'ACS-NAICS-SOC x-walk'!L:L) -> Wholesale Trade | K92: =_xlfn.XLOOKUP($C92,'NAICS-SOC-CIP x-walk'!$C:$C, 'NAICS-SOC-CIP x-walk'!I:I) -> Wholesale Trade, Transportation and Warehousing | L92: =SUMIF(K:K, K92, A:A) -> 3770 | M92: =AVERAGEIF(K:K, K92, A:A) -> 53.857143
A93: 89 | B93: 1-2 | C93: 49-3092 | D93: =VALUE(LEFT(C93,2)) -> 49 | E93: Recreational Vehicle Service Technicians | F93: {=_xlfn.IFS( AND(D93>=11, D93<=29), "Management, business, science, and arts occupations", AND(D93>=31, D93<=39), "Service occupations", AND(D93>=41, D93<=43), "Sales and office occupations", AND(D93>=51, D93<=53), "Production, transportation, and material moving occupations", AND(D93>=45, D93<=49), "Natural resources, construction, and maintenance occupations", TRUE, "Not applicable to study area" )} -> Natural resources, construction, and maintenance occupations | G93: =SUMIF(F:F, F93, A:A) -> 7339 | H93: =AVERAGEIF(F:F, F93, A:A) -> 59.666667 | I93: =_xlfn.XLOOKUP($C93,'NAICS-SOC-CIP x-walk'!C:C, 'NAICS-SOC-CIP x-walk'!H:H) -> 42, 48-49 | J93: =_xlfn.XLOOKUP(K93,'ACS-NAICS-SOC x-walk'!K:K,'ACS-NAICS-SOC x-walk'!L:L) -> Wholesale Trade | K93: =_xlfn.XLOOKUP($C93,'NAICS-SOC-CIP x-walk'!$C:$C, 'NAICS-SOC-CIP x-walk'!I:I) -> Wholesale Trade, Transportation and Warehousing | L93: =SUMIF(K:K, K93, A:A) -> 3770 | M93: =AVERAGEIF(K:K, K93, A:A) -> 53.857143
A94: 91 | B94: 1-2 | C94: 49-3093 | D94: =VALUE(LEFT(C94,2)) -> 49 | E94: Tire Repairers and Changers | F94: {=_xlfn.IFS( AND(D94>=11, D94<=29), "Management, business, science, and arts occupations", AND(D94>=31, D94<=39), "Service occupations", AND(D94>=41, D94<=43), "Sales and office occupations", AND(D94>=51, D94<=53), "Production, transportation, and material moving occupations", AND(D94>=45, D94<=49), "Natural resources, construction, and maintenance occupations", TRUE, "Not applicable to study area" )} -> Natural resources, construction, and maintenance occupations | G94: =SUMIF(F:F, F94, A:A) -> 7339 | H94: =AVERAGEIF(F:F, F94, A:A) -> 59.666667 | I94: =_xlfn.XLOOKUP($C94,'NAICS-SOC-CIP x-walk'!C:C, 'NAICS-SOC-CIP x-walk'!H:H) -> 42, 48-49 | J94: =_xlfn.XLOOKUP(K94,'ACS-NAICS-SOC x-walk'!K:K,'ACS-NAICS-SOC x-walk'!L:L) -> Wholesale Trade | K94: =_xlfn.XLOOKUP($C94,'NAICS-SOC-CIP x-walk'!$C:$C, 'NAICS-SOC-CIP x-walk'!I:I) -> Wholesale Trade, Transportation and Warehousing | L94: =SUMIF(K:K, K94, A:A) -> 3770 | M94: =AVERAGEIF(K:K, K94, A:A) -> 53.857143
A95: 67 | B95: 3 | C95: 49-9092 | D95: =VALUE(LEFT(C95,2)) -> 49 | E95: Commercial Divers | F95: {=_xlfn.IFS( AND(D95>=11, D95<=29), "Management, business, science, and arts occupations", AND(D95>=31, D95<=39), "Service occupations", AND(D95>=41, D95<=43), "Sales and office occupations", AND(D95>=51, D95<=53), "Production, transportation, and material moving occupations", AND(D95>=45, D95<=49), "Natural resources, construction, and maintenance occupations", TRUE, "Not applicable to study area" )} -> Natural resources, construction, and maintenance occupations | G95: =SUMIF(F:F, F95, A:A) -> 7339 | H95: =AVERAGEIF(F:F, F95, A:A) -> 59.666667 | I95: =_xlfn.XLOOKUP($C95,'NAICS-SOC-CIP x-walk'!C:C, 'NAICS-SOC-CIP x-walk'!H:H) -> 42, 48-49 | J95: =_xlfn.XLOOKUP(K95,'ACS-NAICS-SOC x-walk'!K:K,'ACS-NAICS-SOC x-walk'!L:L) -> Wholesale Trade | K95: =_xlfn.XLOOKUP($C95,'NAICS-SOC-CIP x-walk'!$C:$C, 'NAICS-SOC-CIP x-walk'!I:I) -> Wholesale Trade, Transportation and Warehousing | L95: =SUMIF(K:K, K95, A:A) -> 3770 | M95: =AVERAGEIF(K:K, K95, A:A) -> 53.857143
A96: 61 | B96: 3 | C96: 49-9097 | D96: =VALUE(LEFT(C96,2)) -> 49 | E96: Signal and Track Switch Repairers | F96: {=_xlfn.IFS( AND(D96>=11, D96<=29), "Management, business, science, and arts occupations", AND(D96>=31, D96<=39), "Service occupations", AND(D96>=41, D96<=43), "Sales and office occupations", AND(D96>=51, D96<=53), "Production, transportation, and material moving occupations", AND(D96>=45, D96<=49), "Natural resources, construction, and maintenance occupations", TRUE, "Not applicable to study area" )} -> Natural resources, construction, and maintenance occupations | G96: =SUMIF(F:F, F96, A:A) -> 7339 | H96: =AVERAGEIF(F:F, F96, A:A) -> 59.666667 | I96: =_xlfn.XLOOKUP($C96,'NAICS-SOC-CIP x-walk'!C:C, 'NAICS-SOC-CIP x-walk'!H:H) -> 42, 48-49 | J96: =_xlfn.XLOOKUP(K96,'ACS-NAICS-SOC x-walk'!K:K,'ACS-NAICS-SOC x-walk'!L:L) -> Wholesale Trade | K96: =_xlfn.XLOOKUP($C96,'NAICS-SOC-CIP x-walk'!$C:$C, 'NAICS-SOC-CIP x-walk'!I:I) -> Wholesale Trade, Transportation and Warehousing | L96: =SUMIF(K:K, K96, A:A) -> 3770 | M96: =AVERAGEIF(K:K, K96, A:A) -> 53.857143
A97: 37 | B97: 1-2 | C97: 51-2011 | D97: =VALUE(LEFT(C97,2)) -> 51 | E97: Aircraft Structure, Surfaces, Rigging, and Systems Assemblers | F97: {=_xlfn.IFS( AND(D97>=11, D97<=29), "Management, business, science, and arts occupations", AND(D97>=31, D97<=39), "Service occupations", AND(D97>=41, D97<=43), "Sales and office occupations", AND(D97>=51, D97<=53), "Production, transportation, and material moving occupations", AND(D97>=45, D97<=49), "Natural resources, construction, and maintenance occupations", TRUE, "Not applicable to study area" )} -> Production, transportation, and material moving occupations | G97: =SUMIF(F:F, F97, A:A) -> 7976 | H97: =AVERAGEIF(F:F, F97, A:A) -> 51.458065 | I97: =_xlfn.XLOOKUP($C97,'NAICS-SOC-CIP x-walk'!C:C, 'NAICS-SOC-CIP x-walk'!H:H) -> 42, 48-49 | J97: =_xlfn.XLOOKUP(K97,'ACS-NAICS-SOC x-walk'!K:K,'ACS-NAICS-SOC x-walk'!L:L) -> Wholesale Trade | K97: =_xlfn.XLOOKUP($C97,'NAICS-SOC-CIP x-walk'!$C:$C, 'NAICS-SOC-CIP x-walk'!I:I) -> Wholesale Trade, Transportation and Warehousing | L97: =SUMIF(K:K, K97, A:A) -> 3770 | M97: =AVERAGEIF(K:K, K97, A:A) -> 53.857143
A98: 41 | B98: 1-2 | C98: 51-9111 | D98: =VALUE(LEFT(C98,2)) -> 51 | E98: Packaging and Filling Machine Operators and Tenders | F98: {=_xlfn.IFS( AND(D98>=11, D98<=29), "Management, business, science, and arts occupations", AND(D98>=31, D98<=39), "Service occupations", AND(D98>=41, D98<=43), "Sales and office occupations", AND(D98>=51, D98<=53), "Production, transportation, and material moving occupations", AND(D98>=45, D98<=49), "Natural resources, construction, and maintenance occupations", TRUE, "Not applicable to study area" )} -> Production, transportation, and material moving occupations | G98: =SUMIF(F:F, F98, A:A) -> 7976 | H98: =AVERAGEIF(F:F, F98, A:A) -> 51.458065 | I98: =_xlfn.XLOOKUP($C98,'NAICS-SOC-CIP x-walk'!C:C, 'NAICS-SOC-CIP x-walk'!H:H) -> 42, 48-49 | J98: =_xlfn.XLOOKUP(K98,'ACS-NAICS-SOC x-walk'!K:K,'ACS-NAICS-SOC x-walk'!L:L) -> Wholesale Trade | K98: =_xlfn.XLOOKUP($C98,'NAICS-SOC-CIP x-walk'!$C:$C, 'NAICS-SOC-CIP x-walk'!I:I) -> Wholesale Trade, Transportation and Warehousing | L98: =SUMIF(K:K, K98, A:A) -> 3770 | M98: =AVERAGEIF(K:K, K98, A:A) -> 53.857143
A99: 56 | B99: 1-2 | C99: 51-9124 | D99: =VALUE(LEFT(C99,2)) -> 51 | E99: Coating, Painting, and Spraying Machine Setters, Operators, and Tenders | F99: {=_xlfn.IFS( AND(D99>=11, D99<=29), "Management, business, science, and arts occupations", AND(D99>=31, D99<=39), "Service occupations", AND(D99>=41, D99<=43), "Sales and office occupations", AND(D99>=51, D99<=53), "Production, transportation, and material moving occupations", AND(D99>=45, D99<=49), "Natural resources, construction, and maintenance occupations", TRUE, "Not applicable to study area" )} -> Production, transportation, and material moving occupations | G99: =SUMIF(F:F, F99, A:A) -> 7976 | H99: =AVERAGEIF(F:F, F99, A:A) -> 51.458065 | I99: =_xlfn.XLOOKUP($C99,'NAICS-SOC-CIP x-walk'!C:C, 'NAICS-SOC-CIP x-walk'!H:H) -> 42, 48-49 | J99: =_xlfn.XLOOKUP(K99,'ACS-NAICS-SOC x-walk'!K:K,'ACS-NAICS-SOC x-walk'!L:L) -> Wholesale Trade | K99: =_xlfn.XLOOKUP($C99,'NAICS-SOC-CIP x-walk'!$C:$C, 'NAICS-SOC-CIP x-walk'!I:I) -> Wholesale Trade, Transportation and Warehousing | L99: =SUMIF(K:K, K99, A:A) -> 3770 | M99: =AVERAGEIF(K:K, K99, A:A) -> 53.857143
A100: 87 | B100: 1-2 | C100: 53-1041 | D100: =VALUE(LEFT(C100,2)) -> 53 | E100: Aircraft Cargo Handling Supervisors | F100: {=_xlfn.IFS( AND(D100>=11, D100<=29), "Management, business, science, and arts occupations", AND(D100>=31, D100<=39), "Service occupations", AND(D100>=41, D100<=43), "Sales and office occupations", AND(D100>=51, D100<=53), "Production, transportation, and material moving occupations", AND(D100>=45, D100<=49), "Natural resources, construction, and maintenance occupations", TRUE, "Not applicable to study area" )} -> Production, transportation, and material moving occupations | G100: =SUMIF(F:F, F100, A:A) -> 7976 | H100: =AVERAGEIF(F:F, F100, A:A) -> 51.458065 | I100: =_xlfn.XLOOKUP($C100,'NAICS-SOC-CIP x-walk'!C:C, 'NAICS-SOC-CIP x-walk'!H:H) -> 42, 48-49 | J100: =_xlfn.XLOOKUP(K100,'ACS-NAICS-SOC x-walk'!K:K,'ACS-NAICS-SOC x-walk'!L:L) -> Wholesale Trade | K100: =_xlfn.XLOOKUP($C100,'NAICS-SOC-CIP x-walk'!$C:$C, 'NAICS-SOC-CIP x-walk'!I:I) -> Wholesale Trade, Transportation and Warehousing | L100: =SUMIF(K:K, K100, A:A) -> 3770 | M100: =AVERAGEIF(K:K, K100, A:A) -> 53.857143
A101: 35 | B101: 4 | C101: 53-2011 | D101: =VALUE(LEFT(C101,2)) -> 53 | E101: Airline Pilots, Copilots, and Flight Engineers | F101: {=_xlfn.IFS( AND(D101>=11, D101<=29), "Management, business, science, and arts occupations", AND(D101>=31, D101<=39), "Service occupations", AND(D101>=41, D101<=43), "Sales and office occupations", AND(D101>=51, D101<=53), "Production, transportation, and material moving occupations", AND(D101>=45, D101<=49), "Natural resources, construction, and maintenance occupations", TRUE, "Not applicable to study area" )} -> Production, transportation, and material moving occupations | G101: =SUMIF(F:F, F101, A:A) -> 7976 | H101: =AVERAGEIF(F:F, F101, A:A) -> 51.458065 | I101: =_xlfn.XLOOKUP($C101,'NAICS-SOC-CIP x-walk'!C:C, 'NAICS-SOC-CIP x-walk'!H:H) -> 42, 48-49 | J101: =_xlfn.XLOOKUP(K101,'ACS-NAICS-SOC x-walk'!K:K,'ACS-NAICS-SOC x-walk'!L:L) -> Wholesale Trade | K101: =_xlfn.XLOOKUP($C101,'NAICS-SOC-CIP x-walk'!$C:$C, 'NAICS-SOC-CIP x-walk'!I:I) -> Wholesale Trade, Transportation and Warehousing | L101: =SUMIF(K:K, K101, A:A) -> 3770 | M101: =AVERAGEIF(K:K, K101, A:A) -> 53.857143
A102: 34 | B102: 3 | C102: 53-2012 | D102: =VALUE(LEFT(C102,2)) -> 53 | E102: Commercial Pilots | F102: {=_xlfn.IFS( AND(D102>=11, D102<=29), "Management, business, science, and arts occupations", AND(D102>=31, D102<=39), "Service occupations", AND(D102>=41, D102<=43), "Sales and office occupations", AND(D102>=51, D102<=53), "Production, transportation, and material moving occupations", AND(D102>=45, D102<=49), "Natural resources, construction, and maintenance occupations", TRUE, "Not applicable to study area" )} -> Production, transportation, and material moving occupations | G102: =SUMIF(F:F, F102, A:A) -> 7976 | H102: =AVERAGEIF(F:F, F102, A:A) -> 51.458065 | I102: =_xlfn.XLOOKUP($C102,'NAICS-SOC-CIP x-walk'!C:C, 'NAICS-SOC-CIP x-walk'!H:H) -> 42, 48-49 | J102: =_xlfn.XLOOKUP(K102,'ACS-NAICS-SOC x-walk'!K:K,'ACS-NAICS-SOC x-walk'!L:L) -> Wholesale Trade | K102: =_xlfn.XLOOKUP($C102,'NAICS-SOC-CIP x-walk'!$C:$C, 'NAICS-SOC-CIP x-walk'!I:I) -> Wholesale Trade, Transportation and Warehousing | L102: =SUMIF(K:K, K102, A:A) -> 3770 | M102: =AVERAGEIF(K:K, K102, A:A) -> 53.857143
A103: 6 | B103: 3 | C103: 53-2021 | D103: =VALUE(LEFT(C103,2)) -> 53 | E103: Air Traffic Controllers | F103: {=_xlfn.IFS( AND(D103>=11, D103<=29), "Management, business, science, and arts occupations", AND(D103>=31, D103<=39), "Service occupations", AND(D103>=41, D103<=43), "Sales and office occupations", AND(D103>=51, D103<=53), "Production, transportation, and material moving occupations", AND(D103>=45, D103<=49), "Natural resources, construction, and maintenance occupations", TRUE, "Not applicable to study area" )} -> Production, transportation, and material moving occupations | G103: =SUMIF(F:F, F103, A:A) -> 7976 | H103: =AVERAGEIF(F:F, F103, A:A) -> 51.458065 | I103: =_xlfn.XLOOKUP($C103,'NAICS-SOC-CIP x-walk'!C:C, 'NAICS-SOC-CIP x-walk'!H:H) -> 42, 48-49 | J103: =_xlfn.XLOOKUP(K103,'ACS-NAICS-SOC x-walk'!K:K,'ACS-NAICS-SOC x-walk'!L:L) -> Wholesale Trade | K103: =_xlfn.XLOOKUP($C103,'NAICS-SOC-CIP x-walk'!$C:$C, 'NAICS-SOC-CIP x-walk'!I:I) -> Wholesale Trade, Transportation and Warehousing | L103: =SUMIF(K:K, K103, A:A) -> 3770 | M103: =AVERAGEIF(K:K, K103, A:A) -> 53.857143
A104: 57 | B104: 3 | C104: 53-2022 | D104: =VALUE(LEFT(C104,2)) -> 53 | E104: Airfield Operations Specialists | F104: {=_xlfn.IFS( AND(D104>=11, D104<=29), "Management, business, science, and arts occupations", AND(D104>=31, D104<=39), "Service occupations", AND(D104>=41, D104<=43), "Sales and office occupations", AND(D104>=51, D104<=53), "Production, transportation, and material moving occupations", AND(D104>=45, D104<=49), "Natural resources, construction, and maintenance occupations", TRUE, "Not applicable to study area" )} -> Production, transportation, and material moving occupations | G104: =SUMIF(F:F, F104, A:A) -> 7976 | H104: =AVERAGEIF(F:F, F104, A:A) -> 51.458065 | I104: =_xlfn.XLOOKUP($C104,'NAICS-SOC-CIP x-walk'!C:C, 'NAICS-SOC-CIP x-walk'!H:H) -> 42, 48-49 | J104: =_xlfn.XLOOKUP(K104,'ACS-NAICS-SOC x-walk'!K:K,'ACS-NAICS-SOC x-walk'!L:L) -> Wholesale Trade | K104: =_xlfn.XLOOKUP($C104,'NAICS-SOC-CIP x-walk'!$C:$C, 'NAICS-SOC-CIP x-walk'!I:I) -> Wholesale Trade, Transportation and Warehousing | L104: =SUMIF(K:K, K104, A:A) -> 3770 | M104: =AVERAGEIF(K:K, K104, A:A) -> 53.857143
...

Sheet Outdoors, exposed
A1: Browse by Work Context
A2: Outdoors, Exposed to All Weather Conditions
A4: Context | B4: Job Zone | C4: SOC Occupation Code | D4: SOC 2-Digit Code | E4: SOC 6-Digit Description | F4: ACS Occupation Description | G4: Aggregate ACS Occupation Context Score | H4: ACS Occupation Category Mean Context Score | I4: NAICS Code | J4: ACS Industry Description | K4: NAICS Description | L4: Aggregate Industry Context Score | M4: ACS Industry Category Mean Context Score
A5: 100 | B5: 1-2 | C5: 47-2073 | D5: =VALUE(LEFT(C5,2)) -> 47 | E5: Operating Engineers and Other Construction Equipment Operators | F5: {=_xlfn.IFS( AND(D5>=11, D5<=29), "Management, business, science, and arts occupations", AND(D5>=31, D5<=39), "Service occupations", AND(D5>=41, D5<=43), "Sales and office occupations", AND(D5>=51, D5<=53), "Production, transportation, and material moving occupations", AND(D5>=45, D5<=49), "Natural resources, construction, and maintenance occupations", TRUE, "Not applicable to study area" )} -> Natural resources, construction, and maintenance occupations | G5: =SUMIF(F:F, F5, A:A) -> 8738 | H5: =AVERAGEIF(F:F, F5, A:A) -> 71.04065 | I5: =_xlfn.XLOOKUP($C5,'NAICS-SOC-CIP x-walk'!C:C, 'NAICS-SOC-CIP x-walk'!H:H) -> 23 | J5: =_xlfn.XLOOKUP(K5,'ACS-NAICS-SOC x-walk'!K:K,'ACS-NAICS-SOC x-walk'!L:L) -> Construction | K5: =_xlfn.XLOOKUP($C5,'NAICS-SOC-CIP x-walk'!$C:$C, 'NAICS-SOC-CIP x-walk'!I:I) -> Construction | L5: =SUMIF(K:K, K5, A:A) -> 4669 | M5: =AVERAGEIF(K:K, K5, A:A) -> 61.434211
A6: 100 | B6: 1-2 | C6: 47-2072 | D6: =VALUE(LEFT(C6,2)) -> 47 | E6: Pile Driver Operators | F6: {=_xlfn.IFS( AND(D6>=11, D6<=29), "Management, business, science, and arts occupations", AND(D6>=31, D6<=39), "Service occupations", AND(D6>=41, D6<=43), "Sales and office occupations", AND(D6>=51, D6<=53), "Production, transportation, and material moving occupations", AND(D6>=45, D6<=49), "Natural resources, construction, and maintenance occupations", TRUE, "Not applicable to study area" )} -> Natural resources, construction, and maintenance occupations | G6: =SUMIF(F:F, F6, A:A) -> 8738 | H6: =AVERAGEIF(F:F, F6, A:A) -> 71.04065 | I6: =_xlfn.XLOOKUP($C6,'NAICS-SOC-CIP x-walk'!C:C, 'NAICS-SOC-CIP x-walk'!H:H) -> 23 | J6: =_xlfn.XLOOKUP(K6,'ACS-NAICS-SOC x-walk'!K:K,'ACS-NAICS-SOC x-walk'!L:L) -> Construction | K6: =_xlfn.XLOOKUP($C6,'NAICS-SOC-CIP x-walk'!$C:$C, 'NAICS-SOC-CIP x-walk'!I:I) -> Construction | L6: =SUMIF(K:K, K6, A:A) -> 4669 | M6: =AVERAGEIF(K:K, K6, A:A) -> 61.434211
A7: 100 | B7: 1-2 | C7: 47-2181 | D7: =VALUE(LEFT(C7,2)) -> 47 | E7: Roofers | F7: {=_xlfn.IFS( AND(D7>=11, D7<=29), "Management, business, science, and arts occupations", AND(D7>=31, D7<=39), "Service occupations", AND(D7>=41, D7<=43), "Sales and office occupations", AND(D7>=51, D7<=53), "Production, transportation, and material moving occupations", AND(D7>=45, D7<=49), "Natural resources, construction, and maintenance occupations", TRUE, "Not applicable to study area" )} -> Natural resources, construction, and maintenance occupations | G7: =SUMIF(F:F, F7, A:A) -> 8738 | H7: =AVERAGEIF(F:F, F7, A:A) -> 71.04065 | I7: =_xlfn.XLOOKUP($C7,'NAICS-SOC-CIP x-walk'!C:C, 'NAICS-SOC-CIP x-walk'!H:H) -> 23 | J7: =_xlfn.XLOOKUP(K7,'ACS-NAICS-SOC x-walk'!K:K,'ACS-NAICS-SOC x-walk'!L:L) -> Construction | K7: =_xlfn.XLOOKUP($C7,'NAICS-SOC-CIP x-walk'!$C:$C, 'NAICS-SOC-CIP x-walk'!I:I) -> Construction | L7: =SUMIF(K:K, K7, A:A) -> 4669 | M7: =AVERAGEIF(K:K, K7, A:A) -> 61.434211
A8: 99 | B8: 1-2 | C8: 47-2021 | D8: =VALUE(LEFT(C8,2)) -> 47 | E8: Brickmasons and Blockmasons | F8: {=_xlfn.IFS( AND(D8>=11, D8<=29), "Management, business, science, and arts occupations", AND(D8>=31, D8<=39), "Service occupations", AND(D8>=41, D8<=43), "Sales and office occupations", AND(D8>=51, D8<=53), "Production, transportation, and material moving occupations", AND(D8>=45, D8<=49), "Natural resources, construction, and maintenance occupations", TRUE, "Not applicable to study area" )} -> Natural resources, construction, and maintenance occupations | G8: =SUMIF(F:F, F8, A:A) -> 8738 | H8: =AVERAGEIF(F:F, F8, A:A) -> 71.04065 | I8: =_xlfn.XLOOKUP($C8,'NAICS-SOC-CIP x-walk'!C:C, 'NAICS-SOC-CIP x-walk'!H:H) -> 23 | J8: =_xlfn.XLOOKUP(K8,'ACS-NAICS-SOC x-walk'!K:K,'ACS-NAICS-SOC x-walk'!L:L) -> Construction | K8: =_xlfn.XLOOKUP($C8,'NAICS-SOC-CIP x-walk'!$C:$C, 'NAICS-SOC-CIP x-walk'!I:I) -> Construction | L8: =SUMIF(K:K, K8, A:A) -> 4669 | M8: =AVERAGEIF(K:K, K8, A:A) -> 61.434211
A9: 99 | B9: 1-2 | C9: 47-4051 | D9: =VALUE(LEFT(C9,2)) -> 47 | E9: Highway Maintenance Workers | F9: {=_xlfn.IFS( AND(D9>=11, D9<=29), "Management, business, science, and arts occupations", AND(D9>=31, D9<=39), "Service occupations", AND(D9>=41, D9<=43), "Sales and office occupations", AND(D9>=51, D9<=53), "Production, transportation, and material moving occupations", AND(D9>=45, D9<=49), "Natural resources, construction, and maintenance occupations", TRUE, "Not applicable to study area" )} -> Natural resources, construction, and maintenance occupations | G9: =SUMIF(F:F, F9, A:A) -> 8738 | H9: =AVERAGEIF(F:F, F9, A:A) -> 71.04065 | I9: =_xlfn.XLOOKUP($C9,'NAICS-SOC-CIP x-walk'!C:C, 'NAICS-SOC-CIP x-walk'!H:H) -> 23 | J9: =_xlfn.XLOOKUP(K9,'ACS-NAICS-SOC x-walk'!K:K,'ACS-NAICS-SOC x-walk'!L:L) -> Construction | K9: =_xlfn.XLOOKUP($C9,'NAICS-SOC-CIP x-walk'!$C:$C, 'NAICS-SOC-CIP x-walk'!I:I) -> Construction | L9: =SUMIF(K:K, K9, A:A) -> 4669 | M9: =AVERAGEIF(K:K, K9, A:A) -> 61.434211
A10: 98 | B10: 1-2 | C10: 47-5032 | D10: =VALUE(LEFT(C10,2)) -> 47 | E10: Explosives Workers, Ordnance Handling Experts, and Blasters | F10: {=_xlfn.IFS( AND(D10>=11, D10<=29), "Management, business, science, and arts occupations", AND(D10>=31, D10<=39), "Service occupations", AND(D10>=41, D10<=43), "Sales and office occupations", AND(D10>=51, D10<=53), "Production, transportation, and material moving occupations", AND(D10>=45, D10<=49), "Natural resources, construction, and maintenance occupations", TRUE, "Not applicable to study area" )} -> Natural resources, construction, and maintenance occupations | G10: =SUMIF(F:F, F10, A:A) -> 8738 | H10: =AVERAGEIF(F:F, F10, A:A) -> 71.04065 | I10: =_xlfn.XLOOKUP($C10,'NAICS-SOC-CIP x-walk'!C:C, 'NAICS-SOC-CIP x-walk'!H:H) -> 21, 22 | J10: =_xlfn.XLOOKUP(K10,'ACS-NAICS-SOC x-walk'!K:K,'ACS-NAICS-SOC x-walk'!L:L) -> Agriculture, Forestry, Fishing and Hunting, and Mining | K10: =_xlfn.XLOOKUP($C10,'NAICS-SOC-CIP x-walk'!$C:$C, 'NAICS-SOC-CIP x-walk'!I:I) -> Mining, Quarrying, and Oil and Gas Extraction, Utilities | L10: =SUMIF(K:K, K10, A:A) -> 5203 | M10: =AVERAGEIF(K:K, K10, A:A) -> 55.946237
A11: 98 | B11: 1-2 | C11: 47-2151 | D11: =VALUE(LEFT(C11,2)) -> 47 | E11: Pipelayers | F11: {=_xlfn.IFS( AND(D11>=11, D11<=29), "Management, business, science, and arts occupations", AND(D11>=31, D11<=39), "Service occupations", AND(D11>=41, D11<=43), "Sales and office occupations", AND(D11>=51, D11<=53), "Production, transportation, and material moving occupations", AND(D11>=45, D11<=49), "Natural resources, construction, and maintenance occupations", TRUE, "Not applicable to study area" )} -> Natural resources, construction, and maintenance occupations | G11: =SUMIF(F:F, F11, A:A) -> 8738 | H11: =AVERAGEIF(F:F, F11, A:A) -> 71.04065 | I11: =_xlfn.XLOOKUP($C11,'NAICS-SOC-CIP x-walk'!C:C, 'NAICS-SOC-CIP x-walk'!H:H) -> 23 | J11: =_xlfn.XLOOKUP(K11,'ACS-NAICS-SOC x-walk'!K:K,'ACS-NAICS-SOC x-walk'!L:L) -> Construction | K11: =_xlfn.XLOOKUP($C11,'NAICS-SOC-CIP x-walk'!$C:$C, 'NAICS-SOC-CIP x-walk'!I:I) -> Construction | L11: =SUMIF(K:K, K11, A:A) -> 4669 | M11: =AVERAGEIF(K:K, K11, A:A) -> 61.434211
A12: 95 | B12: 1-2 | C12: 47-2051 | D12: =VALUE(LEFT(C12,2)) -> 47 | E12: Cement Masons and Concrete Finishers | F12: {=_xlfn.IFS( AND(D12>=11, D12<=29), "Management, business, science, and arts occupations", AND(D12>=31, D12<=39), "Service occupations", AND(D12>=41, D12<=43), "Sales and office occupations", AND(D12>=51, D12<=53), "Production, transportation, and material moving occupations", AND(D12>=45, D12<=49), "Natural resources, construction, and maintenance occupations", TRUE, "Not applicable to study area" )} -> Natural resources, construction, and maintenance occupations | G12: =SUMIF(F:F, F12, A:A) -> 8738 | H12: =AVERAGEIF(F:F, F12, A:A) -> 71.04065 | I12: =_xlfn.XLOOKUP($C12,'NAICS-SOC-CIP x-walk'!C:C, 'NAICS-SOC-CIP x-walk'!H:H) -> 23 | J12: =_xlfn.XLOOKUP(K12,'ACS-NAICS-SOC x-walk'!K:K,'ACS-NAICS-SOC x-walk'!L:L) -> Construction | K12: =_xlfn.XLOOKUP($C12,'NAICS-SOC-CIP x-walk'!$C:$C, 'NAICS-SOC-CIP x-walk'!I:I) -> Construction | L12: =SUMIF(K:K, K12, A:A) -> 4669 | M12: =AVERAGEIF(K:K, K12, A:A) -> 61.434211
A13: 95 | B13: 1-2 | C13: 47-2221 | D13: =VALUE(LEFT(C13,2)) -> 47 | E13: Structural Iron and Steel Workers | F13: {=_xlfn.IFS( AND(D13>=11, D13<=29), "Management, business, science, and arts occupations", AND(D13>=31, D13<=39), "Service occupations", AND(D13>=41, D13<=43), "Sales and office occupations", AND(D13>=51, D13<=53), "Production, transportation, and material moving occupations", AND(D13>=45, D13<=49), "Natural resources, construction, and maintenance occupations", TRUE, "Not applicable to study area" )} -> Natural resources, construction, and maintenance occupations | G13: =SUMIF(F:F, F13, A:A) -> 8738 | H13: =AVERAGEIF(F:F, F13, A:A) -> 71.04065 | I13: =_xlfn.XLOOKUP($C13,'NAICS-SOC-CIP x-walk'!C:C, 'NAICS-SOC-CIP x-walk'!H:H) -> 23 | J13: =_xlfn.XLOOKUP(K13,'ACS-NAICS-SOC x-walk'!K:K,'ACS-NAICS-SOC x-walk'!L:L) -> Construction | K13: =_xlfn.XLOOKUP($C13,'NAICS-SOC-CIP x-walk'!$C:$C, 'NAICS-SOC-CIP x-walk'!I:I) -> Construction | L13: =SUMIF(K:K, K13, A:A) -> 4669 | M13: =AVERAGEIF(K:K, K13, A:A) -> 61.434211
A14: 94 | B14: 1-2 | C14: 47-4031 | D14: =VALUE(LEFT(C14,2)) -> 47 | E14: Fence Erectors | F14: {=_xlfn.IFS( AND(D14>=11, D14<=29), "Management, business, science, and arts occupations", AND(D14>=31, D14<=39), "Service occupations", AND(D14>=41, D14<=43), "Sales and office occupations", AND(D14>=51, D14<=53), "Production, transportation, and material moving occupations", AND(D14>=45, D14<=49), "Natural resources, construction, and maintenance occupations", TRUE, "Not applicable to study area" )} -> Natural resources, construction, and maintenance occupations | G14: =SUMIF(F:F, F14, A:A) -> 8738 | H14: =AVERAGEIF(F:F, F14, A:A) -> 71.04065 | I14: =_xlfn.XLOOKUP($C14,'NAICS-SOC-CIP x-walk'!C:C, 'NAICS-SOC-CIP x-walk'!H:H) -> 23 | J14: =_xlfn.XLOOKUP(K14,'ACS-NAICS-SOC x-walk'!K:K,'ACS-NAICS-SOC x-walk'!L:L) -> Construction | K14: =_xlfn.XLOOKUP($C14,'NAICS-SOC-CIP x-walk'!$C:$C, 'NAICS-SOC-CIP x-walk'!I:I) -> Construction | L14: =SUMIF(K:K, K14, A:A) -> 4669 | M14: =AVERAGEIF(K:K, K14, A:A) -> 61.434211
A15: 94 | B15: 1-2 | C15: 47-2022 | D15: =VALUE(LEFT(C15,2)) -> 47 | E15: Stonemasons | F15: {=_xlfn.IFS( AND(D15>=11, D15<=29), "Management, business, science, and arts occupations", AND(D15>=31, D15<=39), "Service occupations", AND(D15>=41, D15<=43), "Sales and office occupations", AND(D15>=51, D15<=53), "Production, transportation, and material moving occupations", AND(D15>=45, D15<=49), "Natural resources, construction, and maintenance occupations", TRUE, "Not applicable to study area" )} -> Natural resources, construction, and maintenance occupations | G15: =SUMIF(F:F, F15, A:A) -> 8738 | H15: =AVERAGEIF(F:F, F15, A:A) -> 71.04065 | I15: =_xlfn.XLOOKUP($C15,'NAICS-SOC-CIP x-walk'!C:C, 'NAICS-SOC-CIP x-walk'!H:H) -> 23 | J15: =_xlfn.XLOOKUP(K15,'ACS-NAICS-SOC x-walk'!K:K,'ACS-NAICS-SOC x-walk'!L:L) -> Construction | K15: =_xlfn.XLOOKUP($C15,'NAICS-SOC-CIP x-walk'!$C:$C, 'NAICS-SOC-CIP x-walk'!I:I) -> Construction | L15: =SUMIF(K:K, K15, A:A) -> 4669 | M15: =AVERAGEIF(K:K, K15, A:A) -> 61.434211
A16: 92 | B16: 1-2 | C16: 47-2231 | D16: =VALUE(LEFT(C16,2)) -> 47 | E16: Solar Photovoltaic Installers | F16: {=_xlfn.IFS( AND(D16>=11, D16<=29), "Management, business, science, and arts occupations", AND(D16>=31, D16<=39), "Service occupations", AND(D16>=41, D16<=43), "Sales and office occupations", AND(D16>=51, D16<=53), "Production, transportation, and material moving occupations", AND(D16>=45, D16<=49), "Natural resources, construction, and maintenance occupations", TRUE, "Not applicable to study area" )} -> Natural resources, construction, and maintenance occupations | G16: =SUMIF(F:F, F16, A:A) -> 8738 | H16: =AVERAGEIF(F:F, F16, A:A) -> 71.04065 | I16: =_xlfn.XLOOKUP($C16,'NAICS-SOC-CIP x-walk'!C:C, 'NAICS-SOC-CIP x-walk'!H:H) -> 21, 22 | J16: =_xlfn.XLOOKUP(K16,'ACS-NAICS-SOC x-walk'!K:K,'ACS-NAICS-SOC x-walk'!L:L) -> Agriculture, Forestry, Fishing and Hunting, and Mining | K16: =_xlfn.XLOOKUP($C16,'NAICS-SOC-CIP x-walk'!$C:$C, 'NAICS-SOC-CIP x-walk'!I:I) -> Mining, Quarrying, and Oil and Gas Extraction, Utilities | L16: =SUMIF(K:K, K16, A:A) -> 5203 | M16: =AVERAGEIF(K:K, K16, A:A) -> 55.946237
A17: 91 | B17: 1-2 | C17: 47-2061 | D17: =VALUE(LEFT(C17,2)) -> 47 | E17: Construction Laborers | F17: {=_xlfn.IFS( AND(D17>=11, D17<=29), "Management, business, science, and arts occupations", AND(D17>=31, D17<=39), "Service occupations", AND(D17>=41, D17<=43), "Sales and office occupations", AND(D17>=51, D17<=53), "Production, transportation, and material moving occupations", AND(D17>=45, D17<=49), "Natural resources, construction, and maintenance occupations", TRUE, "Not applicable to study area" )} -> Natural resources, construction, and maintenance occupations | G17: =SUMIF(F:F, F17, A:A) -> 8738 | H17: =AVERAGEIF(F:F, F17, A:A) -> 71.04065 | I17: =_xlfn.XLOOKUP($C17,'NAICS-SOC-CIP x-walk'!C:C, 'NAICS-SOC-CIP x-walk'!H:H) -> 23 | J17: =_xlfn.XLOOKUP(K17,'ACS-NAICS-SOC x-walk'!K:K,'ACS-NAICS-SOC x-walk'!L:L) -> Construction | K17: =_xlfn.XLOOKUP($C17,'NAICS-SOC-CIP x-walk'!$C:$C, 'NAICS-SOC-CIP x-walk'!I:I) -> Construction | L17: =SUMIF(K:K, K17, A:A) -> 4669 | M17: =AVERAGEIF(K:K, K17, A:A) -> 61.434211
A18: 91 | B18: 3 | C18: 49-9012 | D18: =VALUE(LEFT(C18,2)) -> 49 | E18: Control and Valve Installers and Repairers, Except Mechanical Door | F18: {=_xlfn.IFS( AND(D18>=11, D18<=29), "Management, business, science, and arts occupations", AND(D18>=31, D18<=39), "Service occupations", AND(D18>=41, D18<=43), "Sales and office occupations", AND(D18>=51, D18<=53), "Production, transportation, and material moving occupations", AND(D18>=45, D18<=49), "Natural resources, construction, and maintenance occupations", TRUE, "Not applicable to study area" )} -> Natural resources, construction, and maintenance occupations | G18: =SUMIF(F:F, F18, A:A) -> 8738 | H18: =AVERAGEIF(F:F, F18, A:A) -> 71.04065 | I18: =_xlfn.XLOOKUP($C18,'NAICS-SOC-CIP x-walk'!C:C, 'NAICS-SOC-CIP x-walk'!H:H) -> 23 | J18: =_xlfn.XLOOKUP(K18,'ACS-NAICS-SOC x-walk'!K:K,'ACS-NAICS-SOC x-walk'!L:L) -> Construction | K18: =_xlfn.XLOOKUP($C18,'NAICS-SOC-CIP x-walk'!$C:$C, 'NAICS-SOC-CIP x-walk'!I:I) -> Construction | L18: =SUMIF(K:K, K18, A:A) -> 4669 | M18: =AVERAGEIF(K:K, K18, A:A) -> 61.434211
A19: 90 | B19: 1-2 | C19: 47-2171 | D19: =VALUE(LEFT(C19,2)) -> 47 | E19: Reinforcing Iron and Rebar Workers | F19: {=_xlfn.IFS( AND(D19>=11, D19<=29), "Management, business, science, and arts occupations", AND(D19>=31, D19<=39), "Service occupations", AND(D19>=41, D19<=43), "Sales and office occupations", AND(D19>=51, D19<=53), "Production, transportation, and material moving occupations", AND(D19>=45, D19<=49), "Natural resources, construction, and maintenance occupations", TRUE, "Not applicable to study area" )} -> Natural resources, construction, and maintenance occupations | G19: =SUMIF(F:F, F19, A:A) -> 8738 | H19: =AVERAGEIF(F:F, F19, A:A) -> 71.04065 | I19: =_xlfn.XLOOKUP($C19,'NAICS-SOC-CIP x-walk'!C:C, 'NAICS-SOC-CIP x-walk'!H:H) -> 23 | J19: =_xlfn.XLOOKUP(K19,'ACS-NAICS-SOC x-walk'!K:K,'ACS-NAICS-SOC x-walk'!L:L) -> Construction | K19: =_xlfn.XLOOKUP($C19,'NAICS-SOC-CIP x-walk'!$C:$C, 'NAICS-SOC-CIP x-walk'!I:I) -> Construction | L19: =SUMIF(K:K, K19, A:A) -> 4669 | M19: =AVERAGEIF(K:K, K19, A:A) -> 61.434211
A20: 88 | B20: 1-2 | C20: 47-3016 | D20: =VALUE(LEFT(C20,2)) -> 47 | E20: Helpers--Roofers | F20: {=_xlfn.IFS( AND(D20>=11, D20<=29), "Management, business, science, and arts occupations", AND(D20>=31, D20<=39), "Service occupations", AND(D20>=41, D20<=43), "Sales and office occupations", AND(D20>=51, D20<=53), "Production, transportation, and material moving occupations", AND(D20>=45, D20<=49), "Natural resources, construction, and maintenance occupations", TRUE, "Not applicable to study area" )} -> Natural resources, construction, and maintenance occupations | G20: =SUMIF(F:F, F20, A:A) -> 8738 | H20: =AVERAGEIF(F:F, F20, A:A) -> 71.04065 | I20: =_xlfn.XLOOKUP($C20,'NAICS-SOC-CIP x-walk'!C:C, 'NAICS-SOC-CIP x-walk'!H:H) -> 23 | J20: =_xlfn.XLOOKUP(K20,'ACS-NAICS-SOC x-walk'!K:K,'ACS-NAICS-SOC x-walk'!L:L) -> Construction | K20: =_xlfn.XLOOKUP($C20,'NAICS-SOC-CIP x-walk'!$C:$C, 'NAICS-SOC-CIP x-walk'!I:I) -> Construction | L20: =SUMIF(K:K, K20, A:A) -> 4669 | M20: =AVERAGEIF(K:K, K20, A:A) -> 61.434211
A21: 87 | B21: 3 | C21: 47-4011 | D21: =VALUE(LEFT(C21,2)) -> 47 | E21: Construction and Building Inspectors | F21: {=_xlfn.IFS( AND(D21>=11, D21<=29), "Management, business, science, and arts occupations", AND(D21>=31, D21<=39), "Service occupations", AND(D21>=41, D21<=43), "Sales and office occupations", AND(D21>=51, D21<=53), "Production, transportation, and material moving occupations", AND(D21>=45, D21<=49), "Natural resources, construction, and maintenance occupations", TRUE, "Not applicable to study area" )} -> Natural resources, construction, and maintenance occupations | G21: =SUMIF(F:F, F21, A:A) -> 8738 | H21: =AVERAGEIF(F:F, F21, A:A) -> 71.04065 | I21: =_xlfn.XLOOKUP($C21,'NAICS-SOC-CIP x-walk'!C:C, 'NAICS-SOC-CIP x-walk'!H:H) -> 23 | J21: =_xlfn.XLOOKUP(K21,'ACS-NAICS-SOC x-walk'!K:K,'ACS-NAICS-SOC x-walk'!L:L) -> Construction | K21: =_xlfn.XLOOKUP($C21,'NAICS-SOC-CIP x-walk'!$C:$C, 'NAICS-SOC-CIP x-walk'!I:I) -> Construction | L21: =SUMIF(K:K, K21, A:A) -> 4669 | M21: =AVERAGEIF(K:K, K21, A:A) -> 61.434211
A22: 87 | B22: 1-2 | C22: 47-3015 | D22: =VALUE(LEFT(C22,2)) -> 47 | E22: Helpers--Pipelayers, Plumbers, Pipefitters, and Steamfitters | F22: {=_xlfn.IFS( AND(D22>=11, D22<=29), "Management, business, science, and arts occupations", AND(D22>=31, D22<=39), "Service occupations", AND(D22>=41, D22<=43), "Sales and office occupations", AND(D22>=51, D22<=53), "Production, transportation, and material moving occupations", AND(D22>=45, D22<=49), "Natural resources, construction, and maintenance occupations", TRUE, "Not applicable to study area" )} -> Natural resources, construction, and maintenance occupations | G22: =SUMIF(F:F, F22, A:A) -> 8738 | H22: =AVERAGEIF(F:F, F22, A:A) -> 71.04065 | I22: =_xlfn.XLOOKUP($C22,'NAICS-SOC-CIP x-walk'!C:C, 'NAICS-SOC-CIP x-walk'!H:H) -> 23 | J22: =_xlfn.XLOOKUP(K22,'ACS-NAICS-SOC x-walk'!K:K,'ACS-NAICS-SOC x-walk'!L:L) -> Construction | K22: =_xlfn.XLOOKUP($C22,'NAICS-SOC-CIP x-walk'!$C:$C, 'NAICS-SOC-CIP x-walk'!I:I) -> Construction | L22: =SUMIF(K:K, K22, A:A) -> 4669 | M22: =AVERAGEIF(K:K, K22, A:A) -> 61.434211
A23: 86 | B23: 3 | C23: 47-1011 | D23: =VALUE(LEFT(C23,2)) -> 47 | E23: First-Line Supervisors of Construction Trades and Extraction Workers | F23: {=_xlfn.IFS( AND(D23>=11, D23<=29), "Management, business, science, and arts occupations", AND(D23>=31, D23<=39), "Service occupations", AND(D23>=41, D23<=43), "Sales and office occupations", AND(D23>=51, D23<=53), "Production, transportation, and material moving occupations", AND(D23>=45, D23<=49), "Natural resources, construction, and maintenance occupations", TRUE, "Not applicable to study area" )} -> Natural resources, construction, and maintenance occupations | G23: =SUMIF(F:F, F23, A:A) -> 8738 | H23: =AVERAGEIF(F:F, F23, A:A) -> 71.04065 | I23: =_xlfn.XLOOKUP($C23,'NAICS-SOC-CIP x-walk'!C:C, 'NAICS-SOC-CIP x-walk'!H:H) -> 21, 22 | J23: =_xlfn.XLOOKUP(K23,'ACS-NAICS-SOC x-walk'!K:K,'ACS-NAICS-SOC x-walk'!L:L) -> Agriculture, Forestry, Fishing and Hunting, and Mining | K23: =_xlfn.XLOOKUP($C23,'NAICS-SOC-CIP x-walk'!$C:$C, 'NAICS-SOC-CIP x-walk'!I:I) -> Mining, Quarrying, and Oil and Gas Extraction, Utilities | L23: =SUMIF(K:K, K23, A:A) -> 5203 | M23: =AVERAGEIF(K:K, K23, A:A) -> 55.946237
A24: 86 | B24: 1-2 | C24: 47-2121 | D24: =VALUE(LEFT(C24,2)) -> 47 | E24: Glaziers | F24: {=_xlfn.IFS( AND(D24>=11, D24<=29), "Management, business, science, and arts occupations", AND(D24>=31, D24<=39), "Service occupations", AND(D24>=41, D24<=43), "Sales and office occupations", AND(D24>=51, D24<=53), "Production, transportation, and material moving occupations", AND(D24>=45, D24<=49), "Natural resources, construction, and maintenance occupations", TRUE, "Not applicable to study area" )} -> Natural resources, construction, and maintenance occupations | G24: =SUMIF(F:F, F24, A:A) -> 8738 | H24: =AVERAGEIF(F:F, F24, A:A) -> 71.04065 | I24: =_xlfn.XLOOKUP($C24,'NAICS-SOC-CIP x-walk'!C:C, 'NAICS-SOC-CIP x-walk'!H:H) -> 23 | J24: =_xlfn.XLOOKUP(K24,'ACS-NAICS-SOC x-walk'!K:K,'ACS-NAICS-SOC x-walk'!L:L) -> Construction | K24: =_xlfn.XLOOKUP($C24,'NAICS-SOC-CIP x-walk'!$C:$C, 'NAICS-SOC-CIP x-walk'!I:I) -> Construction | L24: =SUMIF(K:K, K24, A:A) -> 4669 | M24: =AVERAGEIF(K:K, K24, A:A) -> 61.434211
A25: 86 | B25: 3 | C25: 47-1011 | D25: =VALUE(LEFT(C25,2)) -> 47 | E25: Solar Energy Installation Managers | F25: {=_xlfn.IFS( AND(D25>=11, D25<=29), "Management, business, science, and arts occupations", AND(D25>=31, D25<=39), "Service occupations", AND(D25>=41, D25<=43), "Sales and office occupations", AND(D25>=51, D25<=53), "Production, transportation, and material moving occupations", AND(D25>=45, D25<=49), "Natural resources, construction, and maintenance occupations", TRUE, "Not applicable to study area" )} -> Natural resources, construction, and maintenance occupations | G25: =SUMIF(F:F, F25, A:A) -> 8738 | H25: =AVERAGEIF(F:F, F25, A:A) -> 71.04065 | I25: =_xlfn.XLOOKUP($C25,'NAICS-SOC-CIP x-walk'!C:C, 'NAICS-SOC-CIP x-walk'!H:H) -> 21, 22 | J25: =_xlfn.XLOOKUP(K25,'ACS-NAICS-SOC x-walk'!K:K,'ACS-NAICS-SOC x-walk'!L:L) -> Agriculture, Forestry, Fishing and Hunting, and Mining | K25: =_xlfn.XLOOKUP($C25,'NAICS-SOC-CIP x-walk'!$C:$C, 'NAICS-SOC-CIP x-walk'!I:I) -> Mining, Quarrying, and Oil and Gas Extraction, Utilities | L25: =SUMIF(K:K, K25, A:A) -> 5203 | M25: =AVERAGEIF(K:K, K25, A:A) -> 55.946237
A26: 85 | B26: 1-2 | C26: 49-9094 | D26: =VALUE(LEFT(C26,2)) -> 49 | E26: Locksmiths and Safe Repairers | F26: {=_xlfn.IFS( AND(D26>=11, D26<=29), "Management, business, science, and arts occupations", AND(D26>=31, D26<=39), "Service occupations", AND(D26>=41, D26<=43), "Sales and office occupations", AND(D26>=51, D26<=53), "Production, transportation, and material moving occupations", AND(D26>=45, D26<=49), "Natural resources, construction, and maintenance occupations", TRUE, "Not applicable to study area" )} -> Natural resources, construction, and maintenance occupations | G26: =SUMIF(F:F, F26, A:A) -> 8738 | H26: =AVERAGEIF(F:F, F26, A:A) -> 71.04065 | I26: =_xlfn.XLOOKUP($C26,'NAICS-SOC-CIP x-walk'!C:C, 'NAICS-SOC-CIP x-walk'!H:H) -> 23 | J26: =_xlfn.XLOOKUP(K26,'ACS-NAICS-SOC x-walk'!K:K,'ACS-NAICS-SOC x-walk'!L:L) -> Construction | K26: =_xlfn.XLOOKUP($C26,'NAICS-SOC-CIP x-walk'!$C:$C, 'NAICS-SOC-CIP x-walk'!I:I) -> Construction | L26: =SUMIF(K:K, K26, A:A) -> 4669 | M26: =AVERAGEIF(K:K, K26, A:A) -> 61.434211
A27: 84 | B27: 1-2 | C27: 47-5023 | D27: =VALUE(LEFT(C27,2)) -> 47 | E27: Earth Drillers, Except Oil and Gas | F27: {=_xlfn.IFS( AND(D27>=11, D27<=29), "Management, business, science, and arts occupations", AND(D27>=31, D27<=39), "Service occupations", AND(D27>=41, D27<=43), "Sales and office occupations", AND(D27>=51, D27<=53), "Production, transportation, and material moving occupations", AND(D27>=45, D27<=49), "Natural resources, construction, and maintenance occupations", TRUE, "Not applicable to study area" )} -> Natural resources, construction, and maintenance occupations | G27: =SUMIF(F:F, F27, A:A) -> 8738 | H27: =AVERAGEIF(F:F, F27, A:A) -> 71.04065 | I27: =_xlfn.XLOOKUP($C27,'NAICS-SOC-CIP x-walk'!C:C, 'NAICS-SOC-CIP x-walk'!H:H) -> 21, 22 | J27: =_xlfn.XLOOKUP(K27,'ACS-NAICS-SOC x-walk'!K:K,'ACS-NAICS-SOC x-walk'!L:L) -> Agriculture, Forestry, Fishing and Hunting, and Mining | K27: =_xlfn.XLOOKUP($C27,'NAICS-SOC-CIP x-walk'!$C:$C, 'NAICS-SOC-CIP x-walk'!I:I) -> Mining, Quarrying, and Oil and Gas Extraction, Utilities | L27: =SUMIF(K:K, K27, A:A) -> 5203 | M27: =AVERAGEIF(K:K, K27, A:A) -> 55.946237
A28: 84 | B28: 1-2 | C28: 49-9044 | D28: =VALUE(LEFT(C28,2)) -> 49 | E28: Millwrights | F28: {=_xlfn.IFS( AND(D28>=11, D28<=29), "Management, business, science, and arts occupations", AND(D28>=31, D28<=39), "Service occupations", AND(D28>=41, D28<=43), "Sales and office occupations", AND(D28>=51, D28<=53), "Production, transportation, and material moving occupations", AND(D28>=45, D28<=49), "Natural resources, construction, and maintenance occupations", TRUE, "Not applicable to study area" )} -> Natural resources, construction, and maintenance occupations | G28: =SUMIF(F:F, F28, A:A) -> 8738 | H28: =AVERAGEIF(F:F, F28, A:A) -> 71.04065 | I28: =_xlfn.XLOOKUP($C28,'NAICS-SOC-CIP x-walk'!C:C, 'NAICS-SOC-CIP x-walk'!H:H) -> 23 | J28: =_xlfn.XLOOKUP(K28,'ACS-NAICS-SOC x-walk'!K:K,'ACS-NAICS-SOC x-walk'!L:L) -> Construction | K28: =_xlfn.XLOOKUP($C28,'NAICS-SOC-CIP x-walk'!$C:$C, 'NAICS-SOC-CIP x-walk'!I:I) -> Construction | L28: =SUMIF(K:K, K28, A:A) -> 4669 | M28: =AVERAGEIF(K:K, K28, A:A) -> 61.434211
A29: 84 | B29: 1-2 | C29: 47-2161 | D29: =VALUE(LEFT(C29,2)) -> 47 | E29: Plasterers and Stucco Masons | F29: {=_xlfn.IFS( AND(D29>=11, D29<=29), "Management, business, science, and arts occupations", AND(D29>=31, D29<=39), "Service occupations", AND(D29>=41, D29<=43), "Sales and office occupations", AND(D29>=51, D29<=53), "Production, transportation, and material moving occupations", AND(D29>=45, D29<=49), "Natural resources, construction, and maintenance occupations", TRUE, "Not applicable to study area" )} -> Natural resources, construction, and maintenance occupations | G29: =SUMIF(F:F, F29, A:A) -> 8738 | H29: =AVERAGEIF(F:F, F29, A:A) -> 71.04065 | I29: =_xlfn.XLOOKUP($C29,'NAICS-SOC-CIP x-walk'!C:C, 'NAICS-SOC-CIP x-walk'!H:H) -> 23 | J29: =_xlfn.XLOOKUP(K29,'ACS-NAICS-SOC x-walk'!K:K,'ACS-NAICS-SOC x-walk'!L:L) -> Construction | K29: =_xlfn.XLOOKUP($C29,'NAICS-SOC-CIP x-walk'!$C:$C, 'NAICS-SOC-CIP x-walk'!I:I) -> Construction | L29: =SUMIF(K:K, K29, A:A) -> 4669 | M29: =AVERAGEIF(K:K, K29, A:A) -> 61.434211
A30: 83 | B30: 1-2 | C30: 47-3011 | D30: =VALUE(LEFT(C30,2)) -> 47 | E30: Helpers--Brickmasons, Blockmasons, Stonemasons, and Tile and Marble Setters | F30: {=_xlfn.IFS( AND(D30>=11, D30<=29), "Management, business, science, and arts occupations", AND(D30>=31, D30<=39), "Service occupations", AND(D30>=41, D30<=43), "Sales and office occupations", AND(D30>=51, D30<=53), "Production, transportation, and material moving occupations", AND(D30>=45, D30<=49), "Natural resources, construction, and maintenance occupations", TRUE, "Not applicable to study area" )} -> Natural resources, construction, and maintenance occupations | G30: =SUMIF(F:F, F30, A:A) -> 8738 | H30: =AVERAGEIF(F:F, F30, A:A) -> 71.04065 | I30: =_xlfn.XLOOKUP($C30,'NAICS-SOC-CIP x-walk'!C:C, 'NAICS-SOC-CIP x-walk'!H:H) -> 23 | J30: =_xlfn.XLOOKUP(K30,'ACS-NAICS-SOC x-walk'!K:K,'ACS-NAICS-SOC x-walk'!L:L) -> Construction | K30: =_xlfn.XLOOKUP($C30,'NAICS-SOC-CIP x-walk'!$C:$C, 'NAICS-SOC-CIP x-walk'!I:I) -> Construction | L30: =SUMIF(K:K, K30, A:A) -> 4669 | M30: =AVERAGEIF(K:K, K30, A:A) -> 61.434211
A31: 83 | B31: 1-2 | C31: 47-2071 | D31: =VALUE(LEFT(C31,2)) -> 47 | E31: Paving, Surfacing, and Tamping Equipment Operators | F31: {=_xlfn.IFS( AND(D31>=11, D31<=29), "Management, business, science, and arts occupations", AND(D31>=31, D31<=39), "Service occupations", AND(D31>=41, D31<=43), "Sales and office occupations", AND(D31>=51, D31<=53), "Production, transportation, and material moving occupations", AND(D31>=45, D31<=49), "Natural resources, construction, and maintenance occupations", TRUE, "Not applicable to study area" )} -> Natural resources, construction, and maintenance occupations | G31: =SUMIF(F:F, F31, A:A) -> 8738 | H31: =AVERAGEIF(F:F, F31, A:A) -> 71.04065 | I31: =_xlfn.XLOOKUP($C31,'NAICS-SOC-CIP x-walk'!C:C, 'NAICS-SOC-CIP x-walk'!H:H) -> 23 | J31: =_xlfn.XLOOKUP(K31,'ACS-NAICS-SOC x-walk'!K:K,'ACS-NAICS-SOC x-walk'!L:L) -> Construction | K31: =_xlfn.XLOOKUP($C31,'NAICS-SOC-CIP x-walk'!$C:$C, 'NAICS-SOC-CIP x-walk'!I:I) -> Construction | L31: =SUMIF(K:K, K31, A:A) -> 4669 | M31: =AVERAGEIF(K:K, K31, A:A) -> 61.434211
A32: 81 | B32: 3 | C32: 49-9071 | D32: =VALUE(LEFT(C32,2)) -> 49 | E32: Maintenance and Repair Workers, General | F32: {=_xlfn.IFS( AND(D32>=11, D32<=29), "Management, business, science, and arts occupations", AND(D32>=31, D32<=39), "Service occupations", AND(D32>=41, D32<=43), "Sales and office occupations", AND(D32>=51, D32<=53), "Production, transportation, and material moving occupations", AND(D32>=45, D32<=49), "Natural resources, construction, and maintenance occupations", TRUE, "Not applicable to study area" )} -> Natural resources, construction, and maintenance occupations | G32: =SUMIF(F:F, F32, A:A) -> 8738 | H32: =AVERAGEIF(F:F, F32, A:A) -> 71.04065 | I32: =_xlfn.XLOOKUP($C32,'NAICS-SOC-CIP x-walk'!C:C, 'NAICS-SOC-CIP x-walk'!H:H) -> 23 | J32: =_xlfn.XLOOKUP(K32,'ACS-NAICS-SOC x-walk'!K:K,'ACS-NAICS-SOC x-walk'!L:L) -> Construction | K32: =_xlfn.XLOOKUP($C32,'NAICS-SOC-CIP x-walk'!$C:$C, 'NAICS-SOC-CIP x-walk'!I:I) -> Construction | L32: =SUMIF(K:K, K32, A:A) -> 4669 | M32: =AVERAGEIF(K:K, K32, A:A) -> 61.434211
A33: 79 | B33: 1-2 | C33: 47-3012 | D33: =VALUE(LEFT(C33,2)) -> 47 | E33: Helpers--Carpenters | F33: {=_xlfn.IFS( AND(D33>=11, D33<=29), "Management, business, science, and arts occupations", AND(D33>=31, D33<=39), "Service occupations", AND(D33>=41, D33<=43), "Sales and office occupations", AND(D33>=51, D33<=53), "Production, transportation, and material moving occupations", AND(D33>=45, D33<=49), "Natural resources, construction, and maintenance occupations", TRUE, "Not applicable to study area" )} -> Natural resources, construction, and maintenance occupations | G33: =SUMIF(F:F, F33, A:A) -> 8738 | H33: =AVERAGEIF(F:F, F33, A:A) -> 71.04065 | I33: =_xlfn.XLOOKUP($C33,'NAICS-SOC-CIP x-walk'!C:C, 'NAICS-SOC-CIP x-walk'!H:H) -> 23 | J33: =_xlfn.XLOOKUP(K33,'ACS-NAICS-SOC x-walk'!K:K,'ACS-NAICS-SOC x-walk'!L:L) -> Construction | K33: =_xlfn.XLOOKUP($C33,'NAICS-SOC-CIP x-walk'!$C:$C, 'NAICS-SOC-CIP x-walk'!I:I) -> Construction | L33: =SUMIF(K:K, K33, A:A) -> 4669 | M33: =AVERAGEIF(K:K, K33, A:A) -> 61.434211
A34: 79 | B34: 1-2 | C34: 49-9011 | D34: =VALUE(LEFT(C34,2)) -> 49 | E34: Mechanical Door Repairers | F34: {=_xlfn.IFS( AND(D34>=11, D34<=29), "Management, business, science, and arts occupations", AND(D34>=31, D34<=39), "Service occupations", AND(D34>=41, D34<=43), "Sales and office occupations", AND(D34>=51, D34<=53), "Production, transportation, and material moving occupations", AND(D34>=45, D34<=49), "Natural resources, construction, and maintenance occupations", TRUE, "Not applicable to study area" )} -> Natural resources, construction, and maintenance occupations | G34: =SUMIF(F:F, F34, A:A) -> 8738 | H34: =AVERAGEIF(F:F, F34, A:A) -> 71.04065 | I34: =_xlfn.XLOOKUP($C34,'NAICS-SOC-CIP x-walk'!C:C, 'NAICS-SOC-CIP x-walk'!H:H) -> 23 | J34: =_xlfn.XLOOKUP(K34,'ACS-NAICS-SOC x-walk'!K:K,'ACS-NAICS-SOC x-walk'!L:L) -> Construction | K34: =_xlfn.XLOOKUP($C34,'NAICS-SOC-CIP x-walk'!$C:$C, 'NAICS-SOC-CIP x-walk'!I:I) -> Construction | L34: =SUMIF(K:K, K34, A:A) -> 4669 | M34: =AVERAGEIF(K:K, K34, A:A) -> 61.434211
A35: 79 | B35: 3 | C35: 47-2152 | D35: =VALUE(LEFT(C35,2)) -> 47 | E35: Solar Thermal Installers and Technicians | F35: {=_xlfn.IFS( AND(D35>=11, D35<=29), "Management, business, science, and arts occupations", AND(D35>=31, D35<=39), "Service occupations", AND(D35>=41, D35<=43), "Sales and office occupations", AND(D35>=51, D35<=53), "Production, transportation, and material moving occupations", AND(D35>=45, D35<=49), "Natural resources, construction, and maintenance occupations", TRUE, "Not applicable to study area" )} -> Natural resources, construction, and maintenance occupations | G35: =SUMIF(F:F, F35, A:A) -> 8738 | H35: =AVERAGEIF(F:F, F35, A:A) -> 71.04065 | I35: =_xlfn.XLOOKUP($C35,'NAICS-SOC-CIP x-walk'!C:C, 'NAICS-SOC-CIP x-walk'!H:H) -> 23 | J35: =_xlfn.XLOOKUP(K35,'ACS-NAICS-SOC x-walk'!K:K,'ACS-NAICS-SOC x-walk'!L:L) -> Construction | K35: =_xlfn.XLOOKUP($C35,'NAICS-SOC-CIP x-walk'!$C:$C, 'NAICS-SOC-CIP x-walk'!I:I) -> Construction | L35: =SUMIF(K:K, K35, A:A) -> 4669 | M35: =AVERAGEIF(K:K, K35, A:A) -> 61.434211
A36: 78 | B36: 3 | C36: 47-2111 | D36: =VALUE(LEFT(C36,2)) -> 47 | E36: Electricians | F36: {=_xlfn.IFS( AND(D36>=11, D36<=29), "Management, business, science, and arts occupations", AND(D36>=31, D36<=39), "Service occupations", AND(D36>=41, D36<=43), "Sales and office occupations", AND(D36>=51, D36<=53), "Production, transportation, and material moving occupations", AND(D36>=45, D36<=49), "Natural resources, construction, and maintenance occupations", TRUE, "Not applicable to study area" )} -> Natural resources, construction, and maintenance occupations | G36: =SUMIF(F:F, F36, A:A) -> 8738 | H36: =AVERAGEIF(F:F, F36, A:A) -> 71.04065 | I36: =_xlfn.XLOOKUP($C36,'NAICS-SOC-CIP x-walk'!C:C, 'NAICS-SOC-CIP x-walk'!H:H) -> 23 | J36: =_xlfn.XLOOKUP(K36,'ACS-NAICS-SOC x-walk'!K:K,'ACS-NAICS-SOC x-walk'!L:L) -> Construction | K36: =_xlfn.XLOOKUP($C36,'NAICS-SOC-CIP x-walk'!$C:$C, 'NAICS-SOC-CIP x-walk'!I:I) -> Construction | L36: =SUMIF(K:K, K36, A:A) -> 4669 | M36: =AVERAGEIF(K:K, K36, A:A) -> 61.434211
A37: 78 | B37: 1-2 | C37: 47-5022 | D37: =VALUE(LEFT(C37,2)) -> 47 | E37: Excavating and Loading Machine and Dragline Operators, Surface Mining | F37: {=_xlfn.IFS( AND(D37>=11, D37<=29), "Management, business, science, and arts occupations", AND(D37>=31, D37<=39), "Service occupations", AND(D37>=41, D37<=43), "Sales and office occupations", AND(D37>=51, D37<=53), "Production, transportation, and material moving occupations", AND(D37>=45, D37<=49), "Natural resources, construction, and maintenance occupations", TRUE, "Not applicable to study area" )} -> Natural resources, construction, and maintenance occupations | G37: =SUMIF(F:F, F37, A:A) -> 8738 | H37: =AVERAGEIF(F:F, F37, A:A) -> 71.04065 | I37: =_xlfn.XLOOKUP($C37,'NAICS-SOC-CIP x-walk'!C:C, 'NAICS-SOC-CIP x-walk'!H:H) -> 21, 22 | J37: =_xlfn.XLOOKUP(K37,'ACS-NAICS-SOC x-walk'!K:K,'ACS-NAICS-SOC x-walk'!L:L) -> Agriculture, Forestry, Fishing and Hunting, and Mining | K37: =_xlfn.XLOOKUP($C37,'NAICS-SOC-CIP x-walk'!$C:$C, 'NAICS-SOC-CIP x-walk'!I:I) -> Mining, Quarrying, and Oil and Gas Extraction, Utilities | L37: =SUMIF(K:K, K37, A:A) -> 5203 | M37: =AVERAGEIF(K:K, K37, A:A) -> 55.946237
A38: 76 | B38: 3 | C38: 49-9021 | D38: =VALUE(LEFT(C38,2)) -> 49 | E38: Heating, Air Conditioning, and Refrigeration Mechanics and Installers | F38: {=_xlfn.IFS( AND(D38>=11, D38<=29), "Management, business, science, and arts occupations", AND(D38>=31, D38<=39), "Service occupations", AND(D38>=41, D38<=43), "Sales and office occupations", AND(D38>=51, D38<=53), "Production, transportation, and material moving occupations", AND(D38>=45, D38<=49), "Natural resources, construction, and maintenance occupations", TRUE, "Not applicable to study area" )} -> Natural resources, construction, and maintenance occupations | G38: =SUMIF(F:F, F38, A:A) -> 8738 | H38: =AVERAGEIF(F:F, F38, A:A) -> 71.04065 | I38: =_xlfn.XLOOKUP($C38,'NAICS-SOC-CIP x-walk'!C:C, 'NAICS-SOC-CIP x-walk'!H:H) -> 23 | J38: =_xlfn.XLOOKUP(K38,'ACS-NAICS-SOC x-walk'!K:K,'ACS-NAICS-SOC x-walk'!L:L) -> Construction | K38: =_xlfn.XLOOKUP($C38,'NAICS-SOC-CIP x-walk'!$C:$C, 'NAICS-SOC-CIP x-walk'!I:I) -> Construction | L38: =SUMIF(K:K, K38, A:A) -> 4669 | M38: =AVERAGEIF(K:K, K38, A:A) -> 61.434211
A39: 74 | B39: 1-2 | C39: 47-3013 | D39: =VALUE(LEFT(C39,2)) -> 47 | E39: Helpers--Electricians | F39: {=_xlfn.IFS( AND(D39>=11, D39<=29), "Management, business, science, and arts occupations", AND(D39>=31, D39<=39), "Service occupations", AND(D39>=41, D39<=43), "Sales and office occupations", AND(D39>=51, D39<=53), "Production, transportation, and material moving occupations", AND(D39>=45, D39<=49), "Natural resources, construction, and maintenance occupations", TRUE, "Not applicable to study area" )} -> Natural resources, construction, and maintenance occupations | G39: =SUMIF(F:F, F39, A:A) -> 8738 | H39: =AVERAGEIF(F:F, F39, A:A) -> 71.04065 | I39: =_xlfn.XLOOKUP($C39,'NAICS-SOC-CIP x-walk'!C:C, 'NAICS-SOC-CIP x-walk'!H:H) -> 23 | J39: =_xlfn.XLOOKUP(K39,'ACS-NAICS-SOC x-walk'!K:K,'ACS-NAICS-SOC x-walk'!L:L) -> Construction | K39: =_xlfn.XLOOKUP($C39,'NAICS-SOC-CIP x-walk'!$C:$C, 'NAICS-SOC-CIP x-walk'!I:I) -> Construction | L39: =SUMIF(K:K, K39, A:A) -> 4669 | M39: =AVERAGEIF(K:K, K39, A:A) -> 61.434211
A40: 74 | B40: 1-2 | C40: 49-9098 | D40: =VALUE(LEFT(C40,2)) -> 49 | E40: Helpers--Installation, Maintenance, and Repair Workers | F40: {=_xlfn.IFS( AND(D40>=11, D40<=29), "Management, business, science, and arts occupations", AND(D40>=31, D40<=39), "Service occupations", AND(D40>=41, D40<=43), "Sales and office occupations", AND(D40>=51, D40<=53), "Production, transportation, and material moving occupations", AND(D40>=45, D40<=49), "Natural resources, construction, and maintenance occupations", TRUE, "Not applicable to study area" )} -> Natural resources, construction, and maintenance occupations | G40: =SUMIF(F:F, F40, A:A) -> 8738 | H40: =AVERAGEIF(F:F, F40, A:A) -> 71.04065 | I40: =_xlfn.XLOOKUP($C40,'NAICS-SOC-CIP x-walk'!C:C, 'NAICS-SOC-CIP x-walk'!H:H) -> 23 | J40: =_xlfn.XLOOKUP(K40,'ACS-NAICS-SOC x-walk'!K:K,'ACS-NAICS-SOC x-walk'!L:L) -> Construction | K40: =_xlfn.XLOOKUP($C40,'NAICS-SOC-CIP x-walk'!$C:$C, 'NAICS-SOC-CIP x-walk'!I:I) -> Construction | L40: =SUMIF(K:K, K40, A:A) -> 4669 | M40: =AVERAGEIF(K:K, K40, A:A) -> 61.434211
A41: 74 | B41: 1-2 | C41: 47-3014 | D41: =VALUE(LEFT(C41,2)) -> 47 | E41: Helpers--Painters, Paperhangers, Plasterers, and Stucco Masons | F41: {=_xlfn.IFS( AND(D41>=11, D41<=29), "Management, business, science, and arts occupations", AND(D41>=31, D41<=39), "Service occupations", AND(D41>=41, D41<=43), "Sales and office occupations", AND(D41>=51, D41<=53), "Production, transportation, and material moving occupations", AND(D41>=45, D41<=49), "Natural resources, construction, and maintenance occupations", TRUE, "Not applicable to study area" )} -> Natural resources, construction, and maintenance occupations | G41: =SUMIF(F:F, F41, A:A) -> 8738 | H41: =AVERAGEIF(F:F, F41, A:A) -> 71.04065 | I41: =_xlfn.XLOOKUP($C41,'NAICS-SOC-CIP x-walk'!C:C, 'NAICS-SOC-CIP x-walk'!H:H) -> 23 | J41: =_xlfn.XLOOKUP(K41,'ACS-NAICS-SOC x-walk'!K:K,'ACS-NAICS-SOC x-walk'!L:L) -> Construction | K41: =_xlfn.XLOOKUP($C41,'NAICS-SOC-CIP x-walk'!$C:$C, 'NAICS-SOC-CIP x-walk'!I:I) -> Construction | L41: =SUMIF(K:K, K41, A:A) -> 4669 | M41: =AVERAGEIF(K:K, K41, A:A) -> 61.434211
A42: 73 | B42: 1-2 | C42: 47-2031 | D42: =VALUE(LEFT(C42,2)) -> 47 | E42: Carpenters | F42: {=_xlfn.IFS( AND(D42>=11, D42<=29), "Management, business, science, and arts occupations", AND(D42>=31, D42<=39), "Service occupations", AND(D42>=41, D42<=43), "Sales and office occupations", AND(D42>=51, D42<=53), "Production, transportation, and material moving occupations", AND(D42>=45, D42<=49), "Natural resources, construction, and maintenance occupations", TRUE, "Not applicable to study area" )} -> Natural resources, construction, and maintenance occupations | G42: =SUMIF(F:F, F42, A:A) -> 8738 | H42: =AVERAGEIF(F:F, F42, A:A) -> 71.04065 | I42: =_xlfn.XLOOKUP($C42,'NAICS-SOC-CIP x-walk'!C:C, 'NAICS-SOC-CIP x-walk'!H:H) -> 23 | J42: =_xlfn.XLOOKUP(K42,'ACS-NAICS-SOC x-walk'!K:K,'ACS-NAICS-SOC x-walk'!L:L) -> Construction | K42: =_xlfn.XLOOKUP($C42,'NAICS-SOC-CIP x-walk'!$C:$C, 'NAICS-SOC-CIP x-walk'!I:I) -> Construction | L42: =SUMIF(K:K, K42, A:A) -> 4669 | M42: =AVERAGEIF(K:K, K42, A:A) -> 61.434211
A43: 72 | B43: 1-2 | C43: 47-2131 | D43: =VALUE(LEFT(C43,2)) -> 47 | E43: Insulation Workers, Floor, Ceiling, and Wall | F43: {=_xlfn.IFS( AND(D43>=11, D43<=29), "Management, business, science, and arts occupations", AND(D43>=31, D43<=39), "Service occupations", AND(D43>=41, D43<=43), "Sales and office occupations", AND(D43>=51, D43<=53), "Production, transportation, and material moving occupations", AND(D43>=45, D43<=49), "Natural resources, construction, and maintenance occupations", TRUE, "Not applicable to study area" )} -> Natural resources, construction, and maintenance occupations | G43: =SUMIF(F:F, F43, A:A) -> 8738 | H43: =AVERAGEIF(F:F, F43, A:A) -> 71.04065 | I43: =_xlfn.XLOOKUP($C43,'NAICS-SOC-CIP x-walk'!C:C, 'NAICS-SOC-CIP x-walk'!H:H) -> 23 | J43: =_xlfn.XLOOKUP(K43,'ACS-NAICS-SOC x-walk'!K:K,'ACS-NAICS-SOC x-walk'!L:L) -> Construction | K43: =_xlfn.XLOOKUP($C43,'NAICS-SOC-CIP x-walk'!$C:$C, 'NAICS-SOC-CIP x-walk'!I:I) -> Construction | L43: =SUMIF(K:K, K43, A:A) -> 4669 | M43: =AVERAGEIF(K:K, K43, A:A) -> 61.434211
A44: 72 | B44: 3 | C44: 47-2152 | D44: =VALUE(LEFT(C44,2)) -> 47 | E44: Plumbers, Pipefitters, and Steamfitters | F44: {=_xlfn.IFS( AND(D44>=11, D44<=29), "Management, business, science, and arts occupations", AND(D44>=31, D44<=39), "Service occupations", AND(D44>=41, D44<=43), "Sales and office occupations", AND(D44>=51, D44<=53), "Production, transportation, and material moving occupations", AND(D44>=45, D44<=49), "Natural resources, construction, and maintenance occupations", TRUE, "Not applicable to study area" )} -> Natural resources, construction, and maintenance occupations | G44: =SUMIF(F:F, F44, A:A) -> 8738 | H44: =AVERAGEIF(F:F, F44, A:A) -> 71.04065 | I44: =_xlfn.XLOOKUP($C44,'NAICS-SOC-CIP x-walk'!C:C, 'NAICS-SOC-CIP x-walk'!H:H) -> 23 | J44: =_xlfn.XLOOKUP(K44,'ACS-NAICS-SOC x-walk'!K:K,'ACS-NAICS-SOC x-walk'!L:L) -> Construction | K44: =_xlfn.XLOOKUP($C44,'NAICS-SOC-CIP x-walk'!$C:$C, 'NAICS-SOC-CIP x-walk'!I:I) -> Construction | L44: =SUMIF(K:K, K44, A:A) -> 4669 | M44: =AVERAGEIF(K:K, K44, A:A) -> 61.434211
A45: 68 | B45: 3 | C45: 47-4011 | D45: =VALUE(LEFT(C45,2)) -> 47 | E45: Energy Auditors | F45: {=_xlfn.IFS( AND(D45>=11, D45<=29), "Management, business, science, and arts occupations", AND(D45>=31, D45<=39), "Service occupations", AND(D45>=41, D45<=43), "Sales and office occupations", AND(D45>=51, D45<=53), "Production, transportation, and material moving occupations", AND(D45>=45, D45<=49), "Natural resources, construction, and maintenance occupations", TRUE, "Not applicable to study area" )} -> Natural resources, construction, and maintenance occupations | G45: =SUMIF(F:F, F45, A:A) -> 8738 | H45: =AVERAGEIF(F:F, F45, A:A) -> 71.04065 | I45: =_xlfn.XLOOKUP($C45,'NAICS-SOC-CIP x-walk'!C:C, 'NAICS-SOC-CIP x-walk'!H:H) -> 23 | J45: =_xlfn.XLOOKUP(K45,'ACS-NAICS-SOC x-walk'!K:K,'ACS-NAICS-SOC x-walk'!L:L) -> Construction | K45: =_xlfn.XLOOKUP($C45,'NAICS-SOC-CIP x-walk'!$C:$C, 'NAICS-SOC-CIP x-walk'!I:I) -> Construction | L45: =SUMIF(K:K, K45, A:A) -> 4669 | M45: =AVERAGEIF(K:K, K45, A:A) -> 61.434211
A46: 62 | B46: 1-2 | C46: 49-9031 | D46: =VALUE(LEFT(C46,2)) -> 49 | E46: Home Appliance Repairers | F46: {=_xlfn.IFS( AND(D46>=11, D46<=29), "Management, business, science, and arts occupations", AND(D46>=31, D46<=39), "Service occupations", AND(D46>=41, D46<=43), "Sales and office occupations", AND(D46>=51, D46<=53), "Production, transportation, and material moving occupations", AND(D46>=45, D46<=49), "Natural resources, construction, and maintenance occupations", TRUE, "Not applicable to study area" )} -> Natural resources, construction, and maintenance occupations | G46: =SUMIF(F:F, F46, A:A) -> 8738 | H46: =AVERAGEIF(F:F, F46, A:A) -> 71.04065 | I46: =_xlfn.XLOOKUP($C46,'NAICS-SOC-CIP x-walk'!C:C, 'NAICS-SOC-CIP x-walk'!H:H) -> 23 | J46: =_xlfn.XLOOKUP(K46,'ACS-NAICS-SOC x-walk'!K:K,'ACS-NAICS-SOC x-walk'!L:L) -> Construction | K46: =_xlfn.XLOOKUP($C46,'NAICS-SOC-CIP x-walk'!$C:$C, 'NAICS-SOC-CIP x-walk'!I:I) -> Construction | L46: =SUMIF(K:K, K46, A:A) -> 4669 | M46: =AVERAGEIF(K:K, K46, A:A) -> 61.434211
A47: 61 | B47: 3 | C47: 49-2098 | D47: =VALUE(LEFT(C47,2)) -> 49 | E47: Security and Fire Alarm Systems Installers | F47: {=_xlfn.IFS( AND(D47>=11, D47<=29), "Management, business, science, and arts occupations", AND(D47>=31, D47<=39), "Service occupations", AND(D47>=41, D47<=43), "Sales and office occupations", AND(D47>=51, D47<=53), "Production, transportation, and material moving occupations", AND(D47>=45, D47<=49), "Natural resources, construction, and maintenance occupations", TRUE, "Not applicable to study area" )} -> Natural resources, construction, and maintenance occupations | G47: =SUMIF(F:F, F47, A:A) -> 8738 | H47: =AVERAGEIF(F:F, F47, A:A) -> 71.04065 | I47: =_xlfn.XLOOKUP($C47,'NAICS-SOC-CIP x-walk'!C:C, 'NAICS-SOC-CIP x-walk'!H:H) -> 23 | J47: =_xlfn.XLOOKUP(K47,'ACS-NAICS-SOC x-walk'!K:K,'ACS-NAICS-SOC x-walk'!L:L) -> Construction | K47: =_xlfn.XLOOKUP($C47,'NAICS-SOC-CIP x-walk'!$C:$C, 'NAICS-SOC-CIP x-walk'!I:I) -> Construction | L47: =SUMIF(K:K, K47, A:A) -> 4669 | M47: =AVERAGEIF(K:K, K47, A:A) -> 61.434211
A48: 57 | B48: 1-2 | C48: 47-2011 | D48: =VALUE(LEFT(C48,2)) -> 47 | E48: Boilermakers | F48: {=_xlfn.IFS( AND(D48>=11, D48<=29), "Management, business, science, and arts occupations", AND(D48>=31, D48<=39), "Service occupations", AND(D48>=41, D48<=43), "Sales and office occupations", AND(D48>=51, D48<=53), "Production, transportation, and material moving occupations", AND(D48>=45, D48<=49), "Natural resources, construction, and maintenance occupations", TRUE, "Not applicable to study area" )} -> Natural resources, construction, and maintenance occupations | G48: =SUMIF(F:F, F48, A:A) -> 8738 | H48: =AVERAGEIF(F:F, F48, A:A) -> 71.04065 | I48: =_xlfn.XLOOKUP($C48,'NAICS-SOC-CIP x-walk'!C:C, 'NAICS-SOC-CIP x-walk'!H:H) -> 23 | J48: =_xlfn.XLOOKUP(K48,'ACS-NAICS-SOC x-walk'!K:K,'ACS-NAICS-SOC x-walk'!L:L) -> Construction | K48: =_xlfn.XLOOKUP($C48,'NAICS-SOC-CIP x-walk'!$C:$C, 'NAICS-SOC-CIP x-walk'!I:I) -> Construction | L48: =SUMIF(K:K, K48, A:A) -> 4669 | M48: =AVERAGEIF(K:K, K48, A:A) -> 61.434211
A49: 57 | B49: 3 | C49: 47-4021 | D49: =VALUE(LEFT(C49,2)) -> 47 | E49: Elevator and Escalator Installers and Repairers | F49: {=_xlfn.IFS( AND(D49>=11, D49<=29), "Management, business, science, and arts occupations", AND(D49>=31, D49<=39), "Service occupations", AND(D49>=41, D49<=43), "Sales and office occupations", AND(D49>=51, D49<=53), "Production, transportation, and material moving occupations", AND(D49>=45, D49<=49), "Natural resources, construction, and maintenance occupations", TRUE, "Not applicable to study area" )} -> Natural resources, construction, and maintenance occupations | G49: =SUMIF(F:F, F49, A:A) -> 8738 | H49: =AVERAGEIF(F:F, F49, A:A) -> 71.04065 | I49: =_xlfn.XLOOKUP($C49,'NAICS-SOC-CIP x-walk'!C:C, 'NAICS-SOC-CIP x-walk'!H:H) -> 23 | J49: =_xlfn.XLOOKUP(K49,'ACS-NAICS-SOC x-walk'!K:K,'ACS-NAICS-SOC x-walk'!L:L) -> Construction | K49: =_xlfn.XLOOKUP($C49,'NAICS-SOC-CIP x-walk'!$C:$C, 'NAICS-SOC-CIP x-walk'!I:I) -> Construction | L49: =SUMIF(K:K, K49, A:A) -> 4669 | M49: =AVERAGEIF(K:K, K49, A:A) -> 61.434211
A50: 57 | B50: 1-2 | C50: 47-2132 | D50: =VALUE(LEFT(C50,2)) -> 47 | E50: Insulation Workers, Mechanical | F50: {=_xlfn.IFS( AND(D50>=11, D50<=29), "Management, business, science, and arts occupations", AND(D50>=31, D50<=39), "Service occupations", AND(D50>=41, D50<=43), "Sales and office occupations", AND(D50>=51, D50<=53), "Production, transportation, and material moving occupations", AND(D50>=45, D50<=49), "Natural resources, construction, and maintenance occupations", TRUE, "Not applicable to study area" )} -> Natural resources, construction, and maintenance occupations | G50: =SUMIF(F:F, F50, A:A) -> 8738 | H50: =AVERAGEIF(F:F, F50, A:A) -> 71.04065 | I50: =_xlfn.XLOOKUP($C50,'NAICS-SOC-CIP x-walk'!C:C, 'NAICS-SOC-CIP x-walk'!H:H) -> 23 | J50: =_xlfn.XLOOKUP(K50,'ACS-NAICS-SOC x-walk'!K:K,'ACS-NAICS-SOC x-walk'!L:L) -> Construction | K50: =_xlfn.XLOOKUP($C50,'NAICS-SOC-CIP x-walk'!$C:$C, 'NAICS-SOC-CIP x-walk'!I:I) -> Construction | L50: =SUMIF(K:K, K50, A:A) -> 4669 | M50: =AVERAGEIF(K:K, K50, A:A) -> 61.434211
A51: 53 | B51: 1-2 | C51: 47-2081 | D51: =VALUE(LEFT(C51,2)) -> 47 | E51: Drywall and Ceiling Tile Installers | F51: {=_xlfn.IFS( AND(D51>=11, D51<=29), "Management, business, science, and arts occupations", AND(D51>=31, D51<=39), "Service occupations", AND(D51>=41, D51<=43), "Sales and office occupations", AND(D51>=51, D51<=53), "Production, transportation, and material moving occupations", AND(D51>=45, D51<=49), "Natural resources, construction, and maintenance occupations", TRUE, "Not applicable to study area" )} -> Natural resources, construction, and maintenance occupations | G51: =SUMIF(F:F, F51, A:A) -> 8738 | H51: =AVERAGEIF(F:F, F51, A:A) -> 71.04065 | I51: =_xlfn.XLOOKUP($C51,'NAICS-SOC-CIP x-walk'!C:C, 'NAICS-SOC-CIP x-walk'!H:H) -> 23 | J51: =_xlfn.XLOOKUP(K51,'ACS-NAICS-SOC x-walk'!K:K,'ACS-NAICS-SOC x-walk'!L:L) -> Construction | K51: =_xlfn.XLOOKUP($C51,'NAICS-SOC-CIP x-walk'!$C:$C, 'NAICS-SOC-CIP x-walk'!I:I) -> Construction | L51: =SUMIF(K:K, K51, A:A) -> 4669 | M51: =AVERAGEIF(K:K, K51, A:A) -> 61.434211
A52: 50 | B52: 1-2 | C52: 49-9045 | D52: =VALUE(LEFT(C52,2)) -> 49 | E52: Refractory Materials Repairers, Except Brickmasons | F52: {=_xlfn.IFS( AND(D52>=11, D52<=29), "Management, business, science, and arts occupations", AND(D52>=31, D52<=39), "Service occupations", AND(D52>=41, D52<=43), "Sales and office occupations", AND(D52>=51, D52<=53), "Production, transportation, and material moving occupations", AND(D52>=45, D52<=49), "Natural resources, construction, and maintenance occupations", TRUE, "Not applicable to study area" )} -> Natural resources, construction, and maintenance occupations | G52: =SUMIF(F:F, F52, A:A) -> 8738 | H52: =AVERAGEIF(F:F, F52, A:A) -> 71.04065 | I52: =_xlfn.XLOOKUP($C52,'NAICS-SOC-CIP x-walk'!C:C, 'NAICS-SOC-CIP x-walk'!H:H) -> 23 | J52: =_xlfn.XLOOKUP(K52,'ACS-NAICS-SOC x-walk'!K:K,'ACS-NAICS-SOC x-walk'!L:L) -> Construction | K52: =_xlfn.XLOOKUP($C52,'NAICS-SOC-CIP x-walk'!$C:$C, 'NAICS-SOC-CIP x-walk'!I:I) -> Construction | L52: =SUMIF(K:K, K52, A:A) -> 4669 | M52: =AVERAGEIF(K:K, K52, A:A) -> 61.434211
A53: 48 | B53: 3 | C53: 49-9043 | D53: =VALUE(LEFT(C53,2)) -> 49 | E53: Maintenance Workers, Machinery | F53: {=_xlfn.IFS( AND(D53>=11, D53<=29), "Management, business, science, and arts occupations", AND(D53>=31, D53<=39), "Service occupations", AND(D53>=41, D53<=43), "Sales and office occupations", AND(D53>=51, D53<=53), "Production, transportation, and material moving occupations", AND(D53>=45, D53<=49), "Natural resources, construction, and maintenance occupations", TRUE, "Not applicable to study area" )} -> Natural resources, construction, and maintenance occupations | G53: =SUMIF(F:F, F53, A:A) -> 8738 | H53: =AVERAGEIF(F:F, F53, A:A) -> 71.04065 | I53: =_xlfn.XLOOKUP($C53,'NAICS-SOC-CIP x-walk'!C:C, 'NAICS-SOC-CIP x-walk'!H:H) -> 23 | J53: =_xlfn.XLOOKUP(K53,'ACS-NAICS-SOC x-walk'!K:K,'ACS-NAICS-SOC x-walk'!L:L) -> Construction | K53: =_xlfn.XLOOKUP($C53,'NAICS-SOC-CIP x-walk'!$C:$C, 'NAICS-SOC-CIP x-walk'!I:I) -> Construction | L53: =SUMIF(K:K, K53, A:A) -> 4669 | M53: =AVERAGEIF(K:K, K53, A:A) -> 61.434211
A54: 47 | B54: 1-2 | C54: 47-2141 | D54: =VALUE(LEFT(C54,2)) -> 47 | E54: Painters, Construction and Maintenance | F54: {=_xlfn.IFS( AND(D54>=11, D54<=29), "Management, business, science, and arts occupations", AND(D54>=31, D54<=39), "Service occupations", AND(D54>=41, D54<=43), "Sales and office occupations", AND(D54>=51, D54<=53), "Production, transportation, and material moving occupations", AND(D54>=45, D54<=49), "Natural resources, construction, and maintenance occupations", TRUE, "Not applicable to study area" )} -> Natural resources, construction, and maintenance occupations | G54: =SUMIF(F:F, F54, A:A) -> 8738 | H54: =AVERAGEIF(F:F, F54, A:A) -> 71.04065 | I54: =_xlfn.XLOOKUP($C54,'NAICS-SOC-CIP x-walk'!C:C, 'NAICS-SOC-CIP x-walk'!H:H) -> 23 | J54: =_xlfn.XLOOKUP(K54,'ACS-NAICS-SOC x-walk'!K:K,'ACS-NAICS-SOC x-walk'!L:L) -> Construction | K54: =_xlfn.XLOOKUP($C54,'NAICS-SOC-CIP x-walk'!$C:$C, 'NAICS-SOC-CIP x-walk'!I:I) -> Construction | L54: =SUMIF(K:K, K54, A:A) -> 4669 | M54: =AVERAGEIF(K:K, K54, A:A) -> 61.434211
A55: 45 | B55: 1-2 | C55: 47-2044 | D55: =VALUE(LEFT(C55,2)) -> 47 | E55: Tile and Stone Setters | F55: {=_xlfn.IFS( AND(D55>=11, D55<=29), "Management, business, science, and arts occupations", AND(D55>=31, D55<=39), "Service occupations", AND(D55>=41, D55<=43), "Sales and office occupations", AND(D55>=51, D55<=53), "Production, transportation, and material moving occupations", AND(D55>=45, D55<=49), "Natural resources, construction, and maintenance occupations", TRUE, "Not applicable to study area" )} -> Natural resources, construction, and maintenance occupations | G55: =SUMIF(F:F, F55, A:A) -> 8738 | H55: =AVERAGEIF(F:F, F55, A:A) -> 71.04065 | I55: =_xlfn.XLOOKUP($C55,'NAICS-SOC-CIP x-walk'!C:C, 'NAICS-SOC-CIP x-walk'!H:H) -> 23 | J55: =_xlfn.XLOOKUP(K55,'ACS-NAICS-SOC x-walk'!K:K,'ACS-NAICS-SOC x-walk'!L:L) -> Construction | K55: =_xlfn.XLOOKUP($C55,'NAICS-SOC-CIP x-walk'!$C:$C, 'NAICS-SOC-CIP x-walk'!I:I) -> Construction | L55: =SUMIF(K:K, K55, A:A) -> 4669 | M55: =AVERAGEIF(K:K, K55, A:A) -> 61.434211
A56: 44 | B56: 1-2 | C56: 47-2142 | D56: =VALUE(LEFT(C56,2)) -> 47 | E56: Paperhangers | F56: {=_xlfn.IFS( AND(D56>=11, D56<=29), "Management, business, science, and arts occupations", AND(D56>=31, D56<=39), "Service occupations", AND(D56>=41, D56<=43), "Sales and office occupations", AND(D56>=51, D56<=53), "Production, transportation, and material moving occupations", AND(D56>=45, D56<=49), "Natural resources, construction, and maintenance occupations", TRUE, "Not applicable to study area" )} -> Natural resources, construction, and maintenance occupations | G56: =SUMIF(F:F, F56, A:A) -> 8738 | H56: =AVERAGEIF(F:F, F56, A:A) -> 71.04065 | I56: =_xlfn.XLOOKUP($C56,'NAICS-SOC-CIP x-walk'!C:C, 'NAICS-SOC-CIP x-walk'!H:H) -> 23 | J56: =_xlfn.XLOOKUP(K56,'ACS-NAICS-SOC x-walk'!K:K,'ACS-NAICS-SOC x-walk'!L:L) -> Construction | K56: =_xlfn.XLOOKUP($C56,'NAICS-SOC-CIP x-walk'!$C:$C, 'NAICS-SOC-CIP x-walk'!I:I) -> Construction | L56: =SUMIF(K:K, K56, A:A) -> 4669 | M56: =AVERAGEIF(K:K, K56, A:A) -> 61.434211
A57: 38 | B57: 1-2 | C57: 47-2211 | D57: =VALUE(LEFT(C57,2)) -> 47 | E57: Sheet Metal Workers | F57: {=_xlfn.IFS( AND(D57>=11, D57<=29), "Management, business, science, and arts occupations", AND(D57>=31, D57<=39), "Service occupations", AND(D57>=41, D57<=43), "Sales and office occupations", AND(D57>=51, D57<=53), "Production, transportation, and material moving occupations", AND(D57>=45, D57<=49), "Natural resources, construction, and maintenance occupations", TRUE, "Not applicable to study area" )} -> Natural resources, construction, and maintenance occupations | G57: =SUMIF(F:F, F57, A:A) -> 8738 | H57: =AVERAGEIF(F:F, F57, A:A) -> 71.04065 | I57: =_xlfn.XLOOKUP($C57,'NAICS-SOC-CIP x-walk'!C:C, 'NAICS-SOC-CIP x-walk'!H:H) -> 23 | J57: =_xlfn.XLOOKUP(K57,'ACS-NAICS-SOC x-walk'!K:K,'ACS-NAICS-SOC x-walk'!L:L) -> Construction | K57: =_xlfn.XLOOKUP($C57,'NAICS-SOC-CIP x-walk'!$C:$C, 'NAICS-SOC-CIP x-walk'!I:I) -> Construction | L57: =SUMIF(K:K, K57, A:A) -> 4669 | M57: =AVERAGEIF(K:K, K57, A:A) -> 61.434211
A58: 27 | B58: 1-2 | C58: 47-2041 | D58: =VALUE(LEFT(C58,2)) -> 47 | E58: Carpet Installers | F58: {=_xlfn.IFS( AND(D58>=11, D58<=29), "Management, business, science, and arts occupations", AND(D58>=31, D58<=39), "Service occupations", AND(D58>=41, D58<=43), "Sales and office occupations", AND(D58>=51, D58<=53), "Production, transportation, and material moving occupations", AND(D58>=45, D58<=49), "Natural resources, construction, and maintenance occupations", TRUE, "Not applicable to study area" )} -> Natural resources, construction, and maintenance occupations | G58: =SUMIF(F:F, F58, A:A) -> 8738 | H58: =AVERAGEIF(F:F, F58, A:A) -> 71.04065 | I58: =_xlfn.XLOOKUP($C58,'NAICS-SOC-CIP x-walk'!C:C, 'NAICS-SOC-CIP x-walk'!H:H) -> 23 | J58: =_xlfn.XLOOKUP(K58,'ACS-NAICS-SOC x-walk'!K:K,'ACS-NAICS-SOC x-walk'!L:L) -> Construction | K58: =_xlfn.XLOOKUP($C58,'NAICS-SOC-CIP x-walk'!$C:$C, 'NAICS-SOC-CIP x-walk'!I:I) -> Construction | L58: =SUMIF(K:K, K58, A:A) -> 4669 | M58: =AVERAGEIF(K:K, K58, A:A) -> 61.434211
A59: 24 | B59: 1-2 | C59: 47-2053 | D59: =VALUE(LEFT(C59,2)) -> 47 | E59: Terrazzo Workers and Finishers | F59: {=_xlfn.IFS( AND(D59>=11, D59<=29), "Management, business, science, and arts occupations", AND(D59>=31, D59<=39), "Service occupations", AND(D59>=41, D59<=43), "Sales and office occupations", AND(D59>=51, D59<=53), "Production, transportation, and material moving occupations", AND(D59>=45, D59<=49), "Natural resources, construction, and maintenance occupations", TRUE, "Not applicable to study area" )} -> Natural resources, construction, and maintenance occupations | G59: =SUMIF(F:F, F59, A:A) -> 8738 | H59: =AVERAGEIF(F:F, F59, A:A) -> 71.04065 | I59: =_xlfn.XLOOKUP($C59,'NAICS-SOC-CIP x-walk'!C:C, 'NAICS-SOC-CIP x-walk'!H:H) -> 23 | J59: =_xlfn.XLOOKUP(K59,'ACS-NAICS-SOC x-walk'!K:K,'ACS-NAICS-SOC x-walk'!L:L) -> Construction | K59: =_xlfn.XLOOKUP($C59,'NAICS-SOC-CIP x-walk'!$C:$C, 'NAICS-SOC-CIP x-walk'!I:I) -> Construction | L59: =SUMIF(K:K, K59, A:A) -> 4669 | M59: =AVERAGEIF(K:K, K59, A:A) -> 61.434211
A60: 23 | B60: 1-2 | C60: 47-5041 | D60: =VALUE(LEFT(C60,2)) -> 47 | E60: Continuous Mining Machine Operators | F60: {=_xlfn.IFS( AND(D60>=11, D60<=29), "Management, business, science, and arts occupations", AND(D60>=31, D60<=39), "Service occupations", AND(D60>=41, D60<=43), "Sales and office occupations", AND(D60>=51, D60<=53), "Production, transportation, and material moving occupations", AND(D60>=45, D60<=49), "Natural resources, construction, and maintenance occupations", TRUE, "Not applicable to study area" )} -> Natural resources, construction, and maintenance occupations | G60: =SUMIF(F:F, F60, A:A) -> 8738 | H60: =AVERAGEIF(F:F, F60, A:A) -> 71.04065 | I60: =_xlfn.XLOOKUP($C60,'NAICS-SOC-CIP x-walk'!C:C, 'NAICS-SOC-CIP x-walk'!H:H) -> 21, 22 | J60: =_xlfn.XLOOKUP(K60,'ACS-NAICS-SOC x-walk'!K:K,'ACS-NAICS-SOC x-walk'!L:L) -> Agriculture, Forestry, Fishing and Hunting, and Mining | K60: =_xlfn.XLOOKUP($C60,'NAICS-SOC-CIP x-walk'!$C:$C, 'NAICS-SOC-CIP x-walk'!I:I) -> Mining, Quarrying, and Oil and Gas Extraction, Utilities | L60: =SUMIF(K:K, K60, A:A) -> 5203 | M60: =AVERAGEIF(K:K, K60, A:A) -> 55.946237
A61: 23 | B61: 1-2 | C61: 47-2082 | D61: =VALUE(LEFT(C61,2)) -> 47 | E61: Tapers | F61: {=_xlfn.IFS( AND(D61>=11, D61<=29), "Management, business, science, and arts occupations", AND(D61>=31, D61<=39), "Service occupations", AND(D61>=41, D61<=43), "Sales and office occupations", AND(D61>=51, D61<=53), "Production, transportation, and material moving occupations", AND(D61>=45, D61<=49), "Natural resources, construction, and maintenance occupations", TRUE, "Not applicable to study area" )} -> Natural resources, construction, and maintenance occupations | G61: =SUMIF(F:F, F61, A:A) -> 8738 | H61: =AVERAGEIF(F:F, F61, A:A) -> 71.04065 | I61: =_xlfn.XLOOKUP($C61,'NAICS-SOC-CIP x-walk'!C:C, 'NAICS-SOC-CIP x-walk'!H:H) -> 23 | J61: =_xlfn.XLOOKUP(K61,'ACS-NAICS-SOC x-walk'!K:K,'ACS-NAICS-SOC x-walk'!L:L) -> Construction | K61: =_xlfn.XLOOKUP($C61,'NAICS-SOC-CIP x-walk'!$C:$C, 'NAICS-SOC-CIP x-walk'!I:I) -> Construction | L61: =SUMIF(K:K, K61, A:A) -> 4669 | M61: =AVERAGEIF(K:K, K61, A:A) -> 61.434211
A62: 21 | B62: 1-2 | C62: 47-2043 | D62: =VALUE(LEFT(C62,2)) -> 47 | E62: Floor Sanders and Finishers | F62: {=_xlfn.IFS( AND(D62>=11, D62<=29), "Management, business, science, and arts occupations", AND(D62>=31, D62<=39), "Service occupations", AND(D62>=41, D62<=43), "Sales and office occupations", AND(D62>=51, D62<=53), "Production, transportation, and material moving occupations", AND(D62>=45, D62<=49), "Natural resources, construction, and maintenance occupations", TRUE, "Not applicable to study area" )} -> Natural resources, construction, and maintenance occupations | G62: =SUMIF(F:F, F62, A:A) -> 8738 | H62: =AVERAGEIF(F:F, F62, A:A) -> 71.04065 | I62: =_xlfn.XLOOKUP($C62,'NAICS-SOC-CIP x-walk'!C:C, 'NAICS-SOC-CIP x-walk'!H:H) -> 23 | J62: =_xlfn.XLOOKUP(K62,'ACS-NAICS-SOC x-walk'!K:K,'ACS-NAICS-SOC x-walk'!L:L) -> Construction | K62: =_xlfn.XLOOKUP($C62,'NAICS-SOC-CIP x-walk'!$C:$C, 'NAICS-SOC-CIP x-walk'!I:I) -> Construction | L62: =SUMIF(K:K, K62, A:A) -> 4669 | M62: =AVERAGEIF(K:K, K62, A:A) -> 61.434211
A63: 19 | B63: 1-2 | C63: 47-2042 | D63: =VALUE(LEFT(C63,2)) -> 47 | E63: Floor Layers, Except Carpet, Wood, and Hard Tiles | F63: {=_xlfn.IFS( AND(D63>=11, D63<=29), "Management, business, science, and arts occupations", AND(D63>=31, D63<=39), "Service occupations", AND(D63>=41, D63<=43), "Sales and office occupations", AND(D63>=51, D63<=53), "Production, transportation, and material moving occupations", AND(D63>=45, D63<=49), "Natural resources, construction, and maintenance occupations", TRUE, "Not applicable to study area" )} -> Natural resources, construction, and maintenance occupations | G63: =SUMIF(F:F, F63, A:A) -> 8738 | H63: =AVERAGEIF(F:F, F63, A:A) -> 71.04065 | I63: =_xlfn.XLOOKUP($C63,'NAICS-SOC-CIP x-walk'!C:C, 'NAICS-SOC-CIP x-walk'!H:H) -> 23 | J63: =_xlfn.XLOOKUP(K63,'ACS-NAICS-SOC x-walk'!K:K,'ACS-NAICS-SOC x-walk'!L:L) -> Construction | K63: =_xlfn.XLOOKUP($C63,'NAICS-SOC-CIP x-walk'!$C:$C, 'NAICS-SOC-CIP x-walk'!I:I) -> Construction | L63: =SUMIF(K:K, K63, A:A) -> 4669 | M63: =AVERAGEIF(K:K, K63, A:A) -> 61.434211
A64: 17 | B64: 1-2 | C64: 51-4122 | D64: =VALUE(LEFT(C64,2)) -> 51 | E64: Welding, Soldering, and Brazing Machine Setters, Operators, and Tenders | F64: {=_xlfn.IFS( AND(D64>=11, D64<=29), "Management, business, science, and arts occupations", AND(D64>=31, D64<=39), "Service occupations", AND(D64>=41, D64<=43), "Sales and office occupations", AND(D64>=51, D64<=53), "Production, transportation, and material moving occupations", AND(D64>=45, D64<=49), "Natural resources, construction, and maintenance occupations", TRUE, "Not applicable to study area" )} -> Production, transportation, and material moving occupations | G64: =SUMIF(F:F, F64, A:A) -> 5839 | H64: =AVERAGEIF(F:F, F64, A:A) -> 37.429487 | I64: =_xlfn.XLOOKUP($C64,'NAICS-SOC-CIP x-walk'!C:C, 'NAICS-SOC-CIP x-walk'!H:H) -> 23 | J64: =_xlfn.XLOOKUP(K64,'ACS-NAICS-SOC x-walk'!K:K,'ACS-NAICS-SOC x-walk'!L:L) -> Construction | K64: =_xlfn.XLOOKUP($C64,'NAICS-SOC-CIP x-walk'!$C:$C, 'NAICS-SOC-CIP x-walk'!I:I) -> Construction | L64: =SUMIF(K:K, K64, A:A) -> 4669 | M64: =AVERAGEIF(K:K, K64, A:A) -> 61.434211
A65: 8 | B65: 3 | C65: 51-4111 | D65: =VALUE(LEFT(C65,2)) -> 51 | E65: Tool and Die Makers | F65: {=_xlfn.IFS( AND(D65>=11, D65<=29), "Management, business, science, and arts occupations", AND(D65>=31, D65<=39), "Service occupations", AND(D65>=41, D65<=43), "Sales and office occupations", AND(D65>=51, D65<=53), "Production, transportation, and material moving occupations", AND(D65>=45, D65<=49), "Natural resources, construction, and maintenance occupations", TRUE, "Not applicable to study area" )} -> Production, transportation, and material moving occupations | G65: =SUMIF(F:F, F65, A:A) -> 5839 | H65: =AVERAGEIF(F:F, F65, A:A) -> 37.429487 | I65: =_xlfn.XLOOKUP($C65,'NAICS-SOC-CIP x-walk'!C:C, 'NAICS-SOC-CIP x-walk'!H:H) -> 23 | J65: =_xlfn.XLOOKUP(K65,'ACS-NAICS-SOC x-walk'!K:K,'ACS-NAICS-SOC x-walk'!L:L) -> Construction | K65: =_xlfn.XLOOKUP($C65,'NAICS-SOC-CIP x-walk'!$C:$C, 'NAICS-SOC-CIP x-walk'!I:I) -> Construction | L65: =SUMIF(K:K, K65, A:A) -> 4669 | M65: =AVERAGEIF(K:K, K65, A:A) -> 61.434211
A66: 6 | B66: 1-2 | C66: 51-9123 | D66: =VALUE(LEFT(C66,2)) -> 51 | E66: Painting, Coating, and Decorating Workers | F66: {=_xlfn.IFS( AND(D66>=11, D66<=29), "Management, business, science, and arts occupations", AND(D66>=31, D66<=39), "Service occupations", AND(D66>=41, D66<=43), "Sales and office occupations", AND(D66>=51, D66<=53), "Production, transportation, and material moving occupations", AND(D66>=45, D66<=49), "Natural resources, construction, and maintenance occupations", TRUE, "Not applicable to study area" )} -> Production, transportation, and material moving occupations | G66: =SUMIF(F:F, F66, A:A) -> 5839 | H66: =AVERAGEIF(F:F, F66, A:A) -> 37.429487 | I66: =_xlfn.XLOOKUP($C66,'NAICS-SOC-CIP x-walk'!C:C, 'NAICS-SOC-CIP x-walk'!H:H) -> 23 | J66: =_xlfn.XLOOKUP(K66,'ACS-NAICS-SOC x-walk'!K:K,'ACS-NAICS-SOC x-walk'!L:L) -> Construction | K66: =_xlfn.XLOOKUP($C66,'NAICS-SOC-CIP x-walk'!$C:$C, 'NAICS-SOC-CIP x-walk'!I:I) -> Construction | L66: =SUMIF(K:K, K66, A:A) -> 4669 | M66: =AVERAGEIF(K:K, K66, A:A) -> 61.434211
A67: 86 | B67: 4 | C67: 17-1022 | D67: =VALUE(LEFT(C67,2)) -> 17 | E67: Surveyors | F67: {=_xlfn.IFS( AND(D67>=11, D67<=29), "Management, business, science, and arts occupations", AND(D67>=31, D67<=39), "Service occupations", AND(D67>=41, D67<=43), "Sales and office occupations", AND(D67>=51, D67<=53), "Production, transportation, and material moving occupations", AND(D67>=45, D67<=49), "Natural resources, construction, and maintenance occupations", TRUE, "Not applicable to study area" )} -> Management, business, science, and arts occupations | G67: =SUMIF(F:F, F67, A:A) -> 9764 | H67: =AVERAGEIF(F:F, F67, A:A) -> 21.941573 | I67: =_xlfn.XLOOKUP($C67,'NAICS-SOC-CIP x-walk'!C:C, 'NAICS-SOC-CIP x-walk'!H:H) -> 21, 22 | J67: =_xlfn.XLOOKUP(K67,'ACS-NAICS-SOC x-walk'!K:K,'ACS-NAICS-SOC x-walk'!L:L) -> Agriculture, Forestry, Fishing and Hunting, and Mining | K67: =_xlfn.XLOOKUP($C67,'NAICS-SOC-CIP x-walk'!$C:$C, 'NAICS-SOC-CIP x-walk'!I:I) -> Mining, Quarrying, and Oil and Gas Extraction, Utilities | L67: =SUMIF(K:K, K67, A:A) -> 5203 | M67: =AVERAGEIF(K:K, K67, A:A) -> 55.946237
A68: 71 | B68: 4 | C68: 11-9021 | D68: =VALUE(LEFT(C68,2)) -> 11 | E68: Construction Managers | F68: {=_xlfn.IFS( AND(D68>=11, D68<=29), "Management, business, science, and arts occupations", AND(D68>=31, D68<=39), "Service occupations", AND(D68>=41, D68<=43), "Sales and office occupations", AND(D68>=51, D68<=53), "Production, transportation, and material moving occupations", AND(D68>=45, D68<=49), "Natural resources, construction, and maintenance occupations", TRUE, "Not applicable to study area" )} -> Management, business, science, and arts occupations | G68: =SUMIF(F:F, F68, A:A) -> 9764 | H68: =AVERAGEIF(F:F, F68, A:A) -> 21.941573 | I68: =_xlfn.XLOOKUP($C68,'NAICS-SOC-CIP x-walk'!C:C, 'NAICS-SOC-CIP x-walk'!H:H) -> 23 | J68: =_xlfn.XLOOKUP(K68,'ACS-NAICS-SOC x-walk'!K:K,'ACS-NAICS-SOC x-walk'!L:L) -> Construction | K68: =_xlfn.XLOOKUP($C68,'NAICS-SOC-CIP x-walk'!$C:$C, 'NAICS-SOC-CIP x-walk'!I:I) -> Construction | L68: =SUMIF(K:K, K68, A:A) -> 4669 | M68: =AVERAGEIF(K:K, K68, A:A) -> 61.434211
A69: 69 | B69: 4 | C69: 17-1022 | D69: =VALUE(LEFT(C69,2)) -> 17 | E69: Geodetic Surveyors | F69: {=_xlfn.IFS( AND(D69>=11, D69<=29), "Management, business, science, and arts occupations", AND(D69>=31, D69<=39), "Service occupations", AND(D69>=41, D69<=43), "Sales and office occupations", AND(D69>=51, D69<=53), "Production, transportation, and material moving occupations", AND(D69>=45, D69<=49), "Natural resources, construction, and maintenance occupations", TRUE, "Not applicable to study area" )} -> Management, business, science, and arts occupations | G69: =SUMIF(F:F, F69, A:A) -> 9764 | H69: =AVERAGEIF(F:F, F69, A:A) -> 21.941573 | I69: =_xlfn.XLOOKUP($C69,'NAICS-SOC-CIP x-walk'!C:C, 'NAICS-SOC-CIP x-walk'!H:H) -> 21, 22 | J69: =_xlfn.XLOOKUP(K69,'ACS-NAICS-SOC x-walk'!K:K,'ACS-NAICS-SOC x-walk'!L:L) -> Agriculture, Forestry, Fishing and Hunting, and Mining | K69: =_xlfn.XLOOKUP($C69,'NAICS-SOC-CIP x-walk'!$C:$C, 'NAICS-SOC-CIP x-walk'!I:I) -> Mining, Quarrying, and Oil and Gas Extraction, Utilities | L69: =SUMIF(K:K, K69, A:A) -> 5203 | M69: =AVERAGEIF(K:K, K69, A:A) -> 55.946237
A70: 63 | B70: 3 | C70: 17-3022 | D70: =VALUE(LEFT(C70,2)) -> 17 | E70: Civil Engineering Technologists and Technicians | F70: {=_xlfn.IFS( AND(D70>=11, D70<=29), "Management, business, science, and arts occupations", AND(D70>=31, D70<=39), "Service occupations", AND(D70>=41, D70<=43), "Sales and office occupations", AND(D70>=51, D70<=53), "Production, transportation, and material moving occupations", AND(D70>=45, D70<=49), "Natural resources, construction, and maintenance occupations", TRUE, "Not applicable to study area" )} -> Management, business, science, and arts occupations | G70: =SUMIF(F:F, F70, A:A) -> 9764 | H70: =AVERAGEIF(F:F, F70, A:A) -> 21.941573 | I70: =_xlfn.XLOOKUP($C70,'NAICS-SOC-CIP x-walk'!C:C, 'NAICS-SOC-CIP x-walk'!H:H) -> 21, 22 | J70: =_xlfn.XLOOKUP(K70,'ACS-NAICS-SOC x-walk'!K:K,'ACS-NAICS-SOC x-walk'!L:L) -> Agriculture, Forestry, Fishing and Hunting, and Mining | K70: =_xlfn.XLOOKUP($C70,'NAICS-SOC-CIP x-walk'!$C:$C, 'NAICS-SOC-CIP x-walk'!I:I) -> Mining, Quarrying, and Oil and Gas Extraction, Utilities | L70: =SUMIF(K:K, K70, A:A) -> 5203 | M70: =AVERAGEIF(K:K, K70, A:A) -> 55.946237
A71: 48 | B71: 4 | C71: 17-1012 | D71: =VALUE(LEFT(C71,2)) -> 17 | E71: Landscape Architects | F71: {=_xlfn.IFS( AND(D71>=11, D71<=29), "Management, business, science, and arts occupations", AND(D71>=31, D71<=39), "Service occupations", AND(D71>=41, D71<=43), "Sales and office occupations", AND(D71>=51, D71<=53), "Production, transportation, and material moving occupations", AND(D71>=45, D71<=49), "Natural resources, construction, and maintenance occupations", TRUE, "Not applicable to study area" )} -> Management, business, science, and arts occupations | G71: =SUMIF(F:F, F71, A:A) -> 9764 | H71: =AVERAGEIF(F:F, F71, A:A) -> 21.941573 | I71: =_xlfn.XLOOKUP($C71,'NAICS-SOC-CIP x-walk'!C:C, 'NAICS-SOC-CIP x-walk'!H:H) -> 23 | J71: =_xlfn.XLOOKUP(K71,'ACS-NAICS-SOC x-walk'!K:K,'ACS-NAICS-SOC x-walk'!L:L) -> Construction | K71: =_xlfn.XLOOKUP($C71,'NAICS-SOC-CIP x-walk'!$C:$C, 'NAICS-SOC-CIP x-walk'!I:I) -> Construction | L71: =SUMIF(K:K, K71, A:A) -> 4669 | M71: =AVERAGEIF(K:K, K71, A:A) -> 61.434211
A72: 47 | B72: 4 | C72: 17-2051 | D72: =VALUE(LEFT(C72,2)) -> 17 | E72: Transportation Engineers | F72: {=_xlfn.IFS( AND(D72>=11, D72<=29), "Management, business, science, and arts occupations", AND(D72>=31, D72<=39), "Service occupations", AND(D72>=41, D72<=43), "Sales and office occupations", AND(D72>=51, D72<=53), "Production, transportation, and material moving occupations", AND(D72>=45, D72<=49), "Natural resources, construction, and maintenance occupations", TRUE, "Not applicable to study area" )} -> Management, business, science, and arts occupations | G72: =SUMIF(F:F, F72, A:A) -> 9764 | H72: =AVERAGEIF(F:F, F72, A:A) -> 21.941573 | I72: =_xlfn.XLOOKUP($C72,'NAICS-SOC-CIP x-walk'!C:C, 'NAICS-SOC-CIP x-walk'!H:H) -> 23 | J72: =_xlfn.XLOOKUP(K72,'ACS-NAICS-SOC x-walk'!K:K,'ACS-NAICS-SOC x-walk'!L:L) -> Construction | K72: =_xlfn.XLOOKUP($C72,'NAICS-SOC-CIP x-walk'!$C:$C, 'NAICS-SOC-CIP x-walk'!I:I) -> Construction | L72: =SUMIF(K:K, K72, A:A) -> 4669 | M72: =AVERAGEIF(K:K, K72, A:A) -> 61.434211
A73: 47 | B73: 4 | C73: 17-2051 | D73: =VALUE(LEFT(C73,2)) -> 17 | E73: Water/Wastewater Engineers | F73: {=_xlfn.IFS( AND(D73>=11, D73<=29), "Management, business, science, and arts occupations", AND(D73>=31, D73<=39), "Service occupations", AND(D73>=41, D73<=43), "Sales and office occupations", AND(D73>=51, D73<=53), "Production, transportation, and material moving occupations", AND(D73>=45, D73<=49), "Natural resources, construction, and maintenance occupations", TRUE, "Not applicable to study area" )} -> Management, business, science, and arts occupations | G73: =SUMIF(F:F, F73, A:A) -> 9764 | H73: =AVERAGEIF(F:F, F73, A:A) -> 21.941573 | I73: =_xlfn.XLOOKUP($C73,'NAICS-SOC-CIP x-walk'!C:C, 'NAICS-SOC-CIP x-walk'!H:H) -> 23 | J73: =_xlfn.XLOOKUP(K73,'ACS-NAICS-SOC x-walk'!K:K,'ACS-NAICS-SOC x-walk'!L:L) -> Construction | K73: =_xlfn.XLOOKUP($C73,'NAICS-SOC-CIP x-walk'!$C:$C, 'NAICS-SOC-CIP x-walk'!I:I) -> Construction | L73: =SUMIF(K:K, K73, A:A) -> 4669 | M73: =AVERAGEIF(K:K, K73, A:A) -> 61.434211
A74: 45 | B74: 4 | C74: 17-2051 | D74: =VALUE(LEFT(C74,2)) -> 17 | E74: Civil Engineers | F74: {=_xlfn.IFS( AND(D74>=11, D74<=29), "Management, business, science, and arts occupations", AND(D74>=31, D74<=39), "Service occupations", AND(D74>=41, D74<=43), "Sales and office occupations", AND(D74>=51, D74<=53), "Production, transportation, and material moving occupations", AND(D74>=45, D74<=49), "Natural resources, construction, and maintenance occupations", TRUE, "Not applicable to study area" )} -> Management, business, science, and arts occupations | G74: =SUMIF(F:F, F74, A:A) -> 9764 | H74: =AVERAGEIF(F:F, F74, A:A) -> 21.941573 | I74: =_xlfn.XLOOKUP($C74,'NAICS-SOC-CIP x-walk'!C:C, 'NAICS-SOC-CIP x-walk'!H:H) -> 23 | J74: =_xlfn.XLOOKUP(K74,'ACS-NAICS-SOC x-walk'!K:K,'ACS-NAICS-SOC x-walk'!L:L) -> Construction | K74: =_xlfn.XLOOKUP($C74,'NAICS-SOC-CIP x-walk'!$C:$C, 'NAICS-SOC-CIP x-walk'!I:I) -> Construction | L74: =SUMIF(K:K, K74, A:A) -> 4669 | M74: =AVERAGEIF(K:K, K74, A:A) -> 61.434211
A75: 41 | B75: 5 | C75: 17-1011 | D75: =VALUE(LEFT(C75,2)) -> 17 | E75: Architects, Except Landscape and Naval | F75: {=_xlfn.IFS( AND(D75>=11, D75<=29), "Management, business, science, and arts occupations", AND(D75>=31, D75<=39), "Service occupations", AND(D75>=41, D75<=43), "Sales and office occupations", AND(D75>=51, D75<=53), "Production, transportation, and material moving occupations", AND(D75>=45, D75<=49), "Natural resources, construction, and maintenance occupations", TRUE, "Not applicable to study area" )} -> Management, business, science, and arts occupations | G75: =SUMIF(F:F, F75, A:A) -> 9764 | H75: =AVERAGEIF(F:F, F75, A:A) -> 21.941573 | I75: =_xlfn.XLOOKUP($C75,'NAICS-SOC-CIP x-walk'!C:C, 'NAICS-SOC-CIP x-walk'!H:H) -> 23 | J75: =_xlfn.XLOOKUP(K75,'ACS-NAICS-SOC x-walk'!K:K,'ACS-NAICS-SOC x-walk'!L:L) -> Construction | K75: =_xlfn.XLOOKUP($C75,'NAICS-SOC-CIP x-walk'!$C:$C, 'NAICS-SOC-CIP x-walk'!I:I) -> Construction | L75: =SUMIF(K:K, K75, A:A) -> 4669 | M75: =AVERAGEIF(K:K, K75, A:A) -> 61.434211
A76: 34 | B76: 3 | C76: 17-3011 | D76: =VALUE(LEFT(C76,2)) -> 17 | E76: Architectural and Civil Drafters | F76: {=_xlfn.IFS( AND(D76>=11, D76<=29), "Management, business, science, and arts occupations", AND(D76>=31, D76<=39), "Service occupations", AND(D76>=41, D76<=43), "Sales and office occupations", AND(D76>=51, D76<=53), "Production, transportation, and material moving occupations", AND(D76>=45, D76<=49), "Natural resources, construction, and maintenance occupations", TRUE, "Not applicable to study area" )} -> Management, business, science, and arts occupations | G76: =SUMIF(F:F, F76, A:A) -> 9764 | H76: =AVERAGEIF(F:F, F76, A:A) -> 21.941573 | I76: =_xlfn.XLOOKUP($C76,'NAICS-SOC-CIP x-walk'!C:C, 'NAICS-SOC-CIP x-walk'!H:H) -> 23 | J76: =_xlfn.XLOOKUP(K76,'ACS-NAICS-SOC x-walk'!K:K,'ACS-NAICS-SOC x-walk'!L:L) -> Construction | K76: =_xlfn.XLOOKUP($C76,'NAICS-SOC-CIP x-walk'!$C:$C, 'NAICS-SOC-CIP x-walk'!I:I) -> Construction | L76: =SUMIF(K:K, K76, A:A) -> 4669 | M76: =AVERAGEIF(K:K, K76, A:A) -> 61.434211
A77: 31 | B77: 5 | C77: 19-3051 | D77: =VALUE(LEFT(C77,2)) -> 19 | E77: Urban and Regional Planners | F77: {=_xlfn.IFS( AND(D77>=11, D77<=29), "Management, business, science, and arts occupations", AND(D77>=31, D77<=39), "Service occupations", AND(D77>=41, D77<=43), "Sales and office occupations", AND(D77>=51, D77<=53), "Production, transportation, and material moving occupations", AND(D77>=45, D77<=49), "Natural resources, construction, and maintenance occupations", TRUE, "Not applicable to study area" )} -> Management, business, science, and arts occupations | G77: =SUMIF(F:F, F77, A:A) -> 9764 | H77: =AVERAGEIF(F:F, F77, A:A) -> 21.941573 | I77: =_xlfn.XLOOKUP($C77,'NAICS-SOC-CIP x-walk'!C:C, 'NAICS-SOC-CIP x-walk'!H:H) -> 23 | J77: =_xlfn.XLOOKUP(K77,'ACS-NAICS-SOC x-walk'!K:K,'ACS-NAICS-SOC x-walk'!L:L) -> Construction | K77: =_xlfn.XLOOKUP($C77,'NAICS-SOC-CIP x-walk'!$C:$C, 'NAICS-SOC-CIP x-walk'!I:I) -> Construction | L77: =SUMIF(K:K, K77, A:A) -> 4669 | M77: =AVERAGEIF(K:K, K77, A:A) -> 61.434211
A78: 26 | B78: 4 | C78: 17-1021 | D78: =VALUE(LEFT(C78,2)) -> 17 | E78: Cartographers and Photogrammetrists | F78: {=_xlfn.IFS( AND(D78>=11, D78<=29), "Management, business, science, and arts occupations", AND(D78>=31, D78<=39), "Service occupations", AND(D78>=41, D78<=43), "Sales and office occupations", AND(D78>=51, D78<=53), "Production, transportation, and material moving occupations", AND(D78>=45, D78<=49), "Natural resources, construction, and maintenance occupations", TRUE, "Not applicable to study area" )} -> Management, business, science, and arts occupations | G78: =SUMIF(F:F, F78, A:A) -> 9764 | H78: =AVERAGEIF(F:F, F78, A:A) -> 21.941573 | I78: =_xlfn.XLOOKUP($C78,'NAICS-SOC-CIP x-walk'!C:C, 'NAICS-SOC-CIP x-walk'!H:H) -> 21, 22 | J78: =_xlfn.XLOOKUP(K78,'ACS-NAICS-SOC x-walk'!K:K,'ACS-NAICS-SOC x-walk'!L:L) -> Agriculture, Forestry, Fishing and Hunting, and Mining | K78: =_xlfn.XLOOKUP($C78,'NAICS-SOC-CIP x-walk'!$C:$C, 'NAICS-SOC-CIP x-walk'!I:I) -> Mining, Quarrying, and Oil and Gas Extraction, Utilities | L78: =SUMIF(K:K, K78, A:A) -> 5203 | M78: =AVERAGEIF(K:K, K78, A:A) -> 55.946237
A79: 13 | B79: 4 | C79: 13-1051 | D79: =VALUE(LEFT(C79,2)) -> 13 | E79: Cost Estimators | F79: {=_xlfn.IFS( AND(D79>=11, D79<=29), "Management, business, science, and arts occupations", AND(D79>=31, D79<=39), "Service occupations", AND(D79>=41, D79<=43), "Sales and office occupations", AND(D79>=51, D79<=53), "Production, transportation, and material moving occupations", AND(D79>=45, D79<=49), "Natural resources, construction, and maintenance occupations", TRUE, "Not applicable to study area" )} -> Management, business, science, and arts occupations | G79: =SUMIF(F:F, F79, A:A) -> 9764 | H79: =AVERAGEIF(F:F, F79, A:A) -> 21.941573 | I79: =_xlfn.XLOOKUP($C79,'NAICS-SOC-CIP x-walk'!C:C, 'NAICS-SOC-CIP x-walk'!H:H) -> 23 | J79: =_xlfn.XLOOKUP(K79,'ACS-NAICS-SOC x-walk'!K:K,'ACS-NAICS-SOC x-walk'!L:L) -> Construction | K79: =_xlfn.XLOOKUP($C79,'NAICS-SOC-CIP x-walk'!$C:$C, 'NAICS-SOC-CIP x-walk'!I:I) -> Construction | L79: =SUMIF(K:K, K79, A:A) -> 4669 | M79: =AVERAGEIF(K:K, K79, A:A) -> 61.434211
A80: 100 | B80: 1-2 | C80: 47-5011 | D80: =VALUE(LEFT(C80,2)) -> 47 | E80: Derrick Operators, Oil and Gas | F80: {=_xlfn.IFS( AND(D80>=11, D80<=29), "Management, business, science, and arts occupations", AND(D80>=31, D80<=39), "Service occupations", AND(D80>=41, D80<=43), "Sales and office occupations", AND(D80>=51, D80<=53), "Production, transportation, and material moving occupations", AND(D80>=45, D80<=49), "Natural resources, construction, and maintenance occupations", TRUE, "Not applicable to study area" )} -> Natural resources, construction, and maintenance occupations | G80: =SUMIF(F:F, F80, A:A) -> 8738 | H80: =AVERAGEIF(F:F, F80, A:A) -> 71.04065 | I80: =_xlfn.XLOOKUP($C80,'NAICS-SOC-CIP x-walk'!C:C, 'NAICS-SOC-CIP x-walk'!H:H) -> 21, 22 | J80: =_xlfn.XLOOKUP(K80,'ACS-NAICS-SOC x-walk'!K:K,'ACS-NAICS-SOC x-walk'!L:L) -> Agriculture, Forestry, Fishing and Hunting, and Mining | K80: =_xlfn.XLOOKUP($C80,'NAICS-SOC-CIP x-walk'!$C:$C, 'NAICS-SOC-CIP x-walk'!I:I) -> Mining, Quarrying, and Oil and Gas Extraction, Utilities | L80: =SUMIF(K:K, K80, A:A) -> 5203 | M80: =AVERAGEIF(K:K, K80, A:A) -> 55.946237
A81: 100 | B81: 1-2 | C81: 49-9051 | D81: =VALUE(LEFT(C81,2)) -> 49 | E81: Electrical Power-Line Installers and Repairers | F81: {=_xlfn.IFS( AND(D81>=11, D81<=29), "Management, business, science, and arts occupations", AND(D81>=31, D81<=39), "Service occupations", AND(D81>=41, D81<=43), "Sales and office occupations", AND(D81>=51, D81<=53), "Production, transportation, and material moving occupations", AND(D81>=45, D81<=49), "Natural resources, construction, and maintenance occupations", TRUE, "Not applicable to study area" )} -> Natural resources, construction, and maintenance occupations | G81: =SUMIF(F:F, F81, A:A) -> 8738 | H81: =AVERAGEIF(F:F, F81, A:A) -> 71.04065 | I81: =_xlfn.XLOOKUP($C81,'NAICS-SOC-CIP x-walk'!C:C, 'NAICS-SOC-CIP x-walk'!H:H) -> 21, 22 | J81: =_xlfn.XLOOKUP(K81,'ACS-NAICS-SOC x-walk'!K:K,'ACS-NAICS-SOC x-walk'!L:L) -> Agriculture, Forestry, Fishing and Hunting, and Mining | K81: =_xlfn.XLOOKUP($C81,'NAICS-SOC-CIP x-walk'!$C:$C, 'NAICS-SOC-CIP x-walk'!I:I) -> Mining, Quarrying, and Oil and Gas Extraction, Utilities | L81: =SUMIF(K:K, K81, A:A) -> 5203 | M81: =AVERAGEIF(K:K, K81, A:A) -> 55.946237
A82: 100 | B82: 1-2 | C82: 47-5071 | D82: =VALUE(LEFT(C82,2)) -> 47 | E82: Roustabouts, Oil and Gas | F82: {=_xlfn.IFS( AND(D82>=11, D82<=29), "Management, business, science, and arts occupations", AND(D82>=31, D82<=39), "Service occupations", AND(D82>=41, D82<=43), "Sales and office occupations", AND(D82>=51, D82<=53), "Production, transportation, and material moving occupations", AND(D82>=45, D82<=49), "Natural resources, construction, and maintenance occupations", TRUE, "Not applicable to study area" )} -> Natural resources, construction, and maintenance occupations | G82: =SUMIF(F:F, F82, A:A) -> 8738 | H82: =AVERAGEIF(F:F, F82, A:A) -> 71.04065 | I82: =_xlfn.XLOOKUP($C82,'NAICS-SOC-CIP x-walk'!C:C, 'NAICS-SOC-CIP x-walk'!H:H) -> 21, 22 | J82: =_xlfn.XLOOKUP(K82,'ACS-NAICS-SOC x-walk'!K:K,'ACS-NAICS-SOC x-walk'!L:L) -> Agriculture, Forestry, Fishing and Hunting, and Mining | K82: =_xlfn.XLOOKUP($C82,'NAICS-SOC-CIP x-walk'!$C:$C, 'NAICS-SOC-CIP x-walk'!I:I) -> Mining, Quarrying, and Oil and Gas Extraction, Utilities | L82: =SUMIF(K:K, K82, A:A) -> 5203 | M82: =AVERAGEIF(K:K, K82, A:A) -> 55.946237
